Workbook

Sheet Investment Summary
A1: INVESTMENT SUMMARY
A2: One-page dashboard — all figures link live to the model. Placeholder assumptions; replace on the Assumptions tab.
A4: KEY METRICS
A5: Purchase Price | B5: =Assumptions!$B$8 -> 1300000
A6: Price per Pad | B6: =Valuation!B17 -> 16250
A7: Total Pads | B7: =Assumptions!$B$16 -> 80
A8: Occupancy at Close | B8: =Assumptions!$B$17/Assumptions!$B$16 -> 0.75
A9: Stabilized Occupancy | B9: =Assumptions!$B$9 -> 0.92
A10: Going-in Cap Rate | B10: =Valuation!B15 -> 0.065557626
A11: Year-1 NOI | B11: =Valuation!B14 -> 85224.913
A12: Stabilized NOI (Yr 3) | B12: =Valuation!B16 -> 132685.85
A13: Initial Loan | B13: =Acquisition!$B$10 -> 910000
A14: Initial LTV | B14: =Acquisition!B26 -> 0.7
A15: Equity Required | B15: =Acquisition!$B$23 -> 600100
A16: Refi Net Proceeds (Yr 3) | B16: =Refinance!$B$14 -> 616028.14
A17: Exit Value | B17: =Exit!B9 -> 2284928.2
A18: Net Sale Proceeds | B18: =Exit!$B$13 -> 701987.73
A20: RETURNS
A21: Levered IRR | B21: ='Equity Returns'!B16 -> 0.27741656
A22: Equity Multiple | B22: ='Equity Returns'!B17 -> 2.5130314
A23: Avg Cash-on-Cash | B23: ='Equity Returns'!B19 -> 0.069377621
A24: Total Profit | B24: ='Equity Returns'!B18 -> 907970.15
A25: Hold Period (yrs) | B25: =Exit!B6 -> 5
A26: LP IRR / GP IRR | B26: ='LP GP Waterfall'!B23 -> 0.25405811
A27: LP Equity Multiple | B27: ='LP GP Waterfall'!B24 -> 2.3182501
A40: Chart data (annual) | C40: Y1 | D40: Y2 | E40: Y3 | F40: Y4 | G40: Y5 | H40: Y6 | I40: Y7 | J40: Y8 | K40: Y9 | L40: Y10
A41: EGR | C41: =Valuation!C5 -> 330763.07 | D41: =Valuation!D5 -> 377116.46 | E41: =Valuation!E5 -> 392925.24 | F41: =Valuation!F5 -> 404620.2 | G41: =Valuation!G5 -> 416663.7 | H41: =Valuation!H5 -> 429066.12 | I41: =Valuation!I5 -> 441838.18 | J41: =Valuation!J5 -> 454990.9 | ... L41: =Valuation!L5 -> 482484.1
A42: NOI | C42: =Valuation!C7 -> 85224.913 | D42: =Valuation!D7 -> 123535.64 | E42: =Valuation!E7 -> 132685.85 | F42: =Valuation!F7 -> 137781.24 | G42: =Valuation!G7 -> 143057.36 | H42: =Valuation!H7 -> 148520.33 | I42: =Valuation!I7 -> 154176.48 | J42: =Valuation!J7 -> 160032.32 | ... L42: =Valuation!L7 -> 172370.28
A43: Occupancy | C43: =Revenue!C14 -> 0.86333333 | D43: =Revenue!D14 -> 0.92 | E43: =Revenue!E14 -> 0.92 | F43: =Revenue!F14 -> 0.92 | G43: =Revenue!G14 -> 0.92 | H43: =Revenue!H14 -> 0.92 | I43: =Revenue!I14 -> 0.92 | J43: =Revenue!J14 -> 0.92 | ... L43: =Revenue!L14 -> 0.92
A44: Debt Balance | C44: =INDEX('Debt Schedule'!D19:DS19,1,1*12) -> 910000 | D44: =INDEX('Debt Schedule'!D19:DS19,1,2*12) -> 910000 | E44: =INDEX('Debt Schedule'!D19:DS19,1,3*12) -> 1530525.2 | F44: =INDEX('Debt Schedule'!D19:DS19,1,4*12) -> 1511617.4 | G44: =INDEX('Debt Schedule'!D19:DS19,1,5*12) -> 1491543.3 | H44: =INDEX('Debt Schedule'!D19:DS19,1,6*12) -> 1470231.2 | I44: =INDEX('Debt Schedule'!D19:DS19,1,7*12) -> 1447604.6 | J44: =INDEX('Debt Schedule'!D19:DS19,1,8*12) -> 1423582.4 | K44: =INDEX('Debt Schedule'!D19:DS19,1,9*12) -> 1398078.6 | L44: =INDEX('Debt Schedule'!D19:DS19,1,10*12) -> 1371001.7
A46: IRR by exit year | C46: =Exit!I18 -> 0.56074197 | D46: =Exit!I19 -> 0.37852234 | E46: =Exit!I20 -> 0.29094732 | F46: =Exit!I21 -> 0.28458014 | G46: =Exit!I22 -> 0.27741656 | H46: =Exit!I23 -> 0.27033933 | I46: =Exit!I24 -> 0.26369184 | J46: =Exit!I25 -> 0.25758924 | K46: =Exit!I26 -> 0.2520483 | L46: =Exit!I27 -> 0.24243309

Sheet Rent Roll
A1: RENT ROLL
A2: Unit-level detail — seeded to tie to Assumptions; edit per-unit and reconcile on Checks
A4: Lot ID | B4: Unit Type | C4: Status | D4: Current Rent ($/mo) | E4: Market Rent ($/mo) | F4: Rent Growth | G4: Lease Expiration | H4: Potential Rent | I4: Actual Rent | J4: Vacancy Loss | K4: Other Income | L4: Notes
A5: P-001 | B5: POH | C5: Occupied | D5: =IF(C5="Occupied",Assumptions!$B$23,0) -> 350 | E5: =Assumptions!$B$24 -> 425 | F5: =Assumptions!$B$10 -> 0.03 | G5: MTM | H5: =E5 -> 425 | I5: =IF(C5="Occupied",D5,0) -> 350 | J5: =IF(C5="Vacant",E5,0) -> 0 | K5: =IF(C5="Occupied",Assumptions!$B$26,0) -> 20 | L5: POH — home rent extra
A6: P-002 | B6: POH | C6: Occupied | D6: =IF(C6="Occupied",Assumptions!$B$23,0) -> 350 | E6: =Assumptions!$B$24 -> 425 | F6: =Assumptions!$B$10 -> 0.03 | G6: MTM | H6: =E6 -> 425 | I6: =IF(C6="Occupied",D6,0) -> 350 | J6: =IF(C6="Vacant",E6,0) -> 0 | K6: =IF(C6="Occupied",Assumptions!$B$26,0) -> 20 | L6: POH — home rent extra
A7: P-003 | B7: POH | C7: Occupied | D7: =IF(C7="Occupied",Assumptions!$B$23,0) -> 350 | E7: =Assumptions!$B$24 -> 425 | F7: =Assumptions!$B$10 -> 0.03 | G7: MTM | H7: =E7 -> 425 | I7: =IF(C7="Occupied",D7,0) -> 350 | J7: =IF(C7="Vacant",E7,0) -> 0 | K7: =IF(C7="Occupied",Assumptions!$B$26,0) -> 20 | L7: POH — home rent extra
A8: P-004 | B8: POH | C8: Occupied | D8: =IF(C8="Occupied",Assumptions!$B$23,0) -> 350 | E8: =Assumptions!$B$24 -> 425 | F8: =Assumptions!$B$10 -> 0.03 | G8: MTM | H8: =E8 -> 425 | I8: =IF(C8="Occupied",D8,0) -> 350 | J8: =IF(C8="Vacant",E8,0) -> 0 | K8: =IF(C8="Occupied",Assumptions!$B$26,0) -> 20 | L8: POH — home rent extra
A9: P-005 | B9: POH | C9: Occupied | D9: =IF(C9="Occupied",Assumptions!$B$23,0) -> 350 | E9: =Assumptions!$B$24 -> 425 | F9: =Assumptions!$B$10 -> 0.03 | G9: MTM | H9: =E9 -> 425 | I9: =IF(C9="Occupied",D9,0) -> 350 | J9: =IF(C9="Vacant",E9,0) -> 0 | K9: =IF(C9="Occupied",Assumptions!$B$26,0) -> 20 | L9: POH — home rent extra
A10: P-006 | B10: POH | C10: Occupied | D10: =IF(C10="Occupied",Assumptions!$B$23,0) -> 350 | E10: =Assumptions!$B$24 -> 425 | F10: =Assumptions!$B$10 -> 0.03 | G10: MTM | H10: =E10 -> 425 | I10: =IF(C10="Occupied",D10,0) -> 350 | J10: =IF(C10="Vacant",E10,0) -> 0 | K10: =IF(C10="Occupied",Assumptions!$B$26,0) -> 20 | L10: POH — home rent extra
A11: P-007 | B11: POH | C11: Occupied | D11: =IF(C11="Occupied",Assumptions!$B$23,0) -> 350 | E11: =Assumptions!$B$24 -> 425 | F11: =Assumptions!$B$10 -> 0.03 | G11: MTM | H11: =E11 -> 425 | I11: =IF(C11="Occupied",D11,0) -> 350 | J11: =IF(C11="Vacant",E11,0) -> 0 | K11: =IF(C11="Occupied",Assumptions!$B$26,0) -> 20 | L11: POH — home rent extra
A12: P-008 | B12: POH | C12: Occupied | D12: =IF(C12="Occupied",Assumptions!$B$23,0) -> 350 | E12: =Assumptions!$B$24 -> 425 | F12: =Assumptions!$B$10 -> 0.03 | G12: MTM | H12: =E12 -> 425 | I12: =IF(C12="Occupied",D12,0) -> 350 | J12: =IF(C12="Vacant",E12,0) -> 0 | K12: =IF(C12="Occupied",Assumptions!$B$26,0) -> 20 | L12: POH — home rent extra
A13: P-009 | B13: POH | C13: Occupied | D13: =IF(C13="Occupied",Assumptions!$B$23,0) -> 350 | E13: =Assumptions!$B$24 -> 425 | F13: =Assumptions!$B$10 -> 0.03 | G13: MTM | H13: =E13 -> 425 | I13: =IF(C13="Occupied",D13,0) -> 350 | J13: =IF(C13="Vacant",E13,0) -> 0 | K13: =IF(C13="Occupied",Assumptions!$B$26,0) -> 20 | L13: POH — home rent extra
A14: P-010 | B14: POH | C14: Occupied | D14: =IF(C14="Occupied",Assumptions!$B$23,0) -> 350 | E14: =Assumptions!$B$24 -> 425 | F14: =Assumptions!$B$10 -> 0.03 | G14: MTM | H14: =E14 -> 425 | I14: =IF(C14="Occupied",D14,0) -> 350 | J14: =IF(C14="Vacant",E14,0) -> 0 | K14: =IF(C14="Occupied",Assumptions!$B$26,0) -> 20 | L14: POH — home rent extra
A15: P-011 | B15: TOH | C15: Occupied | D15: =IF(C15="Occupied",Assumptions!$B$23,0) -> 350 | E15: =Assumptions!$B$24 -> 425 | F15: =Assumptions!$B$10 -> 0.03 | G15: MTM | H15: =E15 -> 425 | I15: =IF(C15="Occupied",D15,0) -> 350 | J15: =IF(C15="Vacant",E15,0) -> 0 | K15: =IF(C15="Occupied",Assumptions!$B$26,0) -> 20
A16: P-012 | B16: TOH | C16: Occupied | D16: =IF(C16="Occupied",Assumptions!$B$23,0) -> 350 | E16: =Assumptions!$B$24 -> 425 | F16: =Assumptions!$B$10 -> 0.03 | G16: MTM | H16: =E16 -> 425 | I16: =IF(C16="Occupied",D16,0) -> 350 | J16: =IF(C16="Vacant",E16,0) -> 0 | K16: =IF(C16="Occupied",Assumptions!$B$26,0) -> 20
A17: P-013 | B17: TOH | C17: Occupied | D17: =IF(C17="Occupied",Assumptions!$B$23,0) -> 350 | E17: =Assumptions!$B$24 -> 425 | F17: =Assumptions!$B$10 -> 0.03 | G17: MTM | H17: =E17 -> 425 | I17: =IF(C17="Occupied",D17,0) -> 350 | J17: =IF(C17="Vacant",E17,0) -> 0 | K17: =IF(C17="Occupied",Assumptions!$B$26,0) -> 20
A18: P-014 | B18: TOH | C18: Occupied | D18: =IF(C18="Occupied",Assumptions!$B$23,0) -> 350 | E18: =Assumptions!$B$24 -> 425 | F18: =Assumptions!$B$10 -> 0.03 | G18: MTM | H18: =E18 -> 425 | I18: =IF(C18="Occupied",D18,0) -> 350 | J18: =IF(C18="Vacant",E18,0) -> 0 | K18: =IF(C18="Occupied",Assumptions!$B$26,0) -> 20
A19: P-015 | B19: TOH | C19: Occupied | D19: =IF(C19="Occupied",Assumptions!$B$23,0) -> 350 | E19: =Assumptions!$B$24 -> 425 | F19: =Assumptions!$B$10 -> 0.03 | G19: MTM | H19: =E19 -> 425 | I19: =IF(C19="Occupied",D19,0) -> 350 | J19: =IF(C19="Vacant",E19,0) -> 0 | K19: =IF(C19="Occupied",Assumptions!$B$26,0) -> 20
A20: P-016 | B20: TOH | C20: Occupied | D20: =IF(C20="Occupied",Assumptions!$B$23,0) -> 350 | E20: =Assumptions!$B$24 -> 425 | F20: =Assumptions!$B$10 -> 0.03 | G20: MTM | H20: =E20 -> 425 | I20: =IF(C20="Occupied",D20,0) -> 350 | J20: =IF(C20="Vacant",E20,0) -> 0 | K20: =IF(C20="Occupied",Assumptions!$B$26,0) -> 20
A21: P-017 | B21: TOH | C21: Occupied | D21: =IF(C21="Occupied",Assumptions!$B$23,0) -> 350 | E21: =Assumptions!$B$24 -> 425 | F21: =Assumptions!$B$10 -> 0.03 | G21: MTM | H21: =E21 -> 425 | I21: =IF(C21="Occupied",D21,0) -> 350 | J21: =IF(C21="Vacant",E21,0) -> 0 | K21: =IF(C21="Occupied",Assumptions!$B$26,0) -> 20
A22: P-018 | B22: TOH | C22: Occupied | D22: =IF(C22="Occupied",Assumptions!$B$23,0) -> 350 | E22: =Assumptions!$B$24 -> 425 | F22: =Assumptions!$B$10 -> 0.03 | G22: MTM | H22: =E22 -> 425 | I22: =IF(C22="Occupied",D22,0) -> 350 | J22: =IF(C22="Vacant",E22,0) -> 0 | K22: =IF(C22="Occupied",Assumptions!$B$26,0) -> 20
A23: P-019 | B23: TOH | C23: Occupied | D23: =IF(C23="Occupied",Assumptions!$B$23,0) -> 350 | E23: =Assumptions!$B$24 -> 425 | F23: =Assumptions!$B$10 -> 0.03 | G23: MTM | H23: =E23 -> 425 | I23: =IF(C23="Occupied",D23,0) -> 350 | J23: =IF(C23="Vacant",E23,0) -> 0 | K23: =IF(C23="Occupied",Assumptions!$B$26,0) -> 20
A24: P-020 | B24: TOH | C24: Occupied | D24: =IF(C24="Occupied",Assumptions!$B$23,0) -> 350 | E24: =Assumptions!$B$24 -> 425 | F24: =Assumptions!$B$10 -> 0.03 | G24: MTM | H24: =E24 -> 425 | I24: =IF(C24="Occupied",D24,0) -> 350 | J24: =IF(C24="Vacant",E24,0) -> 0 | K24: =IF(C24="Occupied",Assumptions!$B$26,0) -> 20
A25: P-021 | B25: TOH | C25: Occupied | D25: =IF(C25="Occupied",Assumptions!$B$23,0) -> 350 | E25: =Assumptions!$B$24 -> 425 | F25: =Assumptions!$B$10 -> 0.03 | G25: MTM | H25: =E25 -> 425 | I25: =IF(C25="Occupied",D25,0) -> 350 | J25: =IF(C25="Vacant",E25,0) -> 0 | K25: =IF(C25="Occupied",Assumptions!$B$26,0) -> 20
A26: P-022 | B26: TOH | C26: Occupied | D26: =IF(C26="Occupied",Assumptions!$B$23,0) -> 350 | E26: =Assumptions!$B$24 -> 425 | F26: =Assumptions!$B$10 -> 0.03 | G26: MTM | H26: =E26 -> 425 | I26: =IF(C26="Occupied",D26,0) -> 350 | J26: =IF(C26="Vacant",E26,0) -> 0 | K26: =IF(C26="Occupied",Assumptions!$B$26,0) -> 20
... A84: P-080 | B84: TOH | C84: Vacant | D84: =IF(C84="Occupied",Assumptions!$B$23,0) -> 0 | E84: =Assumptions!$B$24 -> 425 | F84: =Assumptions!$B$10 -> 0.03 | G84: MTM | H84: =E84 -> 425 | I84: =IF(C84="Occupied",D84,0) -> 0 | J84: =IF(C84="Vacant",E84,0) -> 425 | K84: =IF(C84="Occupied",Assumptions!$B$26,0) -> 0
A85: TOTALS / SUMMARY | H85: =SUM(H5:H84) -> 34000 | I85: =SUM(I5:I84) -> 21000 | J85: =SUM(J5:J84) -> 8500 | K85: =SUM(K5:K84) -> 1200
A87: Total pads (count) | B87: =COUNTA(A5:A84) -> 80
A88: Occupied pads (count) | B88: =COUNTIF(C5:C84,"Occupied") -> 60
A89: Avg in-place lot rent | B89: =IFERROR(AVERAGEIF(C5:C84,"Occupied",D5:D84),0) -> 350
A90: Monthly potential (market) rent | B90: =H85 -> 34000

Sheet Revenue
A1: REVENUE — ANNUAL
A2: Rolled up from the 120-month engine (green = linked to Monthly Operations)
C4: Year 1 | D4: Year 2 | E4: Year 3 | F4: Year 4 | G4: Year 5 | H4: Year 6 | I4: Year 7 | J4: Year 8 | K4: Year 9 | L4: Year 10
A5: Potential Gross Rent | C5: =SUM('Monthly Operations'!D11:O11) -> 336000 | D5: =SUM('Monthly Operations'!P11:AA11) -> 346080 | E5: =SUM('Monthly Operations'!AB11:AM11) -> 356462.4 | F5: =SUM('Monthly Operations'!AN11:AY11) -> 367156.27 | G5: =SUM('Monthly Operations'!AZ11:BK11) -> 378170.96 | H5: =SUM('Monthly Operations'!BL11:BW11) -> 389516.09 | I5: =SUM('Monthly Operations'!BX11:CI11) -> 401201.57 | J5: =SUM('Monthly Operations'!CJ11:CU11) -> 413237.62 | K5: =SUM('Monthly Operations'!CV11:DG11) -> 425634.75 | L5: =SUM('Monthly Operations'!DH11:DS11) -> 438403.79
A6: Less: Vacancy Loss | C6: =SUM('Monthly Operations'!D12:O12) -> -63373.333 | D6: =SUM('Monthly Operations'!P12:AA12) -> -31772.067 | E6: =SUM('Monthly Operations'!AB12:AM12) -> -28516.992 | F6: =SUM('Monthly Operations'!AN12:AY12) -> -29372.502 | G6: =SUM('Monthly Operations'!AZ12:BK12) -> -30253.677 | H6: =SUM('Monthly Operations'!BL12:BW12) -> -31161.287 | I6: =SUM('Monthly Operations'!BX12:CI12) -> -32096.126 | J6: =SUM('Monthly Operations'!CJ12:CU12) -> -33059.01 | K6: =SUM('Monthly Operations'!CV12:DG12) -> -34050.78 | L6: =SUM('Monthly Operations'!DH12:DS12) -> -35072.303
A7: Less: Collection Loss | C7: =SUM('Monthly Operations'!D13:O13) -> -2726.2667 | D7: =SUM('Monthly Operations'!P13:AA13) -> -3143.0793 | E7: =SUM('Monthly Operations'!AB13:AM13) -> -3279.4541 | F7: =SUM('Monthly Operations'!AN13:AY13) -> -3377.8377 | G7: =SUM('Monthly Operations'!AZ13:BK13) -> -3479.1728 | H7: =SUM('Monthly Operations'!BL13:BW13) -> -3583.548 | I7: =SUM('Monthly Operations'!BX13:CI13) -> -3691.0545 | J7: =SUM('Monthly Operations'!CJ13:CU13) -> -3801.7861 | K7: =SUM('Monthly Operations'!CV13:DG13) -> -3915.8397 | L7: =SUM('Monthly Operations'!DH13:DS13) -> -4033.3149
A8: Effective Gross Rental Revenue | C8: =SUM('Monthly Operations'!D14:O14) -> 269900.4 | D8: =SUM('Monthly Operations'!P14:AA14) -> 311164.85 | E8: =SUM('Monthly Operations'!AB14:AM14) -> 324665.95 | F8: =SUM('Monthly Operations'!AN14:AY14) -> 334405.93 | G8: =SUM('Monthly Operations'!AZ14:BK14) -> 344438.11 | H8: =SUM('Monthly Operations'!BL14:BW14) -> 354771.25 | I8: =SUM('Monthly Operations'!BX14:CI14) -> 365414.39 | J8: =SUM('Monthly Operations'!CJ14:CU14) -> 376376.82 | K8: =SUM('Monthly Operations'!CV14:DG14) -> 387668.13 | L8: =SUM('Monthly Operations'!DH14:DS14) -> 399298.17
A9: POH Home Revenue | C9: =SUM('Monthly Operations'!D15:O15) -> 33600 | D9: =SUM('Monthly Operations'!P15:AA15) -> 34608 | E9: =SUM('Monthly Operations'!AB15:AM15) -> 35646.24 | F9: =SUM('Monthly Operations'!AN15:AY15) -> 36715.627 | G9: =SUM('Monthly Operations'!AZ15:BK15) -> 37817.096 | H9: =SUM('Monthly Operations'!BL15:BW15) -> 38951.609 | I9: =SUM('Monthly Operations'!BX15:CI15) -> 40120.157 | J9: =SUM('Monthly Operations'!CJ15:CU15) -> 41323.762 | K9: =SUM('Monthly Operations'!CV15:DG15) -> 42563.475 | L9: =SUM('Monthly Operations'!DH15:DS15) -> 43840.379
A10: Other Income | C10: =SUM('Monthly Operations'!D16:O16) -> 15578.667 | D10: =SUM('Monthly Operations'!P16:AA16) -> 17873.267 | E10: =SUM('Monthly Operations'!AB16:AM16) -> 18558.24 | F10: =SUM('Monthly Operations'!AN16:AY16) -> 19022.196 | G10: =SUM('Monthly Operations'!AZ16:BK16) -> 19497.751 | H10: =SUM('Monthly Operations'!BL16:BW16) -> 19985.195 | I10: =SUM('Monthly Operations'!BX16:CI16) -> 20484.825 | J10: =SUM('Monthly Operations'!CJ16:CU16) -> 20996.945 | K10: =SUM('Monthly Operations'!CV16:DG16) -> 21521.869 | L10: =SUM('Monthly Operations'!DH16:DS16) -> 22059.916
A11: Utility Reimbursement | C11: =SUM('Monthly Operations'!D17:O17) -> 11684 | D11: =SUM('Monthly Operations'!P17:AA17) -> 13470.34 | E11: =SUM('Monthly Operations'!AB17:AM17) -> 14054.803 | F11: =SUM('Monthly Operations'!AN17:AY17) -> 14476.447 | G11: =SUM('Monthly Operations'!AZ17:BK17) -> 14910.741 | H11: =SUM('Monthly Operations'!BL17:BW17) -> 15358.063 | I11: =SUM('Monthly Operations'!BX17:CI17) -> 15818.805 | J11: =SUM('Monthly Operations'!CJ17:CU17) -> 16293.369 | K11: =SUM('Monthly Operations'!CV17:DG17) -> 16782.17 | L11: =SUM('Monthly Operations'!DH17:DS17) -> 17285.635
A12: EFFECTIVE GROSS REVENUE | C12: =SUM('Monthly Operations'!D18:O18) -> 330763.07 | D12: =SUM('Monthly Operations'!P18:AA18) -> 377116.46 | E12: =SUM('Monthly Operations'!AB18:AM18) -> 392925.24 | F12: =SUM('Monthly Operations'!AN18:AY18) -> 404620.2 | G12: =SUM('Monthly Operations'!AZ18:BK18) -> 416663.7 | H12: =SUM('Monthly Operations'!BL18:BW18) -> 429066.12 | I12: =SUM('Monthly Operations'!BX18:CI18) -> 441838.18 | J12: =SUM('Monthly Operations'!CJ18:CU18) -> 454990.9 | K12: =SUM('Monthly Operations'!CV18:DG18) -> 468535.64 | L12: =SUM('Monthly Operations'!DH18:DS18) -> 482484.1
A14: Occupancy % (avg, Yr-end) | C14: ='Monthly Operations'!O9 -> 0.86333333 | D14: ='Monthly Operations'!AA9 -> 0.92 | E14: ='Monthly Operations'!AM9 -> 0.92 | F14: ='Monthly Operations'!AY9 -> 0.92 | G14: ='Monthly Operations'!BK9 -> 0.92 | H14: ='Monthly Operations'!BW9 -> 0.92 | I14: ='Monthly Operations'!CI9 -> 0.92 | J14: ='Monthly Operations'!CU9 -> 0.92 | K14: ='Monthly Operations'!DG9 -> 0.92 | L14: ='Monthly Operations'!DS9 -> 0.92

Sheet Operating Expenses
A1: OPERATING EXPENSES — ANNUAL
A2: Fixed lines escalate at expense growth; management fee floats with revenue
C4: Year 1 | D4: Year 2 | E4: Year 3 | F4: Year 4 | G4: Year 5 | H4: Year 6 | I4: Year 7 | J4: Year 8 | K4: Year 9 | L4: Year 10
A5: Property Taxes | C5: =SUM('Monthly Operations'!D20:O20) -> -45000 | D5: =SUM('Monthly Operations'!P20:AA20) -> -46125 | E5: =SUM('Monthly Operations'!AB20:AM20) -> -47278.125 | F5: =SUM('Monthly Operations'!AN20:AY20) -> -48460.078 | G5: =SUM('Monthly Operations'!AZ20:BK20) -> -49671.58 | H5: =SUM('Monthly Operations'!BL20:BW20) -> -50913.37 | I5: =SUM('Monthly Operations'!BX20:CI20) -> -52186.204 | J5: =SUM('Monthly Operations'!CJ20:CU20) -> -53490.859 | K5: =SUM('Monthly Operations'!CV20:DG20) -> -54828.13 | L5: =SUM('Monthly Operations'!DH20:DS20) -> -56198.834
A6: Insurance | C6: =SUM('Monthly Operations'!D21:O21) -> -20000 | D6: =SUM('Monthly Operations'!P21:AA21) -> -20500 | E6: =SUM('Monthly Operations'!AB21:AM21) -> -21012.5 | F6: =SUM('Monthly Operations'!AN21:AY21) -> -21537.812 | G6: =SUM('Monthly Operations'!AZ21:BK21) -> -22076.258 | H6: =SUM('Monthly Operations'!BL21:BW21) -> -22628.164 | I6: =SUM('Monthly Operations'!BX21:CI21) -> -23193.868 | J6: =SUM('Monthly Operations'!CJ21:CU21) -> -23773.715 | K6: =SUM('Monthly Operations'!CV21:DG21) -> -24368.058 | L6: =SUM('Monthly Operations'!DH21:DS21) -> -24977.259
A7: Electricity | C7: =SUM('Monthly Operations'!D22:O22) -> -12000 | D7: =SUM('Monthly Operations'!P22:AA22) -> -12300 | E7: =SUM('Monthly Operations'!AB22:AM22) -> -12607.5 | F7: =SUM('Monthly Operations'!AN22:AY22) -> -12922.687 | G7: =SUM('Monthly Operations'!AZ22:BK22) -> -13245.755 | H7: =SUM('Monthly Operations'!BL22:BW22) -> -13576.899 | I7: =SUM('Monthly Operations'!BX22:CI22) -> -13916.321 | J7: =SUM('Monthly Operations'!CJ22:CU22) -> -14264.229 | K7: =SUM('Monthly Operations'!CV22:DG22) -> -14620.835 | L7: =SUM('Monthly Operations'!DH22:DS22) -> -14986.356
A8: Gas | C8: =SUM('Monthly Operations'!D23:O23) -> -3000 | D8: =SUM('Monthly Operations'!P23:AA23) -> -3075 | E8: =SUM('Monthly Operations'!AB23:AM23) -> -3151.875 | F8: =SUM('Monthly Operations'!AN23:AY23) -> -3230.6719 | G8: =SUM('Monthly Operations'!AZ23:BK23) -> -3311.4387 | H8: =SUM('Monthly Operations'!BL23:BW23) -> -3394.2246 | I8: =SUM('Monthly Operations'!BX23:CI23) -> -3479.0803 | J8: =SUM('Monthly Operations'!CJ23:CU23) -> -3566.0573 | K8: =SUM('Monthly Operations'!CV23:DG23) -> -3655.2087 | L8: =SUM('Monthly Operations'!DH23:DS23) -> -3746.5889
A9: Water | C9: =SUM('Monthly Operations'!D24:O24) -> -30000 | D9: =SUM('Monthly Operations'!P24:AA24) -> -30750 | E9: =SUM('Monthly Operations'!AB24:AM24) -> -31518.75 | F9: =SUM('Monthly Operations'!AN24:AY24) -> -32306.719 | G9: =SUM('Monthly Operations'!AZ24:BK24) -> -33114.387 | H9: =SUM('Monthly Operations'!BL24:BW24) -> -33942.246 | I9: =SUM('Monthly Operations'!BX24:CI24) -> -34790.803 | J9: =SUM('Monthly Operations'!CJ24:CU24) -> -35660.573 | K9: =SUM('Monthly Operations'!CV24:DG24) -> -36552.087 | L9: =SUM('Monthly Operations'!DH24:DS24) -> -37465.889
A10: Sewer | C10: =SUM('Monthly Operations'!D25:O25) -> -25000 | D10: =SUM('Monthly Operations'!P25:AA25) -> -25625 | E10: =SUM('Monthly Operations'!AB25:AM25) -> -26265.625 | F10: =SUM('Monthly Operations'!AN25:AY25) -> -26922.266 | G10: =SUM('Monthly Operations'!AZ25:BK25) -> -27595.322 | H10: =SUM('Monthly Operations'!BL25:BW25) -> -28285.205 | I10: =SUM('Monthly Operations'!BX25:CI25) -> -28992.335 | J10: =SUM('Monthly Operations'!CJ25:CU25) -> -29717.144 | K10: =SUM('Monthly Operations'!CV25:DG25) -> -30460.072 | L10: =SUM('Monthly Operations'!DH25:DS25) -> -31221.574
A11: Repairs & Maintenance | C11: =SUM('Monthly Operations'!D26:O26) -> -35000 | D11: =SUM('Monthly Operations'!P26:AA26) -> -35875 | E11: =SUM('Monthly Operations'!AB26:AM26) -> -36771.875 | F11: =SUM('Monthly Operations'!AN26:AY26) -> -37691.172 | G11: =SUM('Monthly Operations'!AZ26:BK26) -> -38633.451 | H11: =SUM('Monthly Operations'!BL26:BW26) -> -39599.287 | I11: =SUM('Monthly Operations'!BX26:CI26) -> -40589.27 | J11: =SUM('Monthly Operations'!CJ26:CU26) -> -41604.001 | K11: =SUM('Monthly Operations'!CV26:DG26) -> -42644.101 | L11: =SUM('Monthly Operations'!DH26:DS26) -> -43710.204
A12: POH Insurance | C12: =SUM('Monthly Operations'!D27:O27) -> -4000 | D12: =SUM('Monthly Operations'!P27:AA27) -> -4100 | E12: =SUM('Monthly Operations'!AB27:AM27) -> -4202.5 | F12: =SUM('Monthly Operations'!AN27:AY27) -> -4307.5625 | G12: =SUM('Monthly Operations'!AZ27:BK27) -> -4415.2516 | H12: =SUM('Monthly Operations'!BL27:BW27) -> -4525.6329 | I12: =SUM('Monthly Operations'!BX27:CI27) -> -4638.7737 | J12: =SUM('Monthly Operations'!CJ27:CU27) -> -4754.743 | K12: =SUM('Monthly Operations'!CV27:DG27) -> -4873.6116 | L12: =SUM('Monthly Operations'!DH27:DS27) -> -4995.4519
A13: POH Repairs | C13: =SUM('Monthly Operations'!D28:O28) -> -8000 | D13: =SUM('Monthly Operations'!P28:AA28) -> -8200 | E13: =SUM('Monthly Operations'!AB28:AM28) -> -8405 | F13: =SUM('Monthly Operations'!AN28:AY28) -> -8615.125 | G13: =SUM('Monthly Operations'!AZ28:BK28) -> -8830.5031 | H13: =SUM('Monthly Operations'!BL28:BW28) -> -9051.2657 | I13: =SUM('Monthly Operations'!BX28:CI28) -> -9277.5473 | J13: =SUM('Monthly Operations'!CJ28:CU28) -> -9509.486 | K13: =SUM('Monthly Operations'!CV28:DG28) -> -9747.2232 | L13: =SUM('Monthly Operations'!DH28:DS28) -> -9990.9038
A14: Turnover / Make-ready | C14: =SUM('Monthly Operations'!D29:O29) -> -6000 | D14: =SUM('Monthly Operations'!P29:AA29) -> -6150 | E14: =SUM('Monthly Operations'!AB29:AM29) -> -6303.75 | F14: =SUM('Monthly Operations'!AN29:AY29) -> -6461.3437 | G14: =SUM('Monthly Operations'!AZ29:BK29) -> -6622.8773 | H14: =SUM('Monthly Operations'!BL29:BW29) -> -6788.4493 | I14: =SUM('Monthly Operations'!BX29:CI29) -> -6958.1605 | J14: =SUM('Monthly Operations'!CJ29:CU29) -> -7132.1145 | K14: =SUM('Monthly Operations'!CV29:DG29) -> -7310.4174 | L14: =SUM('Monthly Operations'!DH29:DS29) -> -7493.1778
A15: Administrative | C15: =SUM('Monthly Operations'!D30:O30) -> -10000 | D15: =SUM('Monthly Operations'!P30:AA30) -> -10250 | E15: =SUM('Monthly Operations'!AB30:AM30) -> -10506.25 | F15: =SUM('Monthly Operations'!AN30:AY30) -> -10768.906 | G15: =SUM('Monthly Operations'!AZ30:BK30) -> -11038.129 | H15: =SUM('Monthly Operations'!BL30:BW30) -> -11314.082 | I15: =SUM('Monthly Operations'!BX30:CI30) -> -11596.934 | J15: =SUM('Monthly Operations'!CJ30:CU30) -> -11886.858 | K15: =SUM('Monthly Operations'!CV30:DG30) -> -12184.029 | L15: =SUM('Monthly Operations'!DH30:DS30) -> -12488.63
A16: Legal / Professional | C16: =SUM('Monthly Operations'!D31:O31) -> -5000 | D16: =SUM('Monthly Operations'!P31:AA31) -> -5125 | E16: =SUM('Monthly Operations'!AB31:AM31) -> -5253.125 | F16: =SUM('Monthly Operations'!AN31:AY31) -> -5384.4531 | G16: =SUM('Monthly Operations'!AZ31:BK31) -> -5519.0645 | H16: =SUM('Monthly Operations'!BL31:BW31) -> -5657.0411 | I16: =SUM('Monthly Operations'!BX31:CI31) -> -5798.4671 | J16: =SUM('Monthly Operations'!CJ31:CU31) -> -5943.4288 | K16: =SUM('Monthly Operations'!CV31:DG31) -> -6092.0145 | L16: =SUM('Monthly Operations'!DH31:DS31) -> -6244.3148
... A21: TOTAL OPERATING EXPENSES | C21: =SUM('Monthly Operations'!D36:O36) -> -245538.15 | D21: =SUM('Monthly Operations'!P36:AA36) -> -253580.82 | E21: =SUM('Monthly Operations'!AB36:AM36) -> -260239.39 | F21: =SUM('Monthly Operations'!AN36:AY36) -> -266838.96 | G21: =SUM('Monthly Operations'!AZ36:BK36) -> -273606.34 | H21: =SUM('Monthly Operations'!BL36:BW36) -> -280545.79 | I21: =SUM('Monthly Operations'!BX36:CI36) -> -287661.7 | J21: =SUM('Monthly Operations'!CJ36:CU36) -> -294958.58 | K21: =SUM('Monthly Operations'!CV36:DG36) -> -302441.05 | L21: =SUM('Monthly Operations'!DH36:DS36) -> -310113.83
A23: Expense Ratio (% of EGR) | C23: =IFERROR(-C21/Revenue!C12,0) -> 0.74233848 | D23: =IFERROR(-D21/Revenue!D12,0) -> 0.67242046 | E23: =IFERROR(-E21/Revenue!E12,0) -> 0.66231273 | F23: =IFERROR(-F21/Revenue!F12,0) -> 0.65948008 | G23: =IFERROR(-G21/Revenue!G12,0) -> 0.65665989 | H23: =IFERROR(-H21/Revenue!H12,0) -> 0.65385211 | I23: =IFERROR(-I21/Revenue!I12,0) -> 0.65105669 | J23: =IFERROR(-J21/Revenue!J12,0) -> 0.64827359 | ... L23: =IFERROR(-L21/Revenue!L12,0) -> 0.64274413

Sheet CapEx
A1: CAPITAL EXPENDITURES
A2: One-time infrastructure funded at close (Uses); ongoing replacement reserves run through NOI-after-CapEx
A4: Initial / One-time CapEx (funded at acquisition)
A5: Roads | B5: =Assumptions!$B$50 -> 40000
A6: Water/Sewer Infrastructure | B6: =Assumptions!$B$51 -> 60000
A7: Electrical | B7: =Assumptions!$B$52 -> 20000
A8: Common-Area Improvements | B8: =Assumptions!$B$53 -> 15000
A9: POH Renovations | B9: =Assumptions!$B$54 -> 30000
A10: Other CapEx | B10: =Assumptions!$B$55 -> 10000
A11: Total Initial CapEx | B11: =Assumptions!$B$56 -> 175000
A13: Ongoing Replacement Reserves (annual)
C14: Year 1 | D14: Year 2 | E14: Year 3 | F14: Year 4 | G14: Year 5 | H14: Year 6 | I14: Year 7 | J14: Year 8 | K14: Year 9 | L14: Year 10
A15: Replacement Reserves | C15: =SUM('Monthly Operations'!D41:O41) -> -4000 | D15: =SUM('Monthly Operations'!P41:AA41) -> -4100 | E15: =SUM('Monthly Operations'!AB41:AM41) -> -4202.5 | F15: =SUM('Monthly Operations'!AN41:AY41) -> -4307.5625 | G15: =SUM('Monthly Operations'!AZ41:BK41) -> -4415.2516 | H15: =SUM('Monthly Operations'!BL41:BW41) -> -4525.6329 | I15: =SUM('Monthly Operations'!BX41:CI41) -> -4638.7737 | J15: =SUM('Monthly Operations'!CJ41:CU41) -> -4754.743 | K15: =SUM('Monthly Operations'!CV41:DG41) -> -4873.6116 | L15: =SUM('Monthly Operations'!DH41:DS41) -> -4995.4519

Sheet Monthly Operations
A1: MONTHLY OPERATING MODEL
A2: 120-month engine — all revenue, expenses, NOI & CapEx. Annual sheets roll these up.
D3: =CEILING(D4/12,1) -> 1 | E3: =ROUNDUP(D4/12,0) -> 1 | F3: all3 formula canbe used
A4: Month # | D4: 1 | E4: 2 | F4: 3 | G4: 4 | H4: 5 | I4: 6 | J4: 7 | K4: 8 | L4: 9 | M4: 10 | N4: 11 | O4: 12 | P4: 13 | Q4: 14 | R4: 15 | S4: 16 | T4: 17 | U4: 18 | V4: 19 | W4: 20 | X4: 21 | Y4: 22 | Z4: 23 | AA4: 24 | AB4: 25 | AC4: 26 | AD4: 27 | AE4: 28 | AF4: 29 | AG4: 30 | AH4: 31 | AI4: 32 | AJ4: 33 | AK4: 34 | AL4: 35 | AM4: 36 | AN4: 37 | AO4: 38 | AP4: 39 | AQ4: 40 | AR4: 41 | AS4: 42 | AT4: 43 | AU4: 44 | AV4: 45 | AW4: 46 | AX4: 47 | AY4: 48 | AZ4: 49 | BA4: 50 | BB4: 51 | BC4: 52 | BD4: 53 | BE4: 54 | BF4: 55 | BG4: 56 | BH4: 57 | BI4: 58 | BJ4: 59 | BK4: 60 | BL4: 61 | BM4: 62 | BN4: 63 | BO4: 64 | BP4: 65 | BQ4: 66 | BR4: 67 | BS4: 68 | BT4: 69 | BU4: 70 | BV4: 71 | BW4: 72 | BX4: 73 | BY4: 74 | BZ4: 75 | CA4: 76 | CB4: 77 | CC4: 78 | CD4: 79 | CE4: 80 | CF4: 81 | CG4: 82 | CH4: 83 | CI4: 84 | CJ4: 85 | CK4: 86 | CL4: 87 | CM4: 88 | CN4: 89 | CO4: 90 | CP4: 91 | CQ4: 92 | CR4: 93 | CS4: 94 | CT4: 95 | CU4: 96 | CV4: 97 | CW4: 98 | CX4: 99 | CY4: 100 | CZ4: 101 | DA4: 102 | DB4: 103 | DC4: 104 | DD4: 105 | DE4: 106 | DF4: 107 | DG4: 108 | DH4: 109 | DI4: 110 | DJ4: 111 | DK4: 112 | DL4: 113 | DM4: 114 | DN4: 115 | DO4: 116 | DP4: 117 | DQ4: 118 | DR4: 119 | DS4: 120
A5: Year | D5: =INT((D4-1)/12)+1 -> 1 | E5: =INT((E4-1)/12)+1 -> 1 | F5: =INT((F4-1)/12)+1 -> 1 | G5: =INT((G4-1)/12)+1 -> 1 | H5: =INT((H4-1)/12)+1 -> 1 | I5: =INT((I4-1)/12)+1 -> 1 | J5: =INT((J4-1)/12)+1 -> 1 | K5: =INT((K4-1)/12)+1 -> 1 | ... DS5: =INT((DS4-1)/12)+1 -> 10
A6: Period | D6: =EDATE(Assumptions!$B$15,D4-1) -> 46023 | E6: =EDATE(Assumptions!$B$15,E4-1) -> 46054 | F6: =EDATE(Assumptions!$B$15,F4-1) -> 46082 | G6: =EDATE(Assumptions!$B$15,G4-1) -> 46113 | H6: =EDATE(Assumptions!$B$15,H4-1) -> 46143 | I6: =EDATE(Assumptions!$B$15,I4-1) -> 46174 | J6: =EDATE(Assumptions!$B$15,J4-1) -> 46204 | K6: =EDATE(Assumptions!$B$15,K4-1) -> 46235 | ... DS6: =EDATE(Assumptions!$B$15,DS4-1) -> 49644
A8: Occupied Pads | D8: =MIN(Assumptions!$B$9*Assumptions!$B$16,Assumptions!$B$17+(Assumptions!$B$9*Assumptions!$B$16-Assumptions!$B$17)*MIN(D4,Assumptions!$B$29)/Assumptions!$B$29) -> 60.755556 | E8: =MIN(Assumptions!$B$9*Assumptions!$B$16,Assumptions!$B$17+(Assumptions!$B$9*Assumptions!$B$16-Assumptions!$B$17)*MIN(E4,Assumptions!$B$29)/Assumptions!$B$29) -> 61.511111 | F8: =MIN(Assumptions!$B$9*Assumptions!$B$16,Assumptions!$B$17+(Assumptions!$B$9*Assumptions!$B$16-Assumptions!$B$17)*MIN(F4,Assumptions!$B$29)/Assumptions!$B$29) -> 62.266667 | G8: =MIN(Assumptions!$B$9*Assumptions!$B$16,Assumptions!$B$17+(Assumptions!$B$9*Assumptions!$B$16-Assumptions!$B$17)*MIN(G4,Assumptions!$B$29)/Assumptions!$B$29) -> 63.022222 | H8: =MIN(Assumptions!$B$9*Assumptions!$B$16,Assumptions!$B$17+(Assumptions!$B$9*Assumptions!$B$16-Assumptions!$B$17)*MIN(H4,Assumptions!$B$29)/Assumptions!$B$29) -> 63.777778 | I8: =MIN(Assumptions!$B$9*Assumptions!$B$16,Assumptions!$B$17+(Assumptions!$B$9*Assumptions!$B$16-Assumptions!$B$17)*MIN(I4,Assumptions!$B$29)/Assumptions!$B$29) -> 64.533333 | J8: =MIN(Assumptions!$B$9*Assumptions!$B$16,Assumptions!$B$17+(Assumptions!$B$9*Assumptions!$B$16-Assumptions!$B$17)*MIN(J4,Assumptions!$B$29)/Assumptions!$B$29) -> 65.288889 | K8: =MIN(Assumptions!$B$9*Assumptions!$B$16,Assumptions!$B$17+(Assumptions!$B$9*Assumptions!$B$16-Assumptions!$B$17)*MIN(K4,Assumptions!$B$29)/Assumptions!$B$29) -> 66.044444 | ... DS8: =MIN(Assumptions!$B$9*Assumptions!$B$16,Assumptions!$B$17+(Assumptions!$B$9*Assumptions!$B$16-Assumptions!$B$17)*MIN(DS4,Assumptions!$B$29)/Assumptions!$B$29) -> 73.6
A9: Occupancy % | D9: =D8/Assumptions!$B$16 -> 0.75944444 | E9: =E8/Assumptions!$B$16 -> 0.76888889 | F9: =F8/Assumptions!$B$16 -> 0.77833333 | G9: =G8/Assumptions!$B$16 -> 0.78777778 | H9: =H8/Assumptions!$B$16 -> 0.79722222 | I9: =I8/Assumptions!$B$16 -> 0.80666667 | J9: =J8/Assumptions!$B$16 -> 0.81611111 | K9: =K8/Assumptions!$B$16 -> 0.82555556 | ... DS9: =DS8/Assumptions!$B$16 -> 0.92
A10: Lot Rent / Pad | D10: =Assumptions!$B$23*(1+Assumptions!$B$10)^(D5-1) -> 350 | E10: =Assumptions!$B$23*(1+Assumptions!$B$10)^(E5-1) -> 350 | F10: =Assumptions!$B$23*(1+Assumptions!$B$10)^(F5-1) -> 350 | G10: =Assumptions!$B$23*(1+Assumptions!$B$10)^(G5-1) -> 350 | H10: =Assumptions!$B$23*(1+Assumptions!$B$10)^(H5-1) -> 350 | I10: =Assumptions!$B$23*(1+Assumptions!$B$10)^(I5-1) -> 350 | J10: =Assumptions!$B$23*(1+Assumptions!$B$10)^(J5-1) -> 350 | K10: =Assumptions!$B$23*(1+Assumptions!$B$10)^(K5-1) -> 350 | ... DS10: =Assumptions!$B$23*(1+Assumptions!$B$10)^(DS5-1) -> 456.67061
A11: Potential Gross Rent | D11: =Assumptions!$B$16*D10 -> 28000 | E11: =Assumptions!$B$16*E10 -> 28000 | F11: =Assumptions!$B$16*F10 -> 28000 | G11: =Assumptions!$B$16*G10 -> 28000 | H11: =Assumptions!$B$16*H10 -> 28000 | I11: =Assumptions!$B$16*I10 -> 28000 | J11: =Assumptions!$B$16*J10 -> 28000 | K11: =Assumptions!$B$16*K10 -> 28000 | ... DS11: =Assumptions!$B$16*DS10 -> 36533.649
A12: Less: Vacancy Loss | D12: =-(Assumptions!$B$16-D8)*D10 -> -6735.5556 | E12: =-(Assumptions!$B$16-E8)*E10 -> -6471.1111 | F12: =-(Assumptions!$B$16-F8)*F10 -> -6206.6667 | G12: =-(Assumptions!$B$16-G8)*G10 -> -5942.2222 | H12: =-(Assumptions!$B$16-H8)*H10 -> -5677.7778 | I12: =-(Assumptions!$B$16-I8)*I10 -> -5413.3333 | J12: =-(Assumptions!$B$16-J8)*J10 -> -5148.8889 | K12: =-(Assumptions!$B$16-K8)*K10 -> -4884.4444 | ... DS12: =-(Assumptions!$B$16-DS8)*DS10 -> -2922.6919
A13: Less: Collection Loss | D13: =-Assumptions!$B$28*(D11+D12) -> -212.64444 | E13: =-Assumptions!$B$28*(E11+E12) -> -215.28889 | F13: =-Assumptions!$B$28*(F11+F12) -> -217.93333 | G13: =-Assumptions!$B$28*(G11+G12) -> -220.57778 | H13: =-Assumptions!$B$28*(H11+H12) -> -223.22222 | I13: =-Assumptions!$B$28*(I11+I12) -> -225.86667 | J13: =-Assumptions!$B$28*(J11+J12) -> -228.51111 | K13: =-Assumptions!$B$28*(K11+K12) -> -231.15556 | ... DS13: =-Assumptions!$B$28*(DS11+DS12) -> -336.10957
A14: Effective Gross Rental Rev | D14: =D11+D12+D13 -> 21051.8 | E14: =E11+E12+E13 -> 21313.6 | F14: =F11+F12+F13 -> 21575.4 | G14: =G11+G12+G13 -> 21837.2 | H14: =H11+H12+H13 -> 22099 | I14: =I11+I12+I13 -> 22360.8 | J14: =J11+J12+J13 -> 22622.6 | K14: =K11+K12+K13 -> 22884.4 | ... DS14: =DS11+DS12+DS13 -> 33274.848
A15: POH Home Revenue | D15: =Assumptions!$B$20*Assumptions!$B$25*(1+Assumptions!$B$10)^(D5-1) -> 2800 | E15: =Assumptions!$B$20*Assumptions!$B$25*(1+Assumptions!$B$10)^(E5-1) -> 2800 | F15: =Assumptions!$B$20*Assumptions!$B$25*(1+Assumptions!$B$10)^(F5-1) -> 2800 | G15: =Assumptions!$B$20*Assumptions!$B$25*(1+Assumptions!$B$10)^(G5-1) -> 2800 | H15: =Assumptions!$B$20*Assumptions!$B$25*(1+Assumptions!$B$10)^(H5-1) -> 2800 | I15: =Assumptions!$B$20*Assumptions!$B$25*(1+Assumptions!$B$10)^(I5-1) -> 2800 | J15: =Assumptions!$B$20*Assumptions!$B$25*(1+Assumptions!$B$10)^(J5-1) -> 2800 | K15: =Assumptions!$B$20*Assumptions!$B$25*(1+Assumptions!$B$10)^(K5-1) -> 2800 | ... DS15: =Assumptions!$B$20*Assumptions!$B$25*(1+Assumptions!$B$10)^(DS5-1) -> 3653.3649
A16: Other Income | D16: =D8*Assumptions!$B$26*(1+Assumptions!$B$30)^(D5-1) -> 1215.1111 | E16: =E8*Assumptions!$B$26*(1+Assumptions!$B$30)^(E5-1) -> 1230.2222 | F16: =F8*Assumptions!$B$26*(1+Assumptions!$B$30)^(F5-1) -> 1245.3333 | G16: =G8*Assumptions!$B$26*(1+Assumptions!$B$30)^(G5-1) -> 1260.4444 | H16: =H8*Assumptions!$B$26*(1+Assumptions!$B$30)^(H5-1) -> 1275.5556 | I16: =I8*Assumptions!$B$26*(1+Assumptions!$B$30)^(I5-1) -> 1290.6667 | J16: =J8*Assumptions!$B$26*(1+Assumptions!$B$30)^(J5-1) -> 1305.7778 | K16: =K8*Assumptions!$B$26*(1+Assumptions!$B$30)^(K5-1) -> 1320.8889 | ... DS16: =DS8*Assumptions!$B$26*(1+Assumptions!$B$30)^(DS5-1) -> 1838.3263
A17: Utility Reimbursement | D17: =D8*Assumptions!$B$27*(1+Assumptions!$B$10)^(D5-1) -> 911.33333 | E17: =E8*Assumptions!$B$27*(1+Assumptions!$B$10)^(E5-1) -> 922.66667 | F17: =F8*Assumptions!$B$27*(1+Assumptions!$B$10)^(F5-1) -> 934 | G17: =G8*Assumptions!$B$27*(1+Assumptions!$B$10)^(G5-1) -> 945.33333 | H17: =H8*Assumptions!$B$27*(1+Assumptions!$B$10)^(H5-1) -> 956.66667 | I17: =I8*Assumptions!$B$27*(1+Assumptions!$B$10)^(I5-1) -> 968 | J17: =J8*Assumptions!$B$27*(1+Assumptions!$B$10)^(J5-1) -> 979.33333 | K17: =K8*Assumptions!$B$27*(1+Assumptions!$B$10)^(K5-1) -> 990.66667 | ... DS17: =DS8*Assumptions!$B$27*(1+Assumptions!$B$10)^(DS5-1) -> 1440.4696
A18: EFFECTIVE GROSS REVENUE | D18: =SUM(D14:D17) -> 25978.244 | E18: =SUM(E14:E17) -> 26266.489 | F18: =SUM(F14:F17) -> 26554.733 | G18: =SUM(G14:G17) -> 26842.978 | H18: =SUM(H14:H17) -> 27131.222 | I18: =SUM(I14:I17) -> 27419.467 | J18: =SUM(J14:J17) -> 27707.711 | K18: =SUM(K14:K17) -> 27995.956 | ... DS18: =SUM(DS14:DS17) -> 40207.008
A19: OPERATING EXPENSES
A20: Property Taxes | D20: =-Assumptions!$B$32/12*(1+Assumptions!$B$11)^(D5-1) -> -3750 | E20: =-Assumptions!$B$32/12*(1+Assumptions!$B$11)^(E5-1) -> -3750 | F20: =-Assumptions!$B$32/12*(1+Assumptions!$B$11)^(F5-1) -> -3750 | G20: =-Assumptions!$B$32/12*(1+Assumptions!$B$11)^(G5-1) -> -3750 | H20: =-Assumptions!$B$32/12*(1+Assumptions!$B$11)^(H5-1) -> -3750 | I20: =-Assumptions!$B$32/12*(1+Assumptions!$B$11)^(I5-1) -> -3750 | J20: =-Assumptions!$B$32/12*(1+Assumptions!$B$11)^(J5-1) -> -3750 | K20: =-Assumptions!$B$32/12*(1+Assumptions!$B$11)^(K5-1) -> -3750 | ... DS20: =-Assumptions!$B$32/12*(1+Assumptions!$B$11)^(DS5-1) -> -4683.2361
A21: Insurance | D21: =-Assumptions!$B$33/12*(1+Assumptions!$B$11)^(D5-1) -> -1666.6667 | E21: =-Assumptions!$B$33/12*(1+Assumptions!$B$11)^(E5-1) -> -1666.6667 | F21: =-Assumptions!$B$33/12*(1+Assumptions!$B$11)^(F5-1) -> -1666.6667 | G21: =-Assumptions!$B$33/12*(1+Assumptions!$B$11)^(G5-1) -> -1666.6667 | H21: =-Assumptions!$B$33/12*(1+Assumptions!$B$11)^(H5-1) -> -1666.6667 | I21: =-Assumptions!$B$33/12*(1+Assumptions!$B$11)^(I5-1) -> -1666.6667 | J21: =-Assumptions!$B$33/12*(1+Assumptions!$B$11)^(J5-1) -> -1666.6667 | K21: =-Assumptions!$B$33/12*(1+Assumptions!$B$11)^(K5-1) -> -1666.6667 | ... DS21: =-Assumptions!$B$33/12*(1+Assumptions!$B$11)^(DS5-1) -> -2081.4383
A22: Electricity | D22: =-Assumptions!$B$34/12*(1+Assumptions!$B$11)^(D5-1) -> -1000 | E22: =-Assumptions!$B$34/12*(1+Assumptions!$B$11)^(E5-1) -> -1000 | F22: =-Assumptions!$B$34/12*(1+Assumptions!$B$11)^(F5-1) -> -1000 | G22: =-Assumptions!$B$34/12*(1+Assumptions!$B$11)^(G5-1) -> -1000 | H22: =-Assumptions!$B$34/12*(1+Assumptions!$B$11)^(H5-1) -> -1000 | I22: =-Assumptions!$B$34/12*(1+Assumptions!$B$11)^(I5-1) -> -1000 | J22: =-Assumptions!$B$34/12*(1+Assumptions!$B$11)^(J5-1) -> -1000 | K22: =-Assumptions!$B$34/12*(1+Assumptions!$B$11)^(K5-1) -> -1000 | ... DS22: =-Assumptions!$B$34/12*(1+Assumptions!$B$11)^(DS5-1) -> -1248.863
A23: Gas | D23: =-Assumptions!$B$35/12*(1+Assumptions!$B$11)^(D5-1) -> -250 | E23: =-Assumptions!$B$35/12*(1+Assumptions!$B$11)^(E5-1) -> -250 | F23: =-Assumptions!$B$35/12*(1+Assumptions!$B$11)^(F5-1) -> -250 | G23: =-Assumptions!$B$35/12*(1+Assumptions!$B$11)^(G5-1) -> -250 | H23: =-Assumptions!$B$35/12*(1+Assumptions!$B$11)^(H5-1) -> -250 | I23: =-Assumptions!$B$35/12*(1+Assumptions!$B$11)^(I5-1) -> -250 | J23: =-Assumptions!$B$35/12*(1+Assumptions!$B$11)^(J5-1) -> -250 | K23: =-Assumptions!$B$35/12*(1+Assumptions!$B$11)^(K5-1) -> -250 | ... DS23: =-Assumptions!$B$35/12*(1+Assumptions!$B$11)^(DS5-1) -> -312.21574
A24: Water | D24: =-Assumptions!$B$36/12*(1+Assumptions!$B$11)^(D5-1) -> -2500 | E24: =-Assumptions!$B$36/12*(1+Assumptions!$B$11)^(E5-1) -> -2500 | F24: =-Assumptions!$B$36/12*(1+Assumptions!$B$11)^(F5-1) -> -2500 | G24: =-Assumptions!$B$36/12*(1+Assumptions!$B$11)^(G5-1) -> -2500 | H24: =-Assumptions!$B$36/12*(1+Assumptions!$B$11)^(H5-1) -> -2500 | I24: =-Assumptions!$B$36/12*(1+Assumptions!$B$11)^(I5-1) -> -2500 | J24: =-Assumptions!$B$36/12*(1+Assumptions!$B$11)^(J5-1) -> -2500 | K24: =-Assumptions!$B$36/12*(1+Assumptions!$B$11)^(K5-1) -> -2500 | ... DS24: =-Assumptions!$B$36/12*(1+Assumptions!$B$11)^(DS5-1) -> -3122.1574
A25: Sewer | D25: =-Assumptions!$B$37/12*(1+Assumptions!$B$11)^(D5-1) -> -2083.3333 | E25: =-Assumptions!$B$37/12*(1+Assumptions!$B$11)^(E5-1) -> -2083.3333 | F25: =-Assumptions!$B$37/12*(1+Assumptions!$B$11)^(F5-1) -> -2083.3333 | G25: =-Assumptions!$B$37/12*(1+Assumptions!$B$11)^(G5-1) -> -2083.3333 | H25: =-Assumptions!$B$37/12*(1+Assumptions!$B$11)^(H5-1) -> -2083.3333 | I25: =-Assumptions!$B$37/12*(1+Assumptions!$B$11)^(I5-1) -> -2083.3333 | J25: =-Assumptions!$B$37/12*(1+Assumptions!$B$11)^(J5-1) -> -2083.3333 | K25: =-Assumptions!$B$37/12*(1+Assumptions!$B$11)^(K5-1) -> -2083.3333 | ... DS25: =-Assumptions!$B$37/12*(1+Assumptions!$B$11)^(DS5-1) -> -2601.7979
A26: Repairs & Maintenance | D26: =-Assumptions!$B$38/12*(1+Assumptions!$B$11)^(D5-1) -> -2916.6667 | E26: =-Assumptions!$B$38/12*(1+Assumptions!$B$11)^(E5-1) -> -2916.6667 | F26: =-Assumptions!$B$38/12*(1+Assumptions!$B$11)^(F5-1) -> -2916.6667 | G26: =-Assumptions!$B$38/12*(1+Assumptions!$B$11)^(G5-1) -> -2916.6667 | H26: =-Assumptions!$B$38/12*(1+Assumptions!$B$11)^(H5-1) -> -2916.6667 | I26: =-Assumptions!$B$38/12*(1+Assumptions!$B$11)^(I5-1) -> -2916.6667 | J26: =-Assumptions!$B$38/12*(1+Assumptions!$B$11)^(J5-1) -> -2916.6667 | K26: =-Assumptions!$B$38/12*(1+Assumptions!$B$11)^(K5-1) -> -2916.6667 | ... DS26: =-Assumptions!$B$38/12*(1+Assumptions!$B$11)^(DS5-1) -> -3642.517
A27: POH Insurance | D27: =-Assumptions!$B$39/12*(1+Assumptions!$B$11)^(D5-1) -> -333.33333 | E27: =-Assumptions!$B$39/12*(1+Assumptions!$B$11)^(E5-1) -> -333.33333 | F27: =-Assumptions!$B$39/12*(1+Assumptions!$B$11)^(F5-1) -> -333.33333 | G27: =-Assumptions!$B$39/12*(1+Assumptions!$B$11)^(G5-1) -> -333.33333 | H27: =-Assumptions!$B$39/12*(1+Assumptions!$B$11)^(H5-1) -> -333.33333 | I27: =-Assumptions!$B$39/12*(1+Assumptions!$B$11)^(I5-1) -> -333.33333 | J27: =-Assumptions!$B$39/12*(1+Assumptions!$B$11)^(J5-1) -> -333.33333 | K27: =-Assumptions!$B$39/12*(1+Assumptions!$B$11)^(K5-1) -> -333.33333 | ... DS27: =-Assumptions!$B$39/12*(1+Assumptions!$B$11)^(DS5-1) -> -416.28766
A28: POH Repairs | D28: =-Assumptions!$B$40/12*(1+Assumptions!$B$11)^(D5-1) -> -666.66667 | E28: =-Assumptions!$B$40/12*(1+Assumptions!$B$11)^(E5-1) -> -666.66667 | F28: =-Assumptions!$B$40/12*(1+Assumptions!$B$11)^(F5-1) -> -666.66667 | G28: =-Assumptions!$B$40/12*(1+Assumptions!$B$11)^(G5-1) -> -666.66667 | H28: =-Assumptions!$B$40/12*(1+Assumptions!$B$11)^(H5-1) -> -666.66667 | I28: =-Assumptions!$B$40/12*(1+Assumptions!$B$11)^(I5-1) -> -666.66667 | J28: =-Assumptions!$B$40/12*(1+Assumptions!$B$11)^(J5-1) -> -666.66667 | K28: =-Assumptions!$B$40/12*(1+Assumptions!$B$11)^(K5-1) -> -666.66667 | ... DS28: =-Assumptions!$B$40/12*(1+Assumptions!$B$11)^(DS5-1) -> -832.57531
A29: Turnover / Make-ready | D29: =-Assumptions!$B$41/12*(1+Assumptions!$B$11)^(D5-1) -> -500 | E29: =-Assumptions!$B$41/12*(1+Assumptions!$B$11)^(E5-1) -> -500 | F29: =-Assumptions!$B$41/12*(1+Assumptions!$B$11)^(F5-1) -> -500 | G29: =-Assumptions!$B$41/12*(1+Assumptions!$B$11)^(G5-1) -> -500 | H29: =-Assumptions!$B$41/12*(1+Assumptions!$B$11)^(H5-1) -> -500 | I29: =-Assumptions!$B$41/12*(1+Assumptions!$B$11)^(I5-1) -> -500 | J29: =-Assumptions!$B$41/12*(1+Assumptions!$B$11)^(J5-1) -> -500 | K29: =-Assumptions!$B$41/12*(1+Assumptions!$B$11)^(K5-1) -> -500 | ... DS29: =-Assumptions!$B$41/12*(1+Assumptions!$B$11)^(DS5-1) -> -624.43148
A30: Administrative | D30: =-Assumptions!$B$42/12*(1+Assumptions!$B$11)^(D5-1) -> -833.33333 | E30: =-Assumptions!$B$42/12*(1+Assumptions!$B$11)^(E5-1) -> -833.33333 | F30: =-Assumptions!$B$42/12*(1+Assumptions!$B$11)^(F5-1) -> -833.33333 | G30: =-Assumptions!$B$42/12*(1+Assumptions!$B$11)^(G5-1) -> -833.33333 | H30: =-Assumptions!$B$42/12*(1+Assumptions!$B$11)^(H5-1) -> -833.33333 | I30: =-Assumptions!$B$42/12*(1+Assumptions!$B$11)^(I5-1) -> -833.33333 | J30: =-Assumptions!$B$42/12*(1+Assumptions!$B$11)^(J5-1) -> -833.33333 | K30: =-Assumptions!$B$42/12*(1+Assumptions!$B$11)^(K5-1) -> -833.33333 | ... DS30: =-Assumptions!$B$42/12*(1+Assumptions!$B$11)^(DS5-1) -> -1040.7191
A31: Legal / Professional | D31: =-Assumptions!$B$43/12*(1+Assumptions!$B$11)^(D5-1) -> -416.66667 | E31: =-Assumptions!$B$43/12*(1+Assumptions!$B$11)^(E5-1) -> -416.66667 | F31: =-Assumptions!$B$43/12*(1+Assumptions!$B$11)^(F5-1) -> -416.66667 | G31: =-Assumptions!$B$43/12*(1+Assumptions!$B$11)^(G5-1) -> -416.66667 | H31: =-Assumptions!$B$43/12*(1+Assumptions!$B$11)^(H5-1) -> -416.66667 | I31: =-Assumptions!$B$43/12*(1+Assumptions!$B$11)^(I5-1) -> -416.66667 | J31: =-Assumptions!$B$43/12*(1+Assumptions!$B$11)^(J5-1) -> -416.66667 | K31: =-Assumptions!$B$43/12*(1+Assumptions!$B$11)^(K5-1) -> -416.66667 | ... DS31: =-Assumptions!$B$43/12*(1+Assumptions!$B$11)^(DS5-1) -> -520.35957
A32: Landscaping | D32: =-Assumptions!$B$44/12*(1+Assumptions!$B$11)^(D5-1) -> -666.66667 | E32: =-Assumptions!$B$44/12*(1+Assumptions!$B$11)^(E5-1) -> -666.66667 | F32: =-Assumptions!$B$44/12*(1+Assumptions!$B$11)^(F5-1) -> -666.66667 | G32: =-Assumptions!$B$44/12*(1+Assumptions!$B$11)^(G5-1) -> -666.66667 | H32: =-Assumptions!$B$44/12*(1+Assumptions!$B$11)^(H5-1) -> -666.66667 | I32: =-Assumptions!$B$44/12*(1+Assumptions!$B$11)^(I5-1) -> -666.66667 | J32: =-Assumptions!$B$44/12*(1+Assumptions!$B$11)^(J5-1) -> -666.66667 | K32: =-Assumptions!$B$44/12*(1+Assumptions!$B$11)^(K5-1) -> -666.66667 | ... DS32: =-Assumptions!$B$44/12*(1+Assumptions!$B$11)^(DS5-1) -> -832.57531
A33: Trash | D33: =-Assumptions!$B$45/12*(1+Assumptions!$B$11)^(D5-1) -> -1000 | E33: =-Assumptions!$B$45/12*(1+Assumptions!$B$11)^(E5-1) -> -1000 | F33: =-Assumptions!$B$45/12*(1+Assumptions!$B$11)^(F5-1) -> -1000 | G33: =-Assumptions!$B$45/12*(1+Assumptions!$B$11)^(G5-1) -> -1000 | H33: =-Assumptions!$B$45/12*(1+Assumptions!$B$11)^(H5-1) -> -1000 | I33: =-Assumptions!$B$45/12*(1+Assumptions!$B$11)^(I5-1) -> -1000 | J33: =-Assumptions!$B$45/12*(1+Assumptions!$B$11)^(J5-1) -> -1000 | K33: =-Assumptions!$B$45/12*(1+Assumptions!$B$11)^(K5-1) -> -1000 | ... DS33: =-Assumptions!$B$45/12*(1+Assumptions!$B$11)^(DS5-1) -> -1248.863
A34: Other Operating | D34: =-Assumptions!$B$46/12*(1+Assumptions!$B$11)^(D5-1) -> -500 | E34: =-Assumptions!$B$46/12*(1+Assumptions!$B$11)^(E5-1) -> -500 | F34: =-Assumptions!$B$46/12*(1+Assumptions!$B$11)^(F5-1) -> -500 | G34: =-Assumptions!$B$46/12*(1+Assumptions!$B$11)^(G5-1) -> -500 | H34: =-Assumptions!$B$46/12*(1+Assumptions!$B$11)^(H5-1) -> -500 | I34: =-Assumptions!$B$46/12*(1+Assumptions!$B$11)^(I5-1) -> -500 | J34: =-Assumptions!$B$46/12*(1+Assumptions!$B$11)^(J5-1) -> -500 | K34: =-Assumptions!$B$46/12*(1+Assumptions!$B$11)^(K5-1) -> -500 | ... DS34: =-Assumptions!$B$46/12*(1+Assumptions!$B$11)^(DS5-1) -> -624.43148
A35: Management Fee | D35: =-Assumptions!$B$47*D18 -> -1298.9122 | E35: =-Assumptions!$B$47*E18 -> -1313.3244 | F35: =-Assumptions!$B$47*F18 -> -1327.7367 | G35: =-Assumptions!$B$47*G18 -> -1342.1489 | H35: =-Assumptions!$B$47*H18 -> -1356.5611 | I35: =-Assumptions!$B$47*I18 -> -1370.9733 | J35: =-Assumptions!$B$47*J18 -> -1385.3856 | K35: =-Assumptions!$B$47*K18 -> -1399.7978 | ... DS35: =-Assumptions!$B$47*DS18 -> -2010.3504
A36: TOTAL OPERATING EXPENSES | D36: =SUM(D20:D35) -> -20382.246 | E36: =SUM(E20:E35) -> -20396.658 | F36: =SUM(F20:F35) -> -20411.07 | G36: =SUM(G20:G35) -> -20425.482 | H36: =SUM(H20:H35) -> -20439.894 | I36: =SUM(I20:I35) -> -20454.307 | J36: =SUM(J20:J35) -> -20468.719 | K36: =SUM(K20:K35) -> -20483.131 | ... DS36: =SUM(DS20:DS35) -> -25842.819
A38: NET OPERATING INCOME | B38: NOI | D38: =D18+D36 -> 5595.9989 | E38: =E18+E36 -> 5869.8311 | F38: =F18+F36 -> 6143.6633 | G38: =G18+G36 -> 6417.4956 | H38: =H18+H36 -> 6691.3278 | I38: =I18+I36 -> 6965.16 | J38: =J18+J36 -> 7238.9922 | K38: =K18+K36 -> 7512.8244 | ... DS38: =DS18+DS36 -> 14364.19
A39: NOI Margin | D39: =IFERROR(D38/D18,0) -> 0.21541097 | E39: =IFERROR(E38/E18,0) -> 0.22347224 | F39: =IFERROR(F38/F18,0) -> 0.2313585 | G39: =IFERROR(G38/G18,0) -> 0.2390754 | H39: =IFERROR(H38/H18,0) -> 0.24662832 | I39: =IFERROR(I38/I18,0) -> 0.25402245 | J39: =IFERROR(J38/J18,0) -> 0.26126273 | K39: =IFERROR(K38/K18,0) -> 0.26835392 | ... DS39: =IFERROR(DS38/DS18,0) -> 0.35725587
A41: Capital Expenditures (reserves) | D41: =-Assumptions!$B$49/12*Assumptions!$B$16*(1+Assumptions!$B$11)^(D5-1) -> -333.33333 | E41: =-Assumptions!$B$49/12*Assumptions!$B$16*(1+Assumptions!$B$11)^(E5-1) -> -333.33333 | F41: =-Assumptions!$B$49/12*Assumptions!$B$16*(1+Assumptions!$B$11)^(F5-1) -> -333.33333 | G41: =-Assumptions!$B$49/12*Assumptions!$B$16*(1+Assumptions!$B$11)^(G5-1) -> -333.33333 | H41: =-Assumptions!$B$49/12*Assumptions!$B$16*(1+Assumptions!$B$11)^(H5-1) -> -333.33333 | I41: =-Assumptions!$B$49/12*Assumptions!$B$16*(1+Assumptions!$B$11)^(I5-1) -> -333.33333 | J41: =-Assumptions!$B$49/12*Assumptions!$B$16*(1+Assumptions!$B$11)^(J5-1) -> -333.33333 | K41: =-Assumptions!$B$49/12*Assumptions!$B$16*(1+Assumptions!$B$11)^(K5-1) -> -333.33333 | ... DS41: =-Assumptions!$B$49/12*Assumptions!$B$16*(1+Assumptions!$B$11)^(DS5-1) -> -416.28766
A42: NOI AFTER CAPEX | D42: =D38+D41 -> 5262.6656 | E42: =E38+E41 -> 5536.4978 | F42: =F38+F41 -> 5810.33 | G42: =G38+G41 -> 6084.1622 | H42: =H38+H41 -> 6357.9944 | I42: =I38+I41 -> 6631.8267 | J42: =J38+J41 -> 6905.6589 | K42: =K38+K41 -> 7179.4911 | ... DS42: =DS38+DS41 -> 13947.902
A44: Fwd 12-mo NOI (for valn) | D44: =SUM(E38:P38) -> 88866.143 | E44: =SUM(F38:Q38) -> 92515.516 | F44: =SUM(G38:R38) -> 96173.032 | G44: =SUM(H38:S38) -> 99838.692 | H44: =SUM(I38:T38) -> 103512.49 | I44: =SUM(J38:U38) -> 107194.44 | J44: =SUM(K38:V38) -> 110602.55 | K44: =SUM(L38:W38) -> 113736.83 | ... DG44: =SUM(DH38:DS38) -> 172370.28 | DH44: =SUM(CW38:DH38) -> 166617.57 | DI44: =SUM(CX38:DI38) -> 167140.54 | DJ44: =SUM(CY38:DJ38) -> 167663.52 | DK44: =SUM(CZ38:DK38) -> 168186.49 | DL44: =SUM(DA38:DL38) -> 168709.46 | DM44: =SUM(DB38:DM38) -> 169232.44 | DN44: =SUM(DC38:DN38) -> 169755.41 | DO44: =SUM(DD38:DO38) -> 170278.38 | ... DS44: =SUM(DH38:DS38) -> 172370.28

Sheet Debt Schedule
A1: DEBT SCHEDULE — MONTHLY
A2: Initial loan (IO then amortizing) paid off at refinance; refinance loan runs to exit. DSCR / Debt Yield / LTV tracked.
A4: Month # | D4: 1 | E4: 2 | F4: 3 | G4: 4 | H4: 5 | I4: 6 | J4: 7 | K4: 8 | L4: 9 | M4: 10 | N4: 11 | O4: 12 | P4: 13 | Q4: 14 | R4: 15 | S4: 16 | T4: 17 | U4: 18 | V4: 19 | W4: 20 | X4: 21 | Y4: 22 | Z4: 23 | AA4: 24 | AB4: 25 | AC4: 26 | AD4: 27 | AE4: 28 | AF4: 29 | AG4: 30 | AH4: 31 | AI4: 32 | AJ4: 33 | AK4: 34 | AL4: 35 | AM4: 36 | AN4: 37 | AO4: 38 | AP4: 39 | AQ4: 40 | AR4: 41 | AS4: 42 | AT4: 43 | AU4: 44 | AV4: 45 | AW4: 46 | AX4: 47 | AY4: 48 | AZ4: 49 | BA4: 50 | BB4: 51 | BC4: 52 | BD4: 53 | BE4: 54 | BF4: 55 | BG4: 56 | BH4: 57 | BI4: 58 | BJ4: 59 | BK4: 60 | BL4: 61 | BM4: 62 | BN4: 63 | BO4: 64 | BP4: 65 | BQ4: 66 | BR4: 67 | BS4: 68 | BT4: 69 | BU4: 70 | BV4: 71 | BW4: 72 | BX4: 73 | BY4: 74 | BZ4: 75 | CA4: 76 | CB4: 77 | CC4: 78 | CD4: 79 | CE4: 80 | CF4: 81 | CG4: 82 | CH4: 83 | CI4: 84 | CJ4: 85 | CK4: 86 | CL4: 87 | CM4: 88 | CN4: 89 | CO4: 90 | CP4: 91 | CQ4: 92 | CR4: 93 | CS4: 94 | CT4: 95 | CU4: 96 | CV4: 97 | CW4: 98 | CX4: 99 | CY4: 100 | CZ4: 101 | DA4: 102 | DB4: 103 | DC4: 104 | DD4: 105 | DE4: 106 | DF4: 107 | DG4: 108 | DH4: 109 | DI4: 110 | DJ4: 111 | DK4: 112 | DL4: 113 | DM4: 114 | DN4: 115 | DO4: 116 | DP4: 117 | DQ4: 118 | DR4: 119 | DS4: 120
A5: INITIAL LOAN | AL5: .
A6: Initial — Beg Balance | D6: =IF(D4<IF(Assumptions!$B$67=1,Assumptions!$B$68,Assumptions!$B$60+1),Acquisition!$B$10,0) -> 910000 | E6: =IF(E4<IF(Assumptions!$B$67=1,Assumptions!$B$68,Assumptions!$B$60+1),D10,0) -> 910000 | F6: =IF(F4<IF(Assumptions!$B$67=1,Assumptions!$B$68,Assumptions!$B$60+1),E10,0) -> 910000 | G6: =IF(G4<IF(Assumptions!$B$67=1,Assumptions!$B$68,Assumptions!$B$60+1),F10,0) -> 910000 | H6: =IF(H4<IF(Assumptions!$B$67=1,Assumptions!$B$68,Assumptions!$B$60+1),G10,0) -> 910000 | I6: =IF(I4<IF(Assumptions!$B$67=1,Assumptions!$B$68,Assumptions!$B$60+1),H10,0) -> 910000 | J6: =IF(J4<IF(Assumptions!$B$67=1,Assumptions!$B$68,Assumptions!$B$60+1),I10,0) -> 910000 | K6: =IF(K4<IF(Assumptions!$B$67=1,Assumptions!$B$68,Assumptions!$B$60+1),J10,0) -> 910000 | L6: =IF(L4<IF(Assumptions!$B$67=1,Assumptions!$B$68,Assumptions!$B$60+1),K10,0) -> 910000 | ... DS6: =IF(DS4<IF(Assumptions!$B$67=1,Assumptions!$B$68,Assumptions!$B$60+1),DR10,0) -> 0
A7: Interest | D7: =IF(D4<IF(Assumptions!$B$67=1,Assumptions!$B$68,Assumptions!$B$60+1),D6*Assumptions!$B$88,0) -> 4929.1667 | E7: =IF(E4<IF(Assumptions!$B$67=1,Assumptions!$B$68,Assumptions!$B$60+1),E6*Assumptions!$B$88,0) -> 4929.1667 | F7: =IF(F4<IF(Assumptions!$B$67=1,Assumptions!$B$68,Assumptions!$B$60+1),F6*Assumptions!$B$88,0) -> 4929.1667 | G7: =IF(G4<IF(Assumptions!$B$67=1,Assumptions!$B$68,Assumptions!$B$60+1),G6*Assumptions!$B$88,0) -> 4929.1667 | H7: =IF(H4<IF(Assumptions!$B$67=1,Assumptions!$B$68,Assumptions!$B$60+1),H6*Assumptions!$B$88,0) -> 4929.1667 | I7: =IF(I4<IF(Assumptions!$B$67=1,Assumptions!$B$68,Assumptions!$B$60+1),I6*Assumptions!$B$88,0) -> 4929.1667 | J7: =IF(J4<IF(Assumptions!$B$67=1,Assumptions!$B$68,Assumptions!$B$60+1),J6*Assumptions!$B$88,0) -> 4929.1667 | K7: =IF(K4<IF(Assumptions!$B$67=1,Assumptions!$B$68,Assumptions!$B$60+1),K6*Assumptions!$B$88,0) -> 4929.1667 | ... DS7: =IF(DS4<IF(Assumptions!$B$67=1,Assumptions!$B$68,Assumptions!$B$60+1),DS6*Assumptions!$B$88,0) -> 0
A8: Principal | D8: =IF(D4<IF(Assumptions!$B$67=1,Assumptions!$B$68,Assumptions!$B$60+1),IF(D4<=Assumptions!$B$61,0,(-PMT(Assumptions!$B$88,Assumptions!$B$59,Acquisition!$B$10))-D7),0) -> 0 | E8: =IF(E4<IF(Assumptions!$B$67=1,Assumptions!$B$68,Assumptions!$B$60+1),IF(E4<=Assumptions!$B$61,0,(-PMT(Assumptions!$B$88,Assumptions!$B$59,Acquisition!$B$10))-E7),0) -> 0 | F8: =IF(F4<IF(Assumptions!$B$67=1,Assumptions!$B$68,Assumptions!$B$60+1),IF(F4<=Assumptions!$B$61,0,(-PMT(Assumptions!$B$88,Assumptions!$B$59,Acquisition!$B$10))-F7),0) -> 0 | G8: =IF(G4<IF(Assumptions!$B$67=1,Assumptions!$B$68,Assumptions!$B$60+1),IF(G4<=Assumptions!$B$61,0,(-PMT(Assumptions!$B$88,Assumptions!$B$59,Acquisition!$B$10))-G7),0) -> 0 | H8: =IF(H4<IF(Assumptions!$B$67=1,Assumptions!$B$68,Assumptions!$B$60+1),IF(H4<=Assumptions!$B$61,0,(-PMT(Assumptions!$B$88,Assumptions!$B$59,Acquisition!$B$10))-H7),0) -> 0 | I8: =IF(I4<IF(Assumptions!$B$67=1,Assumptions!$B$68,Assumptions!$B$60+1),IF(I4<=Assumptions!$B$61,0,(-PMT(Assumptions!$B$88,Assumptions!$B$59,Acquisition!$B$10))-I7),0) -> 0 | J8: =IF(J4<IF(Assumptions!$B$67=1,Assumptions!$B$68,Assumptions!$B$60+1),IF(J4<=Assumptions!$B$61,0,(-PMT(Assumptions!$B$88,Assumptions!$B$59,Acquisition!$B$10))-J7),0) -> 0 | K8: =IF(K4<IF(Assumptions!$B$67=1,Assumptions!$B$68,Assumptions!$B$60+1),IF(K4<=Assumptions!$B$61,0,(-PMT(Assumptions!$B$88,Assumptions!$B$59,Acquisition!$B$10))-K7),0) -> 0 | ... DS8: =IF(DS4<IF(Assumptions!$B$67=1,Assumptions!$B$68,Assumptions!$B$60+1),IF(DS4<=Assumptions!$B$61,0,(-PMT(Assumptions!$B$88,Assumptions!$B$59,Acquisition!$B$10))-DS7),0) -> 0
A9: Debt Service | D9: =D7+D8 -> 4929.1667 | E9: =E7+E8 -> 4929.1667 | F9: =F7+F8 -> 4929.1667 | G9: =G7+G8 -> 4929.1667 | H9: =H7+H8 -> 4929.1667 | I9: =I7+I8 -> 4929.1667 | J9: =J7+J8 -> 4929.1667 | K9: =K7+K8 -> 4929.1667 | ... DS9: =DS7+DS8 -> 0
A10: Initial — End Balance | D10: =D6-D8 -> 910000 | E10: =E6-E8 -> 910000 | F10: =F6-F8 -> 910000 | G10: =G6-G8 -> 910000 | H10: =H6-H8 -> 910000 | I10: =I6-I8 -> 910000 | J10: =J6-J8 -> 910000 | K10: =K6-K8 -> 910000 | ... DS10: =DS6-DS8 -> 0
A11: REFINANCE LOAN
A12: Refi — Beg Balance | D12: =IF(AND(Assumptions!$B$67=1,D4>=Assumptions!$B$68,D4<=Assumptions!$B$68+Assumptions!$B$60),Refinance!$B$11,0) -> 0 | E12: =IF(AND(Assumptions!$B$67=1,E4>=Assumptions!$B$68,E4<=Assumptions!$B$68+Assumptions!$B$60),IF(E4=Assumptions!$B$68,Refinance!$B$11,D16),0) -> 0 | F12: =IF(AND(Assumptions!$B$67=1,F4>=Assumptions!$B$68,F4<=Assumptions!$B$68+Assumptions!$B$60),IF(F4=Assumptions!$B$68,Refinance!$B$11,E16),0) -> 0 | G12: =IF(AND(Assumptions!$B$67=1,G4>=Assumptions!$B$68,G4<=Assumptions!$B$68+Assumptions!$B$60),IF(G4=Assumptions!$B$68,Refinance!$B$11,F16),0) -> 0 | H12: =IF(AND(Assumptions!$B$67=1,H4>=Assumptions!$B$68,H4<=Assumptions!$B$68+Assumptions!$B$60),IF(H4=Assumptions!$B$68,Refinance!$B$11,G16),0) -> 0 | I12: =IF(AND(Assumptions!$B$67=1,I4>=Assumptions!$B$68,I4<=Assumptions!$B$68+Assumptions!$B$60),IF(I4=Assumptions!$B$68,Refinance!$B$11,H16),0) -> 0 | J12: =IF(AND(Assumptions!$B$67=1,J4>=Assumptions!$B$68,J4<=Assumptions!$B$68+Assumptions!$B$60),IF(J4=Assumptions!$B$68,Refinance!$B$11,I16),0) -> 0 | K12: =IF(AND(Assumptions!$B$67=1,K4>=Assumptions!$B$68,K4<=Assumptions!$B$68+Assumptions!$B$60),IF(K4=Assumptions!$B$68,Refinance!$B$11,J16),0) -> 0 | L12: =IF(AND(Assumptions!$B$67=1,L4>=Assumptions!$B$68,L4<=Assumptions!$B$68+Assumptions!$B$60),IF(L4=Assumptions!$B$68,Refinance!$B$11,K16),0) -> 0 | ... DS12: =IF(AND(Assumptions!$B$67=1,DS4>=Assumptions!$B$68,DS4<=Assumptions!$B$68+Assumptions!$B$60),IF(DS4=Assumptions!$B$68,Refinance!$B$11,DR16),0) -> 1373320.5
A13: Interest | D13: =IF(AND(Assumptions!$B$67=1,D4>=Assumptions!$B$68,D4<=Assumptions!$B$68+Assumptions!$B$60),D12*Assumptions!$B$89,0) -> 0 | E13: =IF(AND(Assumptions!$B$67=1,E4>=Assumptions!$B$68,E4<=Assumptions!$B$68+Assumptions!$B$60),E12*Assumptions!$B$89,0) -> 0 | F13: =IF(AND(Assumptions!$B$67=1,F4>=Assumptions!$B$68,F4<=Assumptions!$B$68+Assumptions!$B$60),F12*Assumptions!$B$89,0) -> 0 | G13: =IF(AND(Assumptions!$B$67=1,G4>=Assumptions!$B$68,G4<=Assumptions!$B$68+Assumptions!$B$60),G12*Assumptions!$B$89,0) -> 0 | H13: =IF(AND(Assumptions!$B$67=1,H4>=Assumptions!$B$68,H4<=Assumptions!$B$68+Assumptions!$B$60),H12*Assumptions!$B$89,0) -> 0 | I13: =IF(AND(Assumptions!$B$67=1,I4>=Assumptions!$B$68,I4<=Assumptions!$B$68+Assumptions!$B$60),I12*Assumptions!$B$89,0) -> 0 | J13: =IF(AND(Assumptions!$B$67=1,J4>=Assumptions!$B$68,J4<=Assumptions!$B$68+Assumptions!$B$60),J12*Assumptions!$B$89,0) -> 0 | K13: =IF(AND(Assumptions!$B$67=1,K4>=Assumptions!$B$68,K4<=Assumptions!$B$68+Assumptions!$B$60),K12*Assumptions!$B$89,0) -> 0 | ... DS13: =IF(AND(Assumptions!$B$67=1,DS4>=Assumptions!$B$68,DS4<=Assumptions!$B$68+Assumptions!$B$60),DS12*Assumptions!$B$89,0) -> 6866.6027
A14: Principal | D14: =IF(AND(Assumptions!$B$67=1,D4>=Assumptions!$B$68,D4<=Assumptions!$B$68+Assumptions!$B$60),IF(D4<Assumptions!$B$68+Assumptions!$B$72,0,(-PMT(Assumptions!$B$89,Assumptions!$B$71,Refinance!$B$11))-D13),0) -> 0 | E14: =IF(AND(Assumptions!$B$67=1,E4>=Assumptions!$B$68,E4<=Assumptions!$B$68+Assumptions!$B$60),IF(E4<Assumptions!$B$68+Assumptions!$B$72,0,(-PMT(Assumptions!$B$89,Assumptions!$B$71,Refinance!$B$11))-E13),0) -> 0 | F14: =IF(AND(Assumptions!$B$67=1,F4>=Assumptions!$B$68,F4<=Assumptions!$B$68+Assumptions!$B$60),IF(F4<Assumptions!$B$68+Assumptions!$B$72,0,(-PMT(Assumptions!$B$89,Assumptions!$B$71,Refinance!$B$11))-F13),0) -> 0 | G14: =IF(AND(Assumptions!$B$67=1,G4>=Assumptions!$B$68,G4<=Assumptions!$B$68+Assumptions!$B$60),IF(G4<Assumptions!$B$68+Assumptions!$B$72,0,(-PMT(Assumptions!$B$89,Assumptions!$B$71,Refinance!$B$11))-G13),0) -> 0 | H14: =IF(AND(Assumptions!$B$67=1,H4>=Assumptions!$B$68,H4<=Assumptions!$B$68+Assumptions!$B$60),IF(H4<Assumptions!$B$68+Assumptions!$B$72,0,(-PMT(Assumptions!$B$89,Assumptions!$B$71,Refinance!$B$11))-H13),0) -> 0 | I14: =IF(AND(Assumptions!$B$67=1,I4>=Assumptions!$B$68,I4<=Assumptions!$B$68+Assumptions!$B$60),IF(I4<Assumptions!$B$68+Assumptions!$B$72,0,(-PMT(Assumptions!$B$89,Assumptions!$B$71,Refinance!$B$11))-I13),0) -> 0 | J14: =IF(AND(Assumptions!$B$67=1,J4>=Assumptions!$B$68,J4<=Assumptions!$B$68+Assumptions!$B$60),IF(J4<Assumptions!$B$68+Assumptions!$B$72,0,(-PMT(Assumptions!$B$89,Assumptions!$B$71,Refinance!$B$11))-J13),0) -> 0 | K14: =IF(AND(Assumptions!$B$67=1,K4>=Assumptions!$B$68,K4<=Assumptions!$B$68+Assumptions!$B$60),IF(K4<Assumptions!$B$68+Assumptions!$B$72,0,(-PMT(Assumptions!$B$89,Assumptions!$B$71,Refinance!$B$11))-K13),0) -> 0 | ... DS14: =IF(AND(Assumptions!$B$67=1,DS4>=Assumptions!$B$68,DS4<=Assumptions!$B$68+Assumptions!$B$60),IF(DS4<Assumptions!$B$68+Assumptions!$B$72,0,(-PMT(Assumptions!$B$89,Assumptions!$B$71,Refinance!$B$11))-DS13),0) -> 2318.8133
A15: Debt Service | D15: =D13+D14 -> 0 | E15: =E13+E14 -> 0 | F15: =F13+F14 -> 0 | G15: =G13+G14 -> 0 | H15: =H13+H14 -> 0 | I15: =I13+I14 -> 0 | J15: =J13+J14 -> 0 | K15: =K13+K14 -> 0 | ... DS15: =DS13+DS14 -> 9185.416
A16: Refi — End Balance | D16: =IF(AND(Assumptions!$B$67=1,D4>=Assumptions!$B$68,D4<=Assumptions!$B$68+Assumptions!$B$60),'Debt Schedule'!D12-'Debt Schedule'!D14,0) -> 0 | E16: =IF(AND(Assumptions!$B$67=1,E4>=Assumptions!$B$68,E4<=Assumptions!$B$68+Assumptions!$B$60),E12-E14,0) -> 0 | F16: =IF(AND(Assumptions!$B$67=1,F4>=Assumptions!$B$68,F4<=Assumptions!$B$68+Assumptions!$B$60),F12-F14,0) -> 0 | G16: =IF(AND(Assumptions!$B$67=1,G4>=Assumptions!$B$68,G4<=Assumptions!$B$68+Assumptions!$B$60),G12-G14,0) -> 0 | H16: =IF(AND(Assumptions!$B$67=1,H4>=Assumptions!$B$68,H4<=Assumptions!$B$68+Assumptions!$B$60),H12-H14,0) -> 0 | I16: =IF(AND(Assumptions!$B$67=1,I4>=Assumptions!$B$68,I4<=Assumptions!$B$68+Assumptions!$B$60),I12-I14,0) -> 0 | J16: =IF(AND(Assumptions!$B$67=1,J4>=Assumptions!$B$68,J4<=Assumptions!$B$68+Assumptions!$B$60),J12-J14,0) -> 0 | K16: =IF(AND(Assumptions!$B$67=1,K4>=Assumptions!$B$68,K4<=Assumptions!$B$68+Assumptions!$B$60),K12-K14,0) -> 0 | L16: =IF(AND(Assumptions!$B$67=1,L4>=Assumptions!$B$68,L4<=Assumptions!$B$68+Assumptions!$B$60),L12-L14,0) -> 0 | ... DS16: =IF(AND(Assumptions!$B$67=1,DS4>=Assumptions!$B$68,DS4<=Assumptions!$B$68+Assumptions!$B$60),DS12-DS14,0) -> 1371001.7
A17: CONSOLIDATED
A18: TOTAL DEBT SERVICE | D18: =D9+D15 -> 4929.1667 | E18: =E9+E15 -> 4929.1667 | F18: =F9+F15 -> 4929.1667 | G18: =G9+G15 -> 4929.1667 | H18: =H9+H15 -> 4929.1667 | I18: =I9+I15 -> 4929.1667 | J18: =J9+J15 -> 4929.1667 | K18: =K9+K15 -> 4929.1667 | ... DS18: =DS9+DS15 -> 9185.416
A19: TOTAL END BALANCE | D19: =D10+D16 -> 910000 | E19: =E10+E16 -> 910000 | F19: =F10+F16 -> 910000 | G19: =G10+G16 -> 910000 | H19: =H10+H16 -> 910000 | I19: =I10+I16 -> 910000 | J19: =J10+J16 -> 910000 | K19: =K10+K16 -> 910000 | ... DS19: =DS10+DS16 -> 1371001.7
A20: DSCR (NOI / DS) | D20: =IFERROR('Monthly Operations'!D38/D18,0) -> 1.135283 | E20: =IFERROR('Monthly Operations'!E38/E18,0) -> 1.1908364 | F20: =IFERROR('Monthly Operations'!F38/F18,0) -> 1.2463899 | G20: =IFERROR('Monthly Operations'!G38/G18,0) -> 1.3019433 | H20: =IFERROR('Monthly Operations'!H38/H18,0) -> 1.3574968 | I20: =IFERROR('Monthly Operations'!I38/I18,0) -> 1.4130502 | J20: =IFERROR('Monthly Operations'!J38/J18,0) -> 1.4686037 | K20: =IFERROR('Monthly Operations'!K38/K18,0) -> 1.5241571 | ... DS20: =IFERROR('Monthly Operations'!DS38/DS18,0) -> 1.5638039
A21: Debt Yield | D21: =IFERROR('Monthly Operations'!D38*12/D19,0) -> 0.073793392 | E21: =IFERROR('Monthly Operations'!E38*12/E19,0) -> 0.077404366 | F21: =IFERROR('Monthly Operations'!F38*12/F19,0) -> 0.081015341 | G21: =IFERROR('Monthly Operations'!G38*12/G19,0) -> 0.084626315 | H21: =IFERROR('Monthly Operations'!H38*12/H19,0) -> 0.088237289 | I21: =IFERROR('Monthly Operations'!I38*12/I19,0) -> 0.091848264 | J21: =IFERROR('Monthly Operations'!J38*12/J19,0) -> 0.095459238 | K21: =IFERROR('Monthly Operations'!K38*12/K19,0) -> 0.099070212 | ... DS21: =IFERROR('Monthly Operations'!DS38*12/DS19,0) -> 0.12572579
A22: LTV | D22: =IFERROR(D19/(IFERROR('Monthly Operations'!D44/Assumptions!$B$12,0)),0) -> 0.66560782 | E22: =IFERROR(E19/(IFERROR('Monthly Operations'!E44/Assumptions!$B$12,0)),0) -> 0.63935221 | F22: =IFERROR(F19/(IFERROR('Monthly Operations'!F44/Assumptions!$B$12,0)),0) -> 0.61503728 | G22: =IFERROR(G19/(IFERROR('Monthly Operations'!G44/Assumptions!$B$12,0)),0) -> 0.59245568 | H22: =IFERROR(H19/(IFERROR('Monthly Operations'!H44/Assumptions!$B$12,0)),0) -> 0.5714286 | I22: =IFERROR(I19/(IFERROR('Monthly Operations'!I44/Assumptions!$B$12,0)),0) -> 0.55180101 | J22: =IFERROR(J19/(IFERROR('Monthly Operations'!J44/Assumptions!$B$12,0)),0) -> 0.53479778 | K22: =IFERROR(K19/(IFERROR('Monthly Operations'!K44/Assumptions!$B$12,0)),0) -> 0.52006019 | ... DS22: =IFERROR(DS19/(IFERROR('Monthly Operations'!DS44/Assumptions!$B$12,0)),0) -> 0.51699814

Sheet Refinance
A1: REFINANCE
A2: At the refi month: value on refi NOI, size the new loan, pay off the old, release cash-out.
A4: REFINANCE SIZING
A5: Refinance Month | B5: =Assumptions!$B$68 -> 36
A6: Refinance NOI (fwd 12-mo) | B6: =IFERROR(INDEX('Monthly Operations'!D44:DS44,1,Assumptions!$B$68),0) -> 137781.24
A7: Refinance Cap Rate | B7: =Assumptions!$B$74 -> 0.062
A8: Refinance Value | B8: =IFERROR(B6/B7,0) -> 2222278.1
A9: Max New Loan — by LTV | B9: =Assumptions!$B$69*B8 -> 1555594.6
A10: Max New Loan — by Debt Yield | B10: =IFERROR(B6/Assumptions!$B$64,0) -> 1722265.5
A11: NEW REFINANCE LOAN | B11: =IF(Assumptions!$B$67=1,MIN(B9,B10,IFERROR(B6/Assumptions!$B$63/(-PMT(Assumptions!$B$89,Assumptions!$B$71,1)*12),0)),0) -> 1532050.4 | D11: Binding of LTV / DY / DSCR
A12: Less: Existing Loan Payoff | B12: =IF(Assumptions!$B$67=1,-(IF(Assumptions!$B$68<=1,Acquisition!$B$10,INDEX('Debt Schedule'!D10:DS10,1,Assumptions!$B$68-1))),0) -> -900701.72
A13: Less: Refinance Fees | B13: =-Assumptions!$B$73*B11 -> -15320.504
A14: NET REFINANCE PROCEEDS | B14: =B11+B12+B13 -> 616028.14
A15: Cash-out result | B15: =IF(Assumptions!$B$67=0,"No refinance",IF(B14>1,"POSITIVE CASH-OUT",IF(B14<-1,"ADDITIONAL EQUITY NEEDED","NO CASH-OUT"))) -> POSITIVE CASH-OUT

Sheet Valuation
A1: NOI & VALUATION
A2: Value = NOI / Cap Rate. Going-in, stabilized, refinance and exit caps set independently on Assumptions.
C4: Year 1 | D4: Year 2 | E4: Year 3 | F4: Year 4 | G4: Year 5 | H4: Year 6 | I4: Year 7 | J4: Year 8 | K4: Year 9 | L4: Year 10
A5: Effective Gross Revenue | C5: =SUM('Monthly Operations'!D18:O18) -> 330763.07 | D5: =SUM('Monthly Operations'!P18:AA18) -> 377116.46 | E5: =SUM('Monthly Operations'!AB18:AM18) -> 392925.24 | F5: =SUM('Monthly Operations'!AN18:AY18) -> 404620.2 | G5: =SUM('Monthly Operations'!AZ18:BK18) -> 416663.7 | H5: =SUM('Monthly Operations'!BL18:BW18) -> 429066.12 | I5: =SUM('Monthly Operations'!BX18:CI18) -> 441838.18 | J5: =SUM('Monthly Operations'!CJ18:CU18) -> 454990.9 | K5: =SUM('Monthly Operations'!CV18:DG18) -> 468535.64 | L5: =SUM('Monthly Operations'!DH18:DS18) -> 482484.1
A6: Total Operating Expenses | C6: =SUM('Monthly Operations'!D36:O36) -> -245538.15 | D6: =SUM('Monthly Operations'!P36:AA36) -> -253580.82 | E6: =SUM('Monthly Operations'!AB36:AM36) -> -260239.39 | F6: =SUM('Monthly Operations'!AN36:AY36) -> -266838.96 | G6: =SUM('Monthly Operations'!AZ36:BK36) -> -273606.34 | H6: =SUM('Monthly Operations'!BL36:BW36) -> -280545.79 | I6: =SUM('Monthly Operations'!BX36:CI36) -> -287661.7 | J6: =SUM('Monthly Operations'!CJ36:CU36) -> -294958.58 | K6: =SUM('Monthly Operations'!CV36:DG36) -> -302441.05 | L6: =SUM('Monthly Operations'!DH36:DS36) -> -310113.83
A7: NET OPERATING INCOME | C7: =SUM('Monthly Operations'!D38:O38) -> 85224.913 | D7: =SUM('Monthly Operations'!P38:AA38) -> 123535.64 | E7: =SUM('Monthly Operations'!AB38:AM38) -> 132685.85 | F7: =SUM('Monthly Operations'!AN38:AY38) -> 137781.24 | G7: =SUM('Monthly Operations'!AZ38:BK38) -> 143057.36 | H7: =SUM('Monthly Operations'!BL38:BW38) -> 148520.33 | I7: =SUM('Monthly Operations'!BX38:CI38) -> 154176.48 | J7: =SUM('Monthly Operations'!CJ38:CU38) -> 160032.32 | K7: =SUM('Monthly Operations'!CV38:DG38) -> 166094.6 | L7: =SUM('Monthly Operations'!DH38:DS38) -> 172370.28
A8: Capital Expenditures | C8: =SUM('Monthly Operations'!D41:O41) -> -4000 | D8: =SUM('Monthly Operations'!P41:AA41) -> -4100 | E8: =SUM('Monthly Operations'!AB41:AM41) -> -4202.5 | F8: =SUM('Monthly Operations'!AN41:AY41) -> -4307.5625 | G8: =SUM('Monthly Operations'!AZ41:BK41) -> -4415.2516 | H8: =SUM('Monthly Operations'!BL41:BW41) -> -4525.6329 | I8: =SUM('Monthly Operations'!BX41:CI41) -> -4638.7737 | J8: =SUM('Monthly Operations'!CJ41:CU41) -> -4754.743 | K8: =SUM('Monthly Operations'!CV41:DG41) -> -4873.6116 | L8: =SUM('Monthly Operations'!DH41:DS41) -> -4995.4519
A9: NOI after CapEx | C9: =SUM('Monthly Operations'!D42:O42) -> 81224.913 | D9: =SUM('Monthly Operations'!P42:AA42) -> 119435.64 | E9: =SUM('Monthly Operations'!AB42:AM42) -> 128483.35 | F9: =SUM('Monthly Operations'!AN42:AY42) -> 133473.68 | G9: =SUM('Monthly Operations'!AZ42:BK42) -> 138642.11 | H9: =SUM('Monthly Operations'!BL42:BW42) -> 143994.7 | I9: =SUM('Monthly Operations'!BX42:CI42) -> 149537.7 | J9: =SUM('Monthly Operations'!CJ42:CU42) -> 155277.57 | K9: =SUM('Monthly Operations'!CV42:DG42) -> 161220.98 | L9: =SUM('Monthly Operations'!DH42:DS42) -> 167374.82
A10: NOI Margin | C10: =IFERROR(C7/C5,0) -> 0.25766152 | D10: =IFERROR(D7/D5,0) -> 0.32757954 | E10: =IFERROR(E7/E5,0) -> 0.33768727 | F10: =IFERROR(F7/F5,0) -> 0.34051992 | G10: =IFERROR(G7/G5,0) -> 0.34334011 | H10: =IFERROR(H7/H5,0) -> 0.34614789 | I10: =IFERROR(I7/I5,0) -> 0.34894331 | J10: =IFERROR(J7/J5,0) -> 0.35172641 | ... L10: =IFERROR(L7/L5,0) -> 0.35725587
A12: VALUATION SUMMARY
A13: Purchase Price | B13: =Assumptions!$B$8 -> 1300000
A14: Year-1 NOI | B14: =Valuation!C7 -> 85224.913
A15: Going-in Cap Rate | B15: =IFERROR(B14/B13,0) -> 0.065557626
A16: Stabilized NOI (Year 3) | B16: =Valuation!E7 -> 132685.85
A17: Price per Pad | B17: =B13/Assumptions!$B$16 -> 16250

Sheet Exit
A1: EXIT / DISPOSITION
A2: Forward-NOI exit value at the chosen month, net of costs, fees and debt payoff. Exit-year table below.
A4: EXIT AT CHOSEN MONTH
A5: Exit Month | B5: =Assumptions!$B$76 -> 60
A6: Exit Year | B6: =INT((Assumptions!$B$76-1)/12)+1 -> 5
A7: Forward 12-mo NOI | B7: =IFERROR(INDEX('Monthly Operations'!D44:DS44,1,Assumptions!$B$76),0) -> 148520.33
A8: Exit Cap Rate | B8: =Assumptions!$B$12 -> 0.065
A9: Gross Exit Value | B9: =IFERROR(B7/B8,0) -> 2284928.2
A10: Less: Selling Costs | B10: =-Assumptions!$B$77*B9 -> -68547.846
A11: Less: Exit / Disposition Fee | B11: =-Assumptions!$B$78*B9 -> -22849.282
A12: Less: Debt Payoff at Exit | B12: =-INDEX('Debt Schedule'!D19:DS19,1,Assumptions!$B$76) -> -1491543.3
A13: NET SALE PROCEEDS | B13: =SUM(B9:B12) -> 701987.73
A16: EXIT-YEAR ANALYSIS (sell at end of each year)
A17: Exit Year | B17: Fwd NOI | C17: Exit Cap | D17: Gross Value | E17: Selling Costs | F17: Debt Payoff | G17: Net Proceeds | H17: Equity CF (all yrs) | I17: IRR | J17: Equity Mult. | K17: Profit
A18: 1 | B18: =INDEX('Monthly Operations'!D44:DS44,1,12) -> 123535.64 | C18: =Assumptions!$B$12 -> 0.065 | D18: =IFERROR(B18/C18,0) -> 1900548.3 | E18: =-(Assumptions!$B$77+Assumptions!$B$78)*D18 -> -76021.931 | F18: =-INDEX('Debt Schedule'!D19:DS19,1,12) -> -910000 | G18: =D18+E18+F18 -> 914526.34 | H18: ='Equity Returns'!C24 -> 936601.25 | I18: ='Equity Returns'!N24 -> 0.56074197 | J18: ='Equity Returns'!O24 -> 1.560742 | K18: ='Equity Returns'!P24 -> 336501.25
A19: 2 | B19: =INDEX('Monthly Operations'!D44:DS44,1,24) -> 132685.85 | C19: =Assumptions!$B$12 -> 0.065 | D19: =IFERROR(B19/C19,0) -> 2041320.8 | E19: =-(Assumptions!$B$77+Assumptions!$B$78)*D19 -> -81652.831 | F19: =-INDEX('Debt Schedule'!D19:DS19,1,24) -> -910000 | G19: =D19+E19+F19 -> 1049667.9 | H19: ='Equity Returns'!D25 -> 1109953.6 | I19: ='Equity Returns'!N25 -> 0.37852234 | J19: ='Equity Returns'!O25 -> 1.8863998 | K19: ='Equity Returns'!P25 -> 531928.49 | L19: =G19+60286 -> 1109953.9
A20: 3 | B20: =INDEX('Monthly Operations'!D44:DS44,1,36) -> 137781.24 | C20: =Assumptions!$B$12 -> 0.065 | D20: =IFERROR(B20/C20,0) -> 2119711.4 | E20: =-(Assumptions!$B$77+Assumptions!$B$78)*D20 -> -84788.455 | F20: =-INDEX('Debt Schedule'!D19:DS19,1,36) -> -1530525.2 | G20: =D20+E20+F20 -> 504397.73 | H20: ='Equity Returns'!E26 -> 1176453.8 | I20: ='Equity Returns'!N26 -> 0.29094732 | J20: ='Equity Returns'!O26 -> 2.0976743 | K20: ='Equity Returns'!P26 -> 658714.35 | L20: 22075
A21: 4 | B21: =INDEX('Monthly Operations'!D44:DS44,1,48) -> 143057.36 | C21: =Assumptions!$B$12 -> 0.065 | D21: =IFERROR(B21/C21,0) -> 2200882.5 | E21: =-(Assumptions!$B$77+Assumptions!$B$78)*D21 -> -88035.299 | F21: =-INDEX('Debt Schedule'!D19:DS19,1,48) -> -1511617.4 | G21: =D21+E21+F21 -> 601229.81 | H21: ='Equity Returns'!F27 -> 624478.5 | I21: ='Equity Returns'!N27 -> 0.28458014 | J21: ='Equity Returns'!O27 -> 2.2977756 | K21: ='Equity Returns'!P27 -> 778795.11 | L21: =SUM(L19:L20) -> 1132028.9
A22: 5 | B22: =INDEX('Monthly Operations'!D44:DS44,1,60) -> 148520.33 | C22: =Assumptions!$B$12 -> 0.065 | D22: =IFERROR(B22/C22,0) -> 2284928.2 | E22: =-(Assumptions!$B$77+Assumptions!$B$78)*D22 -> -91397.128 | F22: =-INDEX('Debt Schedule'!D19:DS19,1,60) -> -1491543.3 | G22: =D22+E22+F22 -> 701987.73 | H22: ='Equity Returns'!G28 -> 730404.85 | I22: ='Equity Returns'!N28 -> 0.27741656 | J22: ='Equity Returns'!O28 -> 2.5130314 | K22: ='Equity Returns'!P28 -> 907970.15
A23: 6 | B23: =INDEX('Monthly Operations'!D44:DS44,1,72) -> 154176.48 | C23: =Assumptions!$B$12 -> 0.065 | D23: =IFERROR(B23/C23,0) -> 2371945.8 | E23: =-(Assumptions!$B$77+Assumptions!$B$78)*D23 -> -94877.832 | F23: =-INDEX('Debt Schedule'!D19:DS19,1,72) -> -1470231.2 | G23: =D23+E23+F23 -> 806836.75 | H23: ='Equity Returns'!H29 -> 840606.46 | I23: ='Equity Returns'!N29 -> 0.27033933 | J23: ='Equity Returns'!O29 -> 2.7440241 | K23: ='Equity Returns'!P29 -> 1046588.9
A24: 7 | B24: =INDEX('Monthly Operations'!D44:DS44,1,84) -> 160032.32 | C24: =Assumptions!$B$12 -> 0.065 | D24: =IFERROR(B24/C24,0) -> 2462035.6 | E24: =-(Assumptions!$B$77+Assumptions!$B$78)*D24 -> -98481.426 | F24: =-INDEX('Debt Schedule'!D19:DS19,1,84) -> -1447604.6 | G24: =D24+E24+F24 -> 915949.63 | H24: ='Equity Returns'!I30 -> 955262.35 | I24: ='Equity Returns'!N30 -> 0.26369184 | J24: ='Equity Returns'!O30 -> 2.9913589 | K24: ='Equity Returns'!P30 -> 1195014.5
A25: 8 | B25: =INDEX('Monthly Operations'!D44:DS44,1,96) -> 166094.6 | C25: =Assumptions!$B$12 -> 0.065 | D25: =IFERROR(B25/C25,0) -> 2555301.5 | E25: =-(Assumptions!$B$77+Assumptions!$B$78)*D25 -> -102212.06 | F25: =-INDEX('Debt Schedule'!D19:DS19,1,96) -> -1423582.4 | G25: =D25+E25+F25 -> 1029507 | H25: ='Equity Returns'!J31 -> 1074559.6 | I25: ='Equity Returns'!N31 -> 0.25758924 | J25: ='Equity Returns'!O31 -> 3.2556648 | K25: ='Equity Returns'!P31 -> 1353624.4
A26: 9 | B26: =INDEX('Monthly Operations'!D44:DS44,1,108) -> 172370.28 | C26: =Assumptions!$B$12 -> 0.065 | D26: =IFERROR(B26/C26,0) -> 2651850.4 | E26: =-(Assumptions!$B$77+Assumptions!$B$78)*D26 -> -106074.02 | F26: =-INDEX('Debt Schedule'!D19:DS19,1,108) -> -1398078.6 | G26: =D26+E26+F26 -> 1147697.8 | H26: ='Equity Returns'!K32 -> 1198693.8 | I26: ='Equity Returns'!N32 -> 0.2520483 | J26: ='Equity Returns'!O32 -> 3.5375958 | K26: ='Equity Returns'!P32 -> 1522811.2
A27: 10 | B27: =INDEX('Monthly Operations'!D44:DS44,1,120) -> 172370.28 | C27: =Assumptions!$B$12 -> 0.065 | D27: =IFERROR(B27/C27,0) -> 2651850.4 | E27: =-(Assumptions!$B$77+Assumptions!$B$78)*D27 -> -106074.02 | F27: =-INDEX('Debt Schedule'!D19:DS19,1,120) -> -1371001.7 | G27: =D27+E27+F27 -> 1174774.7 | H27: ='Equity Returns'!L33 -> 1231924.5 | I27: ='Equity Returns'!N33 -> 0.24243309 | J27: ='Equity Returns'!O33 -> 3.6779502 | K27: ='Equity Returns'!P33 -> 1607037.9

Sheet Acquisition
A1: ACQUISITION — SOURCES & USES
A2: Initial loan sized to the binding of LTV / DSCR / Debt-Yield tests on stabilized (Yr-3) NOI
A4: DEBT SIZING
A5: Stabilized NOI (Year 3) | B5: =Valuation!E7 -> 132685.85 | D5: Underwriting NOI for loan sizing
A6: Annual Loan Constant (amortizing) | B6: =-PMT(Assumptions!$B$88,Assumptions!$B$59,1)*12 -> 0.075848163 | D6: 12 × monthly PMT per $1
A7: Max Loan — by LTV | B7: =Assumptions!$B$58*Assumptions!$B$8 -> 910000
A8: Max Loan — by Debt Yield | B8: =IFERROR(B5/Assumptions!$B$64,0) -> 1658573.1
A9: Max Loan — by DSCR | B9: =IFERROR(B5/Assumptions!$B$63/B6,0) -> 1399489.1
A10: INITIAL LOAN (binding) | B10: =MIN(B7,B8,B9) -> 910000
A12: USES OF FUNDS
A13: Purchase Price | B13: =Assumptions!$B$8 -> 1300000
A14: Acquisition Costs | B14: =Assumptions!$B$87 -> 26000
A15: Financing Fees | B15: =Assumptions!$B$62*B10 -> 9100
A16: Initial CapEx | B16: =Assumptions!$B$56 -> 175000
A17: Other Uses | B17: 0
A18: TOTAL USES | B18: =SUM(B13:B17) -> 1510100
A20: SOURCES OF FUNDS
A21: Initial Loan | B21: =B10 -> 910000
A22: Other Sources | B22: 0
A23: Investor Equity (plug) | B23: =B18-B21-B22 -> 600100
A24: TOTAL SOURCES | B24: =SUM(B21:B23) -> 1510100
A26: Initial LTV (loan / price) | B26: =IFERROR(B10/Assumptions!$B$8,0) -> 0.7
A27: Check: Sources = Uses | B27: =IF(ABS(B24-B18)<1,"OK","ERROR") -> OK

Sheet Assumptions
A1: MOBILE HOME PARK — ACQUISITION & UNDERWRITING MODEL
A2: Assumptions & scenario levers | BLUE = editable input YELLOW = key assumption GREEN = pulled from another sheet
A4: SCENARIO CONTROL
A5: Active Scenario (1=Down 2=Base 3=Up) | B5: 2 | H5: Change this one cell to flip the whole model between cases.
A6: Scenario name | B6: =CHOOSE($B$5,"DOWNSIDE","BASE CASE","UPSIDE") -> BASE CASE | H6: Stabilized Physical Occupancy is the occupancy the park will achieve AFTER you finish your lease-up / infill, and it will stay there forever
A7: Scenario-driven levers | B7: Active (used) | D7: Downside | E7: Base | F7: Upside | H7: This is the industry standard for MHP. No park ever stabilizes at 100% because you always have 1-2 evictions, abandons, rehab. Institutional buyers use 90-95%. 92% is textbook.
A8: Purchase Price ($) | B8: =CHOOSE($B$5,D8,E8,F8) -> 1300000 | D8: 1450000 | E8: 1300000 | F8: 1200000 | H8: Placeholder — replace with LOI/contract price
A9: Stabilized Physical Occupancy | B9: 0.92 | D9: 0.85 | E9: 0.92 | F9: 0.95 | H9: Stabilized Physical Occupancy is the occupancy the park will achieve AFTER you finish your lease-up / infill, and it will stay there forever or The max occupancy your park will ever realistically hold long-term, after you finish fixing it
A10: Annual Rent Growth | B10: =CHOOSE($B$5,D10,E10,F10) -> 0.03 | D10: 0.02 | E10: 0.03 | F10: 0.04 | H10: This is the industry standard for MHP. No park ever stabilizes at 100% because you always have 1-2 evictions, abandons, rehab. Institutional buyers use 90-95%. 92% is textbook.
A11: Annual Expense Growth | B11: =CHOOSE($B$5,D11,E11,F11) -> 0.025 | D11: 0.035 | E11: 0.025 | F11: 0.02
A12: Exit Cap Rate | B12: =CHOOSE($B$5,D12,E12,F12) -> 0.065 | D12: 0.075 | E12: 0.065 | F12: 0.06 | H12: Exit Cap Rate = NOI at sale / Sale Price. | I12: Can I change NOI to get 5% exit cap? --> Confusion was Cap = NOI/Price means either can change.---> No we cannot change NOI. 2025 NOI is locked. At Jan 2026 sale, only Price is negotiable. Price = Fixed NOI / Target Cap.
A13: Initial Loan Interest Rate | B13: =CHOOSE($B$5,D13,E13,F13) -> 0.065 | D13: 0.075 | E13: 0.065 | F13: 0.06
A14: PROPERTY
A15: Acquisition Date | B15: =DATE(2026,1,1) -> 46023 | H15: First month of operations
A16: Total Pads / Lots | B16: 80 | H16: All rentable pads
A17: Occupied Pads (in-place) | B17: 60 | H17: Physical occupancy at close
A18: Vacant Pads | B18: =Assumptions!$B$16-Assumptions!$B$17 -> 20
A19: Park-Owned Homes (POH) — total | B19: 10 | H19: Homes owned by park (subset of pads)
A20: POH — occupied | B20: 8
A21: POH — vacant | B21: =Assumptions!$B$19-Assumptions!$B$20 -> 2
A22: REVENUE
A23: Lot Rent — in-place ($/pad/mo) | B23: 350 | H23: Blended in-place pad rent
A24: Lot Rent — market ($/pad/mo) | B24: 425 | H24: Loss-to-lease target. Loss-to-Lease = Rent you COULD charge minus Rent you DO charge. | M24: Do charge: $350
A25: POH Home Rent premium ($/home/mo) | B25: 350 | H25: Charged on top of lot rent for POH | M25: Could charge: $425
A26: Other Income ($/occ pad/mo) | B26: 20 | H26: Late fees, pet, utility admin, etc. | M26: Loss: $75 / pad
A27: Utility Reimbursement ($/occ pad/mo) | B27: 15 | H27: RUBS / direct bill-back
A28: Collection Loss / Bad Debt (% of gross) | B28: 0.01
A29: Lease-up Period (months to stabilize) | B29: 18 | H29: Occupancy ramps to stabilized over this period. Lease-up period= Time to fill empty lots.the initial period when a newly built, renovated, or repositioned rental property actively markets and fills its vacant units to reach stable occupancy | L29: 18 months to stabilize.
A30: Other-Income Growth | B30: 0.025
A31: OPERATING EXPENSES (Year-1 annual $)
A32: Property Taxes | B32: 45000
A33: Insurance | B33: 20000
A34: Electricity | B34: 12000
A35: Gas | B35: 3000
A36: Water | B36: 30000
A37: Sewer | B37: 25000
A38: Repairs & Maintenance | B38: 35000
A39: POH Insurance | B39: 4000
A40: POH Repairs / Home Maint. | B40: 8000
A41: Turnover / Make-ready | B41: 6000
A42: Administrative | B42: 10000
A43: Legal / Professional | B43: 5000
... A46: Other Operating | B46: 6000
A47: Management Fee (% of EGR) | B47: 0.05 | H47: Modeled as % of revenue, not fixed $. EGR = Effective Gross Revenue
A48: CAPITAL EXPENDITURES
A49: Replacement Reserve ($/pad/yr) | B49: 50
A50: Roads (one-time, month 1) | B50: 40000
A51: Water/Sewer Infrastructure (one-time) | B51: 60000
A52: Electrical (one-time) | B52: 20000
A53: Common-Area Improvements (one-time) | B53: 15000
A54: POH Renovations (one-time) | B54: 30000
A55: Other CapEx (one-time) | B55: 10000
A56: Total Initial CapEx (in Uses) | B56: =SUM(Assumptions!$B$50:$B$55) -> 175000 | H56: Funded at close via Sources & Uses
A57: FINANCING — INITIAL LOAN
A58: Initial LTV (max) | B58: 0.7
A59: Amortization (months) | B59: 360
A60: Loan Term (months) | B60: 120
A61: Interest-Only Period (months) | B61: 24
A62: Loan Fees (% of loan) | B62: 0.01
A63: DSCR Requirement (min) | B63: 1.25 | H63: DSCR = Annual NOI / Annual DS(Principal + Interest) | I63: $125k / $100k = 1.25, 1.25x also mean 125%.means for every $1.00 of debt payment(P+I), you have $1.25 of NOI. 100k ia the annual debt wservice., not the wholeloan amount.
A64: Debt Yield Requirement (min) | B64: 0.08 | H64: Debt Yield = NOI / Total Loan Amount | I64: $125,000 / $1,562000 = 0.08, So 8% is minimum rate which is reqired by ban. bank's panic button return. If you asked for $2.5M loan → return is only 5% (125k/2.5M) → Bank says: "5% is too low for the risk, I won't lend that much.Problem Statement: We buy Jan 2026. Bank gives loan based on projected Year 3 NOI $132k at 8% Debt Yield. Actual NOI at Dec 2026 is $50k (not $85k projected). Yield drops to 5.49% below 8% benchmar.Answer: Bank will not recall loan if you keep paying, but you are in technical default.DSCR 0.72x < 1.25x = covenant breach. Debt Yield 5.49% < 8% = covenant breach. Bank triggers cash sweep - zero distributions.Declare technical default - covenant breach. Charge extension fee 1% + higher rate
A65: Acquisition Costs (% of price) | B65: 0.02 | H65: Legal, DD, title, closing | I65: Total money to BUY the deal = Purchase Price + Closing + Lender Fees + Rehab + Initial Infills
A66: FINANCING — REFINANCE
A67: Model Refinance? (1=Yes 0=No) | B67: 1 | H67: Toggle refinance event
A68: Refinance Month | B68: 36
A69: Refinance LTV | B69: 0.7
A70: Refinance Interest Rate | B70: 0.06
A71: Refinance Amortization (months) | B71: 360
A72: Refinance Interest-Only (months) | B72: 0
A73: Refinance Fees (% of new loan) | B73: 0.01
A74: Refinance Cap Rate | B74: 0.062
A75: EXIT
A76: Exit Month (1–120) | B76: 60 | H76: Dynamic — Year = month/12
A77: Selling Costs (% of value) | B77: 0.03
A78: Exit / Disposition Fee (% of value) | B78: 0.01
A79: LP / GP WATERFALL
A80: LP Equity Share | B80: 0.9 | H80: LP (limited partner) | I80: Puts in 90% of cash, passive.
A81: GP Equity Share | B81: 0.1 | H81: GP( general partner) | I81: You (does all work.
A82: Preferred Return (annual, compounded) | B82: 0.08
A83: GP Catch-up (% to GP) | B83: 1
A84: Promote / Carry (GP over hurdle) | B84: 0.2
A85: DERIVED (calculated — do not edit)
A86: Max Loan by LTV | B86: =Assumptions!$B$58*Assumptions!$B$8 -> 910000
A87: Acquisition Costs ($) | B87: =Assumptions!$B$65*Assumptions!$B$8 -> 26000
A88: Initial monthly rate | B88: =Assumptions!$B$13/12 -> 0.0054166667
A89: Refi monthly rate | B89: =Assumptions!$B$70/12 -> 0.005

Sheet Equity Returns
A1: EQUITY RETURNS
A2: Annual levered cash flow to equity. IRR / equity multiple / cash-on-cash. Operations stop at the exit year.
A4: ($) | B4: Year 0 | C4: Year 1 | D4: Year 2 | E4: Year 3 | F4: Year 4 | G4: Year 5 | H4: Year 6 | I4: Year 7 | J4: Year 8 | K4: Year 9 | L4: Year 10
A5: NOI after CapEx | B5: - | C5: =SUM('Monthly Operations'!D42:O42) -> 81224.913 | D5: =SUM('Monthly Operations'!P42:AA42) -> 119435.64 | E5: =SUM('Monthly Operations'!AB42:AM42) -> 128483.35 | F5: =SUM('Monthly Operations'!AN42:AY42) -> 133473.68 | G5: =SUM('Monthly Operations'!AZ42:BK42) -> 138642.11 | H5: =SUM('Monthly Operations'!BL42:BW42) -> 143994.7 | I5: =SUM('Monthly Operations'!BX42:CI42) -> 149537.7 | J5: =SUM('Monthly Operations'!CJ42:CU42) -> 155277.57 | K5: =SUM('Monthly Operations'!CV42:DG42) -> 161220.98 | L5: =SUM('Monthly Operations'!DH42:DS42) -> 167374.82
A6: Debt Service | B6: - | C6: =-SUM('Debt Schedule'!D18:O18) -> -59150 | D6: =-SUM('Debt Schedule'!P18:AA18) -> -59150 | E6: =-SUM('Debt Schedule'!AB18:AM18) -> -72455.425 | F6: =-SUM('Debt Schedule'!AN18:AY18) -> -110224.99 | G6: =-SUM('Debt Schedule'!AZ18:BK18) -> -110224.99 | H6: =-SUM('Debt Schedule'!BL18:BW18) -> -110224.99 | I6: =-SUM('Debt Schedule'!BX18:CI18) -> -110224.99 | J6: =-SUM('Debt Schedule'!CJ18:CU18) -> -110224.99 | K6: =-SUM('Debt Schedule'!CV18:DG18) -> -110224.99 | L6: =-SUM('Debt Schedule'!DH18:DS18) -> -110224.99
A7: Operating CF (levered) | B7: - | C7: =C5+C6 -> 22074.913 | D7: =D5+D6 -> 60285.638 | E7: =E5+E6 -> 56027.925 | F7: =F5+F6 -> 23248.685 | G7: =G5+G6 -> 28417.118 | H7: =H5+H6 -> 33769.709 | I7: =I5+I6 -> 39312.711 | J7: =J5+J6 -> 45052.582 | ... L7: =L5+L6 -> 57149.832
A8: Refinance Proceeds | B8: - | C8: =IF(AND(Assumptions!$B$67=1,(INT((Assumptions!$B$68-1)/12)+1)=COLUMN(A1),(INT((Assumptions!$B$68-1)/12)+1)<=Exit!$B$6),Refinance!$B$14,0) -> 0 | D8: =IF(AND(Assumptions!$B$67=1,(INT((Assumptions!$B$68-1)/12)+1)=COLUMN(B1),(INT((Assumptions!$B$68-1)/12)+1)<=Exit!$B$6),Refinance!$B$14,0) -> 0 | E8: =IF(AND(Assumptions!$B$67=1,(INT((Assumptions!$B$68-1)/12)+1)=COLUMN(C1),(INT((Assumptions!$B$68-1)/12)+1)<=Exit!$B$6),Refinance!$B$14,0) -> 616028.14 | F8: =IF(AND(Assumptions!$B$67=1,(INT((Assumptions!$B$68-1)/12)+1)=COLUMN(D1),(INT((Assumptions!$B$68-1)/12)+1)<=Exit!$B$6),Refinance!$B$14,0) -> 0 | G8: =IF(AND(Assumptions!$B$67=1,(INT((Assumptions!$B$68-1)/12)+1)=COLUMN(E1),(INT((Assumptions!$B$68-1)/12)+1)<=Exit!$B$6),Refinance!$B$14,0) -> 0 | H8: =IF(AND(Assumptions!$B$67=1,(INT((Assumptions!$B$68-1)/12)+1)=COLUMN(F1),(INT((Assumptions!$B$68-1)/12)+1)<=Exit!$B$6),Refinance!$B$14,0) -> 0 | I8: =IF(AND(Assumptions!$B$67=1,(INT((Assumptions!$B$68-1)/12)+1)=COLUMN(G1),(INT((Assumptions!$B$68-1)/12)+1)<=Exit!$B$6),Refinance!$B$14,0) -> 0 | J8: =IF(AND(Assumptions!$B$67=1,(INT((Assumptions!$B$68-1)/12)+1)=COLUMN(H1),(INT((Assumptions!$B$68-1)/12)+1)<=Exit!$B$6),Refinance!$B$14,0) -> 0 | ... L8: =IF(AND(Assumptions!$B$67=1,(INT((Assumptions!$B$68-1)/12)+1)=COLUMN(J1),(INT((Assumptions!$B$68-1)/12)+1)<=Exit!$B$6),Refinance!$B$14,0) -> 0
A9: Net Sale Proceeds | B9: - | C9: =IF(1=Exit!$B$6,Exit!$B$13,0) -> 0 | D9: =IF(2=Exit!$B$6,Exit!$B$13,0) -> 0 | E9: =IF(3=Exit!$B$6,Exit!$B$13,0) -> 0 | F9: =IF(4=Exit!$B$6,Exit!$B$13,0) -> 0 | G9: =IF(5=Exit!$B$6,Exit!$B$13,0) -> 701987.73 | H9: =IF(6=Exit!$B$6,Exit!$B$13,0) -> 0 | I9: =IF(7=Exit!$B$6,Exit!$B$13,0) -> 0 | J9: =IF(8=Exit!$B$6,Exit!$B$13,0) -> 0 | K9: =IF(9=Exit!$B$6,Exit!$B$13,0) -> 0 | L9: =IF(10=Exit!$B$6,Exit!$B$13,0) -> 0
A10: Equity Contributed | B10: =-Acquisition!$B$23 -> -600100 | C10: - | D10: - | E10: - | F10: - | G10: - | H10: - | I10: - | J10: - | K10: - | L10: -
A11: NET CASH FLOW TO EQUITY | B11: =B10 -> -600100 | C11: =IF(1>Exit!$B$6,0,C7+C8)+C9 -> 22074.913 | D11: =IF(2>Exit!$B$6,0,D7+D8)+D9 -> 60285.638 | E11: =IF(3>Exit!$B$6,0,E7+E8)+E9 -> 672056.07 | F11: =IF(4>Exit!$B$6,0,F7+F8)+F9 -> 23248.685 | G11: =IF(5>Exit!$B$6,0,G7+G8)+G9 -> 730404.85 | H11: =IF(6>Exit!$B$6,0,H7+H8)+H9 -> 0 | I11: =IF(7>Exit!$B$6,0,I7+I8)+I9 -> 0 | J11: =IF(8>Exit!$B$6,0,J7+J8)+J9 -> 0 | K11: =IF(9>Exit!$B$6,0,K7+K8)+K9 -> 0 | L11: =IF(10>Exit!$B$6,0,L7+L8)+L9 -> 0
A12: Cumulative CF | B12: =B11 -> -600100 | C12: =B12+C11 -> -578025.09 | D12: =C12+D11 -> -517739.45 | E12: =D12+E11 -> 154316.62 | F12: =E12+F11 -> 177565.3 | G12: =F12+G11 -> 907970.15 | H12: =G12+H11 -> 907970.15 | I12: =H12+I11 -> 907970.15 | J12: =I12+J11 -> 907970.15 | ... L12: =K12+L11 -> 907970.15
A14: RETURN METRICS
A15: Equity Invested | B15: =Acquisition!$B$23 -> 600100
A16: Levered IRR | B16: =IFERROR(IRR(B11:L11),0) -> 0.27741656
A17: Equity Multiple (MOIC) | B17: =IFERROR(SUMIF(C11:L11,">0")/Acquisition!$B$23,0) -> 2.5130314 | E17: IF(C$23>$A24,0,C7+IF(ROUNDUP(Assumptions!$B$68/12,0)=C$23,Refinance!$B$14,0)+IF(C$23=$A24,Exit!G$18,0))
A18: Total Profit | B18: =SUM(C11:L11)-Acquisition!$B$23 -> 907970.15 | C18: =IF(AND(Assumptions!$B$67=1,(INT((Assumptions!$B$68-1)/12)+1)=COLUMN(A11),(INT((Assumptions!$B$68-1)/12)+1)<=Exit!$B$6),Refinance!$B$14,0) -> 0 | E18: IF(1<=1,C7+IF(AND(Assumptions!$B$67=1,1=(INT((Assumptions!$B$68-1)/12)+1),(INT((Assumptions!$B$68-1)/12)+1)<=1),Refinance!$B$14,0)+IF(1=1,Exit!G18,0),0)
A19: Avg Cash-on-Cash (operating) | B19: =IFERROR(AVERAGE(C7:L7)/Acquisition!$B$23,0) -> 0.069377621
A20: Hold Period (years) | B20: =Exit!$B$6 -> 5
A22: EXIT-YEAR CASH-FLOW MATRIX (row = sale year N; col = Year 0..10)
A23: Sale year ↓ | B23: Y0 | C23: 1 | D23: 2 | E23: 3 | F23: 4 | G23: 5 | H23: 6 | I23: 7 | J23: 8 | K23: 9 | L23: 10 | N23: IRR | O23: EM | P23: Profit
A24: 1 | B24: =-Acquisition!$B$23 -> -600100 | C24: =IF(C$23<=$A24,C7+IF(AND(Assumptions!$B$67=1,1=(INT((Assumptions!$B$68-1)/12)+1),(INT((Assumptions!$B$68-1)/12)+1)<=1),Refinance!$B$14,0)+IF(1=1,Exit!G18,0),0) -> 936601.25 | D24: =IF(2<=1,D7+IF(AND(Assumptions!$B$67=1,2=(INT((Assumptions!$B$68-1)/12)+1),(INT((Assumptions!$B$68-1)/12)+1)<=1),Refinance!$B$14,0)+IF(2=1,Exit!G18,0),0) -> 0 | E24: =IF(3<=1,E7+IF(AND(Assumptions!$B$67=1,3=(INT((Assumptions!$B$68-1)/12)+1),(INT((Assumptions!$B$68-1)/12)+1)<=1),Refinance!$B$14,0)+IF(3=1,Exit!G18,0),0) -> 0 | F24: =IF(4<=1,F7+IF(AND(Assumptions!$B$67=1,4=(INT((Assumptions!$B$68-1)/12)+1),(INT((Assumptions!$B$68-1)/12)+1)<=1),Refinance!$B$14,0)+IF(4=1,Exit!G18,0),0) -> 0 | G24: =IF(5<=1,G7+IF(AND(Assumptions!$B$67=1,5=(INT((Assumptions!$B$68-1)/12)+1),(INT((Assumptions!$B$68-1)/12)+1)<=1),Refinance!$B$14,0)+IF(5=1,Exit!G18,0),0) -> 0 | H24: =IF(6<=1,H7+IF(AND(Assumptions!$B$67=1,6=(INT((Assumptions!$B$68-1)/12)+1),(INT((Assumptions!$B$68-1)/12)+1)<=1),Refinance!$B$14,0)+IF(6=1,Exit!G18,0),0) -> 0 | I24: =IF(7<=1,I7+IF(AND(Assumptions!$B$67=1,7=(INT((Assumptions!$B$68-1)/12)+1),(INT((Assumptions!$B$68-1)/12)+1)<=1),Refinance!$B$14,0)+IF(7=1,Exit!G18,0),0) -> 0 | J24: =IF(8<=1,J7+IF(AND(Assumptions!$B$67=1,8=(INT((Assumptions!$B$68-1)/12)+1),(INT((Assumptions!$B$68-1)/12)+1)<=1),Refinance!$B$14,0)+IF(8=1,Exit!G18,0),0) -> 0 | K24: =IF(9<=1,K7+IF(AND(Assumptions!$B$67=1,9=(INT((Assumptions!$B$68-1)/12)+1),(INT((Assumptions!$B$68-1)/12)+1)<=1),Refinance!$B$14,0)+IF(9=1,Exit!G18,0),0) -> 0 | L24: =IF(10<=1,L7+IF(AND(Assumptions!$B$67=1,10=(INT((Assumptions!$B$68-1)/12)+1),(INT((Assumptions!$B$68-1)/12)+1)<=1),Refinance!$B$14,0)+IF(10=1,Exit!G18,0),0) -> 0 | N24: =IFERROR(IRR(B24:L24),0) -> 0.56074197 | O24: =IFERROR(SUMIF(C24:L24,">0")/Acquisition!$B$23,0) -> 1.560742 | P24: =SUM(C24:L24)-Acquisition!$B$23 -> 336501.25
A25: 2 | B25: =-Acquisition!$B$23 -> -600100 | C25: =IF(1<=2,C7+IF(AND(Assumptions!$B$67=1,1=(INT((Assumptions!$B$68-1)/12)+1),(INT((Assumptions!$B$68-1)/12)+1)<=2),Refinance!$B$14,0)+IF(1=2,Exit!G19,0),0) -> 22074.913 | D25: =IF(2<=2,D7+IF(AND(Assumptions!$B$67=1,2=(INT((Assumptions!$B$68-1)/12)+1),(INT((Assumptions!$B$68-1)/12)+1)<=2),Refinance!$B$14,0)+IF(2=2,Exit!G19,0),0) -> 1109953.6 | E25: =IF(3<=2,E7+IF(AND(Assumptions!$B$67=1,3=(INT((Assumptions!$B$68-1)/12)+1),(INT((Assumptions!$B$68-1)/12)+1)<=2),Refinance!$B$14,0)+IF(3=2,Exit!G19,0),0) -> 0 | F25: =IF(4<=2,F7+IF(AND(Assumptions!$B$67=1,4=(INT((Assumptions!$B$68-1)/12)+1),(INT((Assumptions!$B$68-1)/12)+1)<=2),Refinance!$B$14,0)+IF(4=2,Exit!G19,0),0) -> 0 | G25: =IF(5<=2,G7+IF(AND(Assumptions!$B$67=1,5=(INT((Assumptions!$B$68-1)/12)+1),(INT((Assumptions!$B$68-1)/12)+1)<=2),Refinance!$B$14,0)+IF(5=2,Exit!G19,0),0) -> 0 | H25: =IF(6<=2,H7+IF(AND(Assumptions!$B$67=1,6=(INT((Assumptions!$B$68-1)/12)+1),(INT((Assumptions!$B$68-1)/12)+1)<=2),Refinance!$B$14,0)+IF(6=2,Exit!G19,0),0) -> 0 | I25: =IF(7<=2,I7+IF(AND(Assumptions!$B$67=1,7=(INT((Assumptions!$B$68-1)/12)+1),(INT((Assumptions!$B$68-1)/12)+1)<=2),Refinance!$B$14,0)+IF(7=2,Exit!G19,0),0) -> 0 | J25: =IF(8<=2,J7+IF(AND(Assumptions!$B$67=1,8=(INT((Assumptions!$B$68-1)/12)+1),(INT((Assumptions!$B$68-1)/12)+1)<=2),Refinance!$B$14,0)+IF(8=2,Exit!G19,0),0) -> 0 | K25: =IF(9<=2,K7+IF(AND(Assumptions!$B$67=1,9=(INT((Assumptions!$B$68-1)/12)+1),(INT((Assumptions!$B$68-1)/12)+1)<=2),Refinance!$B$14,0)+IF(9=2,Exit!G19,0),0) -> 0 | L25: =IF(10<=2,L7+IF(AND(Assumptions!$B$67=1,10=(INT((Assumptions!$B$68-1)/12)+1),(INT((Assumptions!$B$68-1)/12)+1)<=2),Refinance!$B$14,0)+IF(10=2,Exit!G19,0),0) -> 0 | N25: =IFERROR(IRR(B25:L25),0) -> 0.37852234 | O25: =IFERROR(SUMIF(C25:L25,">0")/Acquisition!$B$23,0) -> 1.8863998 | P25: =SUM(C25:L25)-Acquisition!$B$23 -> 531928.49
A26: 3 | B26: =-Acquisition!$B$23 -> -600100 | C26: =IF(1<=3,C7+IF(AND(Assumptions!$B$67=1,1=(INT((Assumptions!$B$68-1)/12)+1),(INT((Assumptions!$B$68-1)/12)+1)<=3),Refinance!$B$14,0)+IF(1=3,Exit!G20,0),0) -> 22074.913 | D26: =IF(2<=3,D7+IF(AND(Assumptions!$B$67=1,2=(INT((Assumptions!$B$68-1)/12)+1),(INT((Assumptions!$B$68-1)/12)+1)<=3),Refinance!$B$14,0)+IF(2=3,Exit!G20,0),0) -> 60285.638 | E26: =IF(3<=3,E7+IF(AND(Assumptions!$B$67=1,3=(INT((Assumptions!$B$68-1)/12)+1),(INT((Assumptions!$B$68-1)/12)+1)<=3),Refinance!$B$14,0)+IF(3=3,Exit!G20,0),0) -> 1176453.8 | F26: =IF(4<=3,F7+IF(AND(Assumptions!$B$67=1,4=(INT((Assumptions!$B$68-1)/12)+1),(INT((Assumptions!$B$68-1)/12)+1)<=3),Refinance!$B$14,0)+IF(4=3,Exit!G20,0),0) -> 0 | G26: =IF(5<=3,G7+IF(AND(Assumptions!$B$67=1,5=(INT((Assumptions!$B$68-1)/12)+1),(INT((Assumptions!$B$68-1)/12)+1)<=3),Refinance!$B$14,0)+IF(5=3,Exit!G20,0),0) -> 0 | H26: =IF(6<=3,H7+IF(AND(Assumptions!$B$67=1,6=(INT((Assumptions!$B$68-1)/12)+1),(INT((Assumptions!$B$68-1)/12)+1)<=3),Refinance!$B$14,0)+IF(6=3,Exit!G20,0),0) -> 0 | I26: =IF(7<=3,I7+IF(AND(Assumptions!$B$67=1,7=(INT((Assumptions!$B$68-1)/12)+1),(INT((Assumptions!$B$68-1)/12)+1)<=3),Refinance!$B$14,0)+IF(7=3,Exit!G20,0),0) -> 0 | J26: =IF(8<=3,J7+IF(AND(Assumptions!$B$67=1,8=(INT((Assumptions!$B$68-1)/12)+1),(INT((Assumptions!$B$68-1)/12)+1)<=3),Refinance!$B$14,0)+IF(8=3,Exit!G20,0),0) -> 0 | K26: =IF(9<=3,K7+IF(AND(Assumptions!$B$67=1,9=(INT((Assumptions!$B$68-1)/12)+1),(INT((Assumptions!$B$68-1)/12)+1)<=3),Refinance!$B$14,0)+IF(9=3,Exit!G20,0),0) -> 0 | L26: =IF(10<=3,L7+IF(AND(Assumptions!$B$67=1,10=(INT((Assumptions!$B$68-1)/12)+1),(INT((Assumptions!$B$68-1)/12)+1)<=3),Refinance!$B$14,0)+IF(10=3,Exit!G20,0),0) -> 0 | N26: =IFERROR(IRR(B26:L26),0) -> 0.29094732 | O26: =IFERROR(SUMIF(C26:L26,">0")/Acquisition!$B$23,0) -> 2.0976743 | P26: =SUM(C26:L26)-Acquisition!$B$23 -> 658714.35
A27: 4 | B27: =-Acquisition!$B$23 -> -600100 | C27: =IF(1<=4,C7+IF(AND(Assumptions!$B$67=1,1=(INT((Assumptions!$B$68-1)/12)+1),(INT((Assumptions!$B$68-1)/12)+1)<=4),Refinance!$B$14,0)+IF(1=4,Exit!G21,0),0) -> 22074.913 | D27: =IF(2<=4,D7+IF(AND(Assumptions!$B$67=1,2=(INT((Assumptions!$B$68-1)/12)+1),(INT((Assumptions!$B$68-1)/12)+1)<=4),Refinance!$B$14,0)+IF(2=4,Exit!G21,0),0) -> 60285.638 | E27: =IF(3<=4,E7+IF(AND(Assumptions!$B$67=1,3=(INT((Assumptions!$B$68-1)/12)+1),(INT((Assumptions!$B$68-1)/12)+1)<=4),Refinance!$B$14,0)+IF(3=4,Exit!G21,0),0) -> 672056.07 | F27: =IF(4<=4,F7+IF(AND(Assumptions!$B$67=1,4=(INT((Assumptions!$B$68-1)/12)+1),(INT((Assumptions!$B$68-1)/12)+1)<=4),Refinance!$B$14,0)+IF(4=4,Exit!G21,0),0) -> 624478.5 | G27: =IF(5<=4,G7+IF(AND(Assumptions!$B$67=1,5=(INT((Assumptions!$B$68-1)/12)+1),(INT((Assumptions!$B$68-1)/12)+1)<=4),Refinance!$B$14,0)+IF(5=4,Exit!G21,0),0) -> 0 | H27: =IF(6<=4,H7+IF(AND(Assumptions!$B$67=1,6=(INT((Assumptions!$B$68-1)/12)+1),(INT((Assumptions!$B$68-1)/12)+1)<=4),Refinance!$B$14,0)+IF(6=4,Exit!G21,0),0) -> 0 | I27: =IF(7<=4,I7+IF(AND(Assumptions!$B$67=1,7=(INT((Assumptions!$B$68-1)/12)+1),(INT((Assumptions!$B$68-1)/12)+1)<=4),Refinance!$B$14,0)+IF(7=4,Exit!G21,0),0) -> 0 | J27: =IF(8<=4,J7+IF(AND(Assumptions!$B$67=1,8=(INT((Assumptions!$B$68-1)/12)+1),(INT((Assumptions!$B$68-1)/12)+1)<=4),Refinance!$B$14,0)+IF(8=4,Exit!G21,0),0) -> 0 | K27: =IF(9<=4,K7+IF(AND(Assumptions!$B$67=1,9=(INT((Assumptions!$B$68-1)/12)+1),(INT((Assumptions!$B$68-1)/12)+1)<=4),Refinance!$B$14,0)+IF(9=4,Exit!G21,0),0) -> 0 | L27: =IF(10<=4,L7+IF(AND(Assumptions!$B$67=1,10=(INT((Assumptions!$B$68-1)/12)+1),(INT((Assumptions!$B$68-1)/12)+1)<=4),Refinance!$B$14,0)+IF(10=4,Exit!G21,0),0) -> 0 | N27: =IFERROR(IRR(B27:L27),0) -> 0.28458014 | O27: =IFERROR(SUMIF(C27:L27,">0")/Acquisition!$B$23,0) -> 2.2977756 | P27: =SUM(C27:L27)-Acquisition!$B$23 -> 778795.11
A28: 5 | B28: =-Acquisition!$B$23 -> -600100 | C28: =IF(1<=5,C7+IF(AND(Assumptions!$B$67=1,1=(INT((Assumptions!$B$68-1)/12)+1),(INT((Assumptions!$B$68-1)/12)+1)<=5),Refinance!$B$14,0)+IF(1=5,Exit!G22,0),0) -> 22074.913 | D28: =IF(2<=5,D7+IF(AND(Assumptions!$B$67=1,2=(INT((Assumptions!$B$68-1)/12)+1),(INT((Assumptions!$B$68-1)/12)+1)<=5),Refinance!$B$14,0)+IF(2=5,Exit!G22,0),0) -> 60285.638 | E28: =IF(3<=5,E7+IF(AND(Assumptions!$B$67=1,3=(INT((Assumptions!$B$68-1)/12)+1),(INT((Assumptions!$B$68-1)/12)+1)<=5),Refinance!$B$14,0)+IF(3=5,Exit!G22,0),0) -> 672056.07 | F28: =IF(4<=5,F7+IF(AND(Assumptions!$B$67=1,4=(INT((Assumptions!$B$68-1)/12)+1),(INT((Assumptions!$B$68-1)/12)+1)<=5),Refinance!$B$14,0)+IF(4=5,Exit!G22,0),0) -> 23248.685 | G28: =IF(5<=5,G7+IF(AND(Assumptions!$B$67=1,5=(INT((Assumptions!$B$68-1)/12)+1),(INT((Assumptions!$B$68-1)/12)+1)<=5),Refinance!$B$14,0)+IF(5=5,Exit!G22,0),0) -> 730404.85 | H28: =IF(6<=5,H7+IF(AND(Assumptions!$B$67=1,6=(INT((Assumptions!$B$68-1)/12)+1),(INT((Assumptions!$B$68-1)/12)+1)<=5),Refinance!$B$14,0)+IF(6=5,Exit!G22,0),0) -> 0 | I28: =IF(7<=5,I7+IF(AND(Assumptions!$B$67=1,7=(INT((Assumptions!$B$68-1)/12)+1),(INT((Assumptions!$B$68-1)/12)+1)<=5),Refinance!$B$14,0)+IF(7=5,Exit!G22,0),0) -> 0 | J28: =IF(8<=5,J7+IF(AND(Assumptions!$B$67=1,8=(INT((Assumptions!$B$68-1)/12)+1),(INT((Assumptions!$B$68-1)/12)+1)<=5),Refinance!$B$14,0)+IF(8=5,Exit!G22,0),0) -> 0 | K28: =IF(9<=5,K7+IF(AND(Assumptions!$B$67=1,9=(INT((Assumptions!$B$68-1)/12)+1),(INT((Assumptions!$B$68-1)/12)+1)<=5),Refinance!$B$14,0)+IF(9=5,Exit!G22,0),0) -> 0 | L28: =IF(10<=5,L7+IF(AND(Assumptions!$B$67=1,10=(INT((Assumptions!$B$68-1)/12)+1),(INT((Assumptions!$B$68-1)/12)+1)<=5),Refinance!$B$14,0)+IF(10=5,Exit!G22,0),0) -> 0 | N28: =IFERROR(IRR(B28:L28),0) -> 0.27741656 | O28: =IFERROR(SUMIF(C28:L28,">0")/Acquisition!$B$23,0) -> 2.5130314 | P28: =SUM(C28:L28)-Acquisition!$B$23 -> 907970.15
A29: 6 | B29: =-Acquisition!$B$23 -> -600100 | C29: =IF(1<=6,C7+IF(AND(Assumptions!$B$67=1,1=(INT((Assumptions!$B$68-1)/12)+1),(INT((Assumptions!$B$68-1)/12)+1)<=6),Refinance!$B$14,0)+IF(1=6,Exit!G23,0),0) -> 22074.913 | D29: =IF(2<=6,D7+IF(AND(Assumptions!$B$67=1,2=(INT((Assumptions!$B$68-1)/12)+1),(INT((Assumptions!$B$68-1)/12)+1)<=6),Refinance!$B$14,0)+IF(2=6,Exit!G23,0),0) -> 60285.638 | E29: =IF(3<=6,E7+IF(AND(Assumptions!$B$67=1,3=(INT((Assumptions!$B$68-1)/12)+1),(INT((Assumptions!$B$68-1)/12)+1)<=6),Refinance!$B$14,0)+IF(3=6,Exit!G23,0),0) -> 672056.07 | F29: =IF(4<=6,F7+IF(AND(Assumptions!$B$67=1,4=(INT((Assumptions!$B$68-1)/12)+1),(INT((Assumptions!$B$68-1)/12)+1)<=6),Refinance!$B$14,0)+IF(4=6,Exit!G23,0),0) -> 23248.685 | G29: =IF(5<=6,G7+IF(AND(Assumptions!$B$67=1,5=(INT((Assumptions!$B$68-1)/12)+1),(INT((Assumptions!$B$68-1)/12)+1)<=6),Refinance!$B$14,0)+IF(5=6,Exit!G23,0),0) -> 28417.118 | H29: =IF(6<=6,H7+IF(AND(Assumptions!$B$67=1,6=(INT((Assumptions!$B$68-1)/12)+1),(INT((Assumptions!$B$68-1)/12)+1)<=6),Refinance!$B$14,0)+IF(6=6,Exit!G23,0),0) -> 840606.46 | I29: =IF(7<=6,I7+IF(AND(Assumptions!$B$67=1,7=(INT((Assumptions!$B$68-1)/12)+1),(INT((Assumptions!$B$68-1)/12)+1)<=6),Refinance!$B$14,0)+IF(7=6,Exit!G23,0),0) -> 0 | J29: =IF(8<=6,J7+IF(AND(Assumptions!$B$67=1,8=(INT((Assumptions!$B$68-1)/12)+1),(INT((Assumptions!$B$68-1)/12)+1)<=6),Refinance!$B$14,0)+IF(8=6,Exit!G23,0),0) -> 0 | K29: =IF(9<=6,K7+IF(AND(Assumptions!$B$67=1,9=(INT((Assumptions!$B$68-1)/12)+1),(INT((Assumptions!$B$68-1)/12)+1)<=6),Refinance!$B$14,0)+IF(9=6,Exit!G23,0),0) -> 0 | L29: =IF(10<=6,L7+IF(AND(Assumptions!$B$67=1,10=(INT((Assumptions!$B$68-1)/12)+1),(INT((Assumptions!$B$68-1)/12)+1)<=6),Refinance!$B$14,0)+IF(10=6,Exit!G23,0),0) -> 0 | N29: =IFERROR(IRR(B29:L29),0) -> 0.27033933 | O29: =IFERROR(SUMIF(C29:L29,">0")/Acquisition!$B$23,0) -> 2.7440241 | P29: =SUM(C29:L29)-Acquisition!$B$23 -> 1046588.9
A30: 7 | B30: =-Acquisition!$B$23 -> -600100 | C30: =IF(1<=7,C7+IF(AND(Assumptions!$B$67=1,1=(INT((Assumptions!$B$68-1)/12)+1),(INT((Assumptions!$B$68-1)/12)+1)<=7),Refinance!$B$14,0)+IF(1=7,Exit!G24,0),0) -> 22074.913 | D30: =IF(2<=7,D7+IF(AND(Assumptions!$B$67=1,2=(INT((Assumptions!$B$68-1)/12)+1),(INT((Assumptions!$B$68-1)/12)+1)<=7),Refinance!$B$14,0)+IF(2=7,Exit!G24,0),0) -> 60285.638 | E30: =IF(3<=7,E7+IF(AND(Assumptions!$B$67=1,3=(INT((Assumptions!$B$68-1)/12)+1),(INT((Assumptions!$B$68-1)/12)+1)<=7),Refinance!$B$14,0)+IF(3=7,Exit!G24,0),0) -> 672056.07 | F30: =IF(4<=7,F7+IF(AND(Assumptions!$B$67=1,4=(INT((Assumptions!$B$68-1)/12)+1),(INT((Assumptions!$B$68-1)/12)+1)<=7),Refinance!$B$14,0)+IF(4=7,Exit!G24,0),0) -> 23248.685 | G30: =IF(5<=7,G7+IF(AND(Assumptions!$B$67=1,5=(INT((Assumptions!$B$68-1)/12)+1),(INT((Assumptions!$B$68-1)/12)+1)<=7),Refinance!$B$14,0)+IF(5=7,Exit!G24,0),0) -> 28417.118 | H30: =IF(6<=7,H7+IF(AND(Assumptions!$B$67=1,6=(INT((Assumptions!$B$68-1)/12)+1),(INT((Assumptions!$B$68-1)/12)+1)<=7),Refinance!$B$14,0)+IF(6=7,Exit!G24,0),0) -> 33769.709 | I30: =IF(7<=7,I7+IF(AND(Assumptions!$B$67=1,7=(INT((Assumptions!$B$68-1)/12)+1),(INT((Assumptions!$B$68-1)/12)+1)<=7),Refinance!$B$14,0)+IF(7=7,Exit!G24,0),0) -> 955262.35 | J30: =IF(8<=7,J7+IF(AND(Assumptions!$B$67=1,8=(INT((Assumptions!$B$68-1)/12)+1),(INT((Assumptions!$B$68-1)/12)+1)<=7),Refinance!$B$14,0)+IF(8=7,Exit!G24,0),0) -> 0 | K30: =IF(9<=7,K7+IF(AND(Assumptions!$B$67=1,9=(INT((Assumptions!$B$68-1)/12)+1),(INT((Assumptions!$B$68-1)/12)+1)<=7),Refinance!$B$14,0)+IF(9=7,Exit!G24,0),0) -> 0 | L30: =IF(10<=7,L7+IF(AND(Assumptions!$B$67=1,10=(INT((Assumptions!$B$68-1)/12)+1),(INT((Assumptions!$B$68-1)/12)+1)<=7),Refinance!$B$14,0)+IF(10=7,Exit!G24,0),0) -> 0 | N30: =IFERROR(IRR(B30:L30),0) -> 0.26369184 | O30: =IFERROR(SUMIF(C30:L30,">0")/Acquisition!$B$23,0) -> 2.9913589 | P30: =SUM(C30:L30)-Acquisition!$B$23 -> 1195014.5
A31: 8 | B31: =-Acquisition!$B$23 -> -600100 | C31: =IF(1<=8,C7+IF(AND(Assumptions!$B$67=1,1=(INT((Assumptions!$B$68-1)/12)+1),(INT((Assumptions!$B$68-1)/12)+1)<=8),Refinance!$B$14,0)+IF(1=8,Exit!G25,0),0) -> 22074.913 | D31: =IF(2<=8,D7+IF(AND(Assumptions!$B$67=1,2=(INT((Assumptions!$B$68-1)/12)+1),(INT((Assumptions!$B$68-1)/12)+1)<=8),Refinance!$B$14,0)+IF(2=8,Exit!G25,0),0) -> 60285.638 | E31: =IF(3<=8,E7+IF(AND(Assumptions!$B$67=1,3=(INT((Assumptions!$B$68-1)/12)+1),(INT((Assumptions!$B$68-1)/12)+1)<=8),Refinance!$B$14,0)+IF(3=8,Exit!G25,0),0) -> 672056.07 | F31: =IF(4<=8,F7+IF(AND(Assumptions!$B$67=1,4=(INT((Assumptions!$B$68-1)/12)+1),(INT((Assumptions!$B$68-1)/12)+1)<=8),Refinance!$B$14,0)+IF(4=8,Exit!G25,0),0) -> 23248.685 | G31: =IF(5<=8,G7+IF(AND(Assumptions!$B$67=1,5=(INT((Assumptions!$B$68-1)/12)+1),(INT((Assumptions!$B$68-1)/12)+1)<=8),Refinance!$B$14,0)+IF(5=8,Exit!G25,0),0) -> 28417.118 | H31: =IF(6<=8,H7+IF(AND(Assumptions!$B$67=1,6=(INT((Assumptions!$B$68-1)/12)+1),(INT((Assumptions!$B$68-1)/12)+1)<=8),Refinance!$B$14,0)+IF(6=8,Exit!G25,0),0) -> 33769.709 | I31: =IF(7<=8,I7+IF(AND(Assumptions!$B$67=1,7=(INT((Assumptions!$B$68-1)/12)+1),(INT((Assumptions!$B$68-1)/12)+1)<=8),Refinance!$B$14,0)+IF(7=8,Exit!G25,0),0) -> 39312.711 | J31: =IF(8<=8,J7+IF(AND(Assumptions!$B$67=1,8=(INT((Assumptions!$B$68-1)/12)+1),(INT((Assumptions!$B$68-1)/12)+1)<=8),Refinance!$B$14,0)+IF(8=8,Exit!G25,0),0) -> 1074559.6 | K31: =IF(9<=8,K7+IF(AND(Assumptions!$B$67=1,9=(INT((Assumptions!$B$68-1)/12)+1),(INT((Assumptions!$B$68-1)/12)+1)<=8),Refinance!$B$14,0)+IF(9=8,Exit!G25,0),0) -> 0 | L31: =IF(10<=8,L7+IF(AND(Assumptions!$B$67=1,10=(INT((Assumptions!$B$68-1)/12)+1),(INT((Assumptions!$B$68-1)/12)+1)<=8),Refinance!$B$14,0)+IF(10=8,Exit!G25,0),0) -> 0 | N31: =IFERROR(IRR(B31:L31),0) -> 0.25758924 | O31: =IFERROR(SUMIF(C31:L31,">0")/Acquisition!$B$23,0) -> 3.2556648 | P31: =SUM(C31:L31)-Acquisition!$B$23 -> 1353624.4
A32: 9 | B32: =-Acquisition!$B$23 -> -600100 | C32: =IF(1<=9,C7+IF(AND(Assumptions!$B$67=1,1=(INT((Assumptions!$B$68-1)/12)+1),(INT((Assumptions!$B$68-1)/12)+1)<=9),Refinance!$B$14,0)+IF(1=9,Exit!G26,0),0) -> 22074.913 | D32: =IF(2<=9,D7+IF(AND(Assumptions!$B$67=1,2=(INT((Assumptions!$B$68-1)/12)+1),(INT((Assumptions!$B$68-1)/12)+1)<=9),Refinance!$B$14,0)+IF(2=9,Exit!G26,0),0) -> 60285.638 | E32: =IF(3<=9,E7+IF(AND(Assumptions!$B$67=1,3=(INT((Assumptions!$B$68-1)/12)+1),(INT((Assumptions!$B$68-1)/12)+1)<=9),Refinance!$B$14,0)+IF(3=9,Exit!G26,0),0) -> 672056.07 | F32: =IF(4<=9,F7+IF(AND(Assumptions!$B$67=1,4=(INT((Assumptions!$B$68-1)/12)+1),(INT((Assumptions!$B$68-1)/12)+1)<=9),Refinance!$B$14,0)+IF(4=9,Exit!G26,0),0) -> 23248.685 | G32: =IF(5<=9,G7+IF(AND(Assumptions!$B$67=1,5=(INT((Assumptions!$B$68-1)/12)+1),(INT((Assumptions!$B$68-1)/12)+1)<=9),Refinance!$B$14,0)+IF(5=9,Exit!G26,0),0) -> 28417.118 | H32: =IF(6<=9,H7+IF(AND(Assumptions!$B$67=1,6=(INT((Assumptions!$B$68-1)/12)+1),(INT((Assumptions!$B$68-1)/12)+1)<=9),Refinance!$B$14,0)+IF(6=9,Exit!G26,0),0) -> 33769.709 | I32: =IF(7<=9,I7+IF(AND(Assumptions!$B$67=1,7=(INT((Assumptions!$B$68-1)/12)+1),(INT((Assumptions!$B$68-1)/12)+1)<=9),Refinance!$B$14,0)+IF(7=9,Exit!G26,0),0) -> 39312.711 | J32: =IF(8<=9,J7+IF(AND(Assumptions!$B$67=1,8=(INT((Assumptions!$B$68-1)/12)+1),(INT((Assumptions!$B$68-1)/12)+1)<=9),Refinance!$B$14,0)+IF(8=9,Exit!G26,0),0) -> 45052.582 | K32: =IF(9<=9,K7+IF(AND(Assumptions!$B$67=1,9=(INT((Assumptions!$B$68-1)/12)+1),(INT((Assumptions!$B$68-1)/12)+1)<=9),Refinance!$B$14,0)+IF(9=9,Exit!G26,0),0) -> 1198693.8 | L32: =IF(10<=9,L7+IF(AND(Assumptions!$B$67=1,10=(INT((Assumptions!$B$68-1)/12)+1),(INT((Assumptions!$B$68-1)/12)+1)<=9),Refinance!$B$14,0)+IF(10=9,Exit!G26,0),0) -> 0 | N32: =IFERROR(IRR(B32:L32),0) -> 0.2520483 | O32: =IFERROR(SUMIF(C32:L32,">0")/Acquisition!$B$23,0) -> 3.5375958 | P32: =SUM(C32:L32)-Acquisition!$B$23 -> 1522811.2
A33: 10 | B33: =-Acquisition!$B$23 -> -600100 | C33: =IF(1<=10,C7+IF(AND(Assumptions!$B$67=1,1=(INT((Assumptions!$B$68-1)/12)+1),(INT((Assumptions!$B$68-1)/12)+1)<=10),Refinance!$B$14,0)+IF(1=10,Exit!G27,0),0) -> 22074.913 | D33: =IF(2<=10,D7+IF(AND(Assumptions!$B$67=1,2=(INT((Assumptions!$B$68-1)/12)+1),(INT((Assumptions!$B$68-1)/12)+1)<=10),Refinance!$B$14,0)+IF(2=10,Exit!G27,0),0) -> 60285.638 | E33: =IF(3<=10,E7+IF(AND(Assumptions!$B$67=1,3=(INT((Assumptions!$B$68-1)/12)+1),(INT((Assumptions!$B$68-1)/12)+1)<=10),Refinance!$B$14,0)+IF(3=10,Exit!G27,0),0) -> 672056.07 | F33: =IF(4<=10,F7+IF(AND(Assumptions!$B$67=1,4=(INT((Assumptions!$B$68-1)/12)+1),(INT((Assumptions!$B$68-1)/12)+1)<=10),Refinance!$B$14,0)+IF(4=10,Exit!G27,0),0) -> 23248.685 | G33: =IF(5<=10,G7+IF(AND(Assumptions!$B$67=1,5=(INT((Assumptions!$B$68-1)/12)+1),(INT((Assumptions!$B$68-1)/12)+1)<=10),Refinance!$B$14,0)+IF(5=10,Exit!G27,0),0) -> 28417.118 | H33: =IF(6<=10,H7+IF(AND(Assumptions!$B$67=1,6=(INT((Assumptions!$B$68-1)/12)+1),(INT((Assumptions!$B$68-1)/12)+1)<=10),Refinance!$B$14,0)+IF(6=10,Exit!G27,0),0) -> 33769.709 | I33: =IF(7<=10,I7+IF(AND(Assumptions!$B$67=1,7=(INT((Assumptions!$B$68-1)/12)+1),(INT((Assumptions!$B$68-1)/12)+1)<=10),Refinance!$B$14,0)+IF(7=10,Exit!G27,0),0) -> 39312.711 | J33: =IF(8<=10,J7+IF(AND(Assumptions!$B$67=1,8=(INT((Assumptions!$B$68-1)/12)+1),(INT((Assumptions!$B$68-1)/12)+1)<=10),Refinance!$B$14,0)+IF(8=10,Exit!G27,0),0) -> 45052.582 | K33: =IF(9<=10,K7+IF(AND(Assumptions!$B$67=1,9=(INT((Assumptions!$B$68-1)/12)+1),(INT((Assumptions!$B$68-1)/12)+1)<=10),Refinance!$B$14,0)+IF(9=10,Exit!G27,0),0) -> 50995.992 | L33: =IF(10<=10,L7+IF(AND(Assumptions!$B$67=1,10=(INT((Assumptions!$B$68-1)/12)+1),(INT((Assumptions!$B$68-1)/12)+1)<=10),Refinance!$B$14,0)+IF(10=10,Exit!G27,0),0) -> 1231924.5 | N33: =IFERROR(IRR(B33:L33),0) -> 0.24243309 | O33: =IFERROR(SUMIF(C33:L33,">0")/Acquisition!$B$23,0) -> 3.6779502 | P33: =SUM(C33:L33)-Acquisition!$B$23 -> 1607037.9

Sheet Equity Returns (2)
A1: EQUITY RETURNS
A2: Annual levered cash flow to equity. IRR / equity multiple / cash-on-cash. Operations stop at the exit year.
A4: ($) | B4: Year 0 | C4: Year 1 | D4: Year 2 | E4: Year 3 | F4: Year 4 | G4: Year 5 | H4: Year 6 | I4: Year 7 | J4: Year 8 | K4: Year 9 | L4: Year 10
A5: NOI after CapEx | B5: - | C5: =SUM('Monthly Operations'!D42:O42) -> 81224.913 | D5: =SUM('Monthly Operations'!P42:AA42) -> 119435.64 | E5: =SUM('Monthly Operations'!AB42:AM42) -> 128483.35 | F5: =SUM('Monthly Operations'!AN42:AY42) -> 133473.68 | G5: =SUM('Monthly Operations'!AZ42:BK42) -> 138642.11 | H5: =SUM('Monthly Operations'!BL42:BW42) -> 143994.7 | I5: =SUM('Monthly Operations'!BX42:CI42) -> 149537.7 | J5: =SUM('Monthly Operations'!CJ42:CU42) -> 155277.57 | K5: =SUM('Monthly Operations'!CV42:DG42) -> 161220.98 | L5: =SUM('Monthly Operations'!DH42:DS42) -> 167374.82
A6: Debt Service | B6: - | C6: =-SUM('Debt Schedule'!D18:O18) -> -59150 | D6: =-SUM('Debt Schedule'!P18:AA18) -> -59150 | E6: =-SUM('Debt Schedule'!AB18:AM18) -> -72455.425 | F6: =-SUM('Debt Schedule'!AN18:AY18) -> -110224.99 | G6: =-SUM('Debt Schedule'!AZ18:BK18) -> -110224.99 | H6: =-SUM('Debt Schedule'!BL18:BW18) -> -110224.99 | I6: =-SUM('Debt Schedule'!BX18:CI18) -> -110224.99 | J6: =-SUM('Debt Schedule'!CJ18:CU18) -> -110224.99 | K6: =-SUM('Debt Schedule'!CV18:DG18) -> -110224.99 | L6: =-SUM('Debt Schedule'!DH18:DS18) -> -110224.99
A7: Operating CF (levered) | B7: - | C7: =C5+C6 -> 22074.913 | D7: =D5+D6 -> 60285.638 | E7: =E5+E6 -> 56027.925 | F7: =F5+F6 -> 23248.685 | G7: =G5+G6 -> 28417.118 | H7: =H5+H6 -> 33769.709 | I7: =I5+I6 -> 39312.711 | J7: =J5+J6 -> 45052.582 | ... L7: =L5+L6 -> 57149.832
A8: Refinance Proceeds | B8: - | C8: =IF(AND(Assumptions!$B$67=1,(INT((Assumptions!$B$68-1)/12)+1)=COLUMN(A1),(INT((Assumptions!$B$68-1)/12)+1)<=Exit!$B$6),Refinance!$B$14,0) -> 0 | D8: =IF(AND(Assumptions!$B$67=1,(INT((Assumptions!$B$68-1)/12)+1)=COLUMN(B1),(INT((Assumptions!$B$68-1)/12)+1)<=Exit!$B$6),Refinance!$B$14,0) -> 0 | E8: =IF(AND(Assumptions!$B$67=1,(INT((Assumptions!$B$68-1)/12)+1)=COLUMN(C1),(INT((Assumptions!$B$68-1)/12)+1)<=Exit!$B$6),Refinance!$B$14,0) -> 616028.14 | F8: =IF(AND(Assumptions!$B$67=1,(INT((Assumptions!$B$68-1)/12)+1)=COLUMN(D1),(INT((Assumptions!$B$68-1)/12)+1)<=Exit!$B$6),Refinance!$B$14,0) -> 0 | G8: =IF(AND(Assumptions!$B$67=1,(INT((Assumptions!$B$68-1)/12)+1)=COLUMN(E1),(INT((Assumptions!$B$68-1)/12)+1)<=Exit!$B$6),Refinance!$B$14,0) -> 0 | H8: =IF(AND(Assumptions!$B$67=1,(INT((Assumptions!$B$68-1)/12)+1)=COLUMN(F1),(INT((Assumptions!$B$68-1)/12)+1)<=Exit!$B$6),Refinance!$B$14,0) -> 0 | I8: =IF(AND(Assumptions!$B$67=1,(INT((Assumptions!$B$68-1)/12)+1)=COLUMN(G1),(INT((Assumptions!$B$68-1)/12)+1)<=Exit!$B$6),Refinance!$B$14,0) -> 0 | J8: =IF(AND(Assumptions!$B$67=1,(INT((Assumptions!$B$68-1)/12)+1)=COLUMN(H1),(INT((Assumptions!$B$68-1)/12)+1)<=Exit!$B$6),Refinance!$B$14,0) -> 0 | ... L8: =IF(AND(Assumptions!$B$67=1,(INT((Assumptions!$B$68-1)/12)+1)=COLUMN(J1),(INT((Assumptions!$B$68-1)/12)+1)<=Exit!$B$6),Refinance!$B$14,0) -> 0
A9: Net Sale Proceeds | B9: - | C9: =IF(1=Exit!$B$6,Exit!$B$13,0) -> 0 | D9: =IF(2=Exit!$B$6,Exit!$B$13,0) -> 0 | E9: =IF(3=Exit!$B$6,Exit!$B$13,0) -> 0 | F9: =IF(4=Exit!$B$6,Exit!$B$13,0) -> 0 | G9: =IF(5=Exit!$B$6,Exit!$B$13,0) -> 701987.73 | H9: =IF(6=Exit!$B$6,Exit!$B$13,0) -> 0 | I9: =IF(7=Exit!$B$6,Exit!$B$13,0) -> 0 | J9: =IF(8=Exit!$B$6,Exit!$B$13,0) -> 0 | K9: =IF(9=Exit!$B$6,Exit!$B$13,0) -> 0 | L9: =IF(10=Exit!$B$6,Exit!$B$13,0) -> 0
A10: Equity Contributed | B10: =-Acquisition!$B$23 -> -600100 | C10: - | D10: - | E10: - | F10: - | G10: - | H10: - | I10: - | J10: - | K10: - | L10: -
A11: NET CASH FLOW TO EQUITY | B11: =B10 -> -600100 | C11: =IF(1>Exit!$B$6,0,C7+C8)+C9 -> 22074.913 | D11: =IF(2>Exit!$B$6,0,D7+D8)+D9 -> 60285.638 | E11: =IF(3>Exit!$B$6,0,E7+E8)+E9 -> 672056.07 | F11: =IF(4>Exit!$B$6,0,F7+F8)+F9 -> 23248.685 | G11: =IF(5>Exit!$B$6,0,G7+G8)+G9 -> 730404.85 | H11: =IF(6>Exit!$B$6,0,H7+H8)+H9 -> 0 | I11: =IF(7>Exit!$B$6,0,I7+I8)+I9 -> 0 | J11: =IF(8>Exit!$B$6,0,J7+J8)+J9 -> 0 | K11: =IF(9>Exit!$B$6,0,K7+K8)+K9 -> 0 | L11: =IF(10>Exit!$B$6,0,L7+L8)+L9 -> 0
A12: Cumulative CF | B12: =B11 -> -600100 | C12: =B12+C11 -> -578025.09 | D12: =C12+D11 -> -517739.45 | E12: =D12+E11 -> 154316.62 | F12: =E12+F11 -> 177565.3 | G12: =F12+G11 -> 907970.15 | H12: =G12+H11 -> 907970.15 | I12: =H12+I11 -> 907970.15 | J12: =I12+J11 -> 907970.15 | ... L12: =K12+L11 -> 907970.15
A14: RETURN METRICS
A15: Equity Invested | B15: =Acquisition!$B$23 -> 600100
A16: Levered IRR | B16: =IFERROR(IRR(B11:L11),0) -> 0.27741656
A17: Equity Multiple (MOIC) | B17: =IFERROR(SUMIF(C11:L11,">0")/Acquisition!$B$23,0) -> 2.5130314 | E17: IF(C$23>$A24,0,C7+IF(ROUNDUP(Assumptions!$B$68/12,0)=C$23,Refinance!$B$14,0)+IF(C$23=$A24,Exit!G$18,0))
A18: Total Profit | B18: =SUM(C11:L11)-Acquisition!$B$23 -> 907970.15 | C18: =IF(AND(Assumptions!$B$67=1,(INT((Assumptions!$B$68-1)/12)+1)=COLUMN(A11),(INT((Assumptions!$B$68-1)/12)+1)<=Exit!$B$6),Refinance!$B$14,0) -> 0 | E18: IF(1<=1,C7+IF(AND(Assumptions!$B$67=1,1=(INT((Assumptions!$B$68-1)/12)+1),(INT((Assumptions!$B$68-1)/12)+1)<=1),Refinance!$B$14,0)+IF(1=1,Exit!G18,0),0)
A19: Avg Cash-on-Cash (operating) | B19: =IFERROR(AVERAGE(C7:L7)/Acquisition!$B$23,0) -> 0.069377621
A20: Hold Period (years) | B20: =Exit!$B$6 -> 5
A22: EXIT-YEAR CASH-FLOW MATRIX (row = sale year N; col = Year 0..10)
C23: Year | D23: Year | E23: Year | F23: Year | G23: Year | H23: Year | I23: Year | J23: Year | K23: Year | L23: Year
A24: Sale year ↓ | B24: Y0 | C24: 1 | D24: 2 | E24: 3 | F24: 4 | G24: 5 | H24: 6 | I24: 7 | J24: 8 | K24: 9 | L24: 10 | N24: IRR | O24: EM | P24: Profit
A25: 1 | B25: =-Acquisition!$B$23 -> -600100 | C25: =IF(C$24<=$A25,C$7+IF(AND(Assumptions!$B$67=1,C$24=(INT((Assumptions!$B$68-1)/12)+1),(INT((Assumptions!$B$68-1)/12)+1)<=$A25),Refinance!$B$14,0)+IF(C$24=$A25,Exit!$G18,0),0) -> 936601.25 | D25: =IF(D$24<=$A25,D$7+IF(AND(Assumptions!$B$67=1,D$24=(INT((Assumptions!$B$68-1)/12)+1),(INT((Assumptions!$B$68-1)/12)+1)<=$A25),Refinance!$B$14,0)+IF(D$24=$A25,Exit!H18,0),0) -> 0 | E25: =IF(E$24<=$A25,E$7+IF(AND(Assumptions!$B$67=1,E$24=(INT((Assumptions!$B$68-1)/12)+1),(INT((Assumptions!$B$68-1)/12)+1)<=$A25),Refinance!$B$14,0)+IF(E$24=$A25,Exit!I18,0),0) -> 0 | F25: =IF(F$24<=$A25,F$7+IF(AND(Assumptions!$B$67=1,F$24=(INT((Assumptions!$B$68-1)/12)+1),(INT((Assumptions!$B$68-1)/12)+1)<=$A25),Refinance!$B$14,0)+IF(F$24=$A25,Exit!J18,0),0) -> 0 | G25: =IF(G$24<=$A25,G$7+IF(AND(Assumptions!$B$67=1,G$24=(INT((Assumptions!$B$68-1)/12)+1),(INT((Assumptions!$B$68-1)/12)+1)<=$A25),Refinance!$B$14,0)+IF(G$24=$A25,Exit!$G18,0),0) -> 0 | H25: =IF(H$24<=$A25,H$7+IF(AND(Assumptions!$B$67=1,H$24=(INT((Assumptions!$B$68-1)/12)+1),(INT((Assumptions!$B$68-1)/12)+1)<=$A25),Refinance!$B$14,0)+IF(H$24=$A25,Exit!$G18,0),0) -> 0 | I25: =IF(I$24<=$A25,I$7+IF(AND(Assumptions!$B$67=1,I$24=(INT((Assumptions!$B$68-1)/12)+1),(INT((Assumptions!$B$68-1)/12)+1)<=$A25),Refinance!$B$14,0)+IF(I$24=$A25,Exit!$G18,0),0) -> 0 | J25: =IF(J$24<=$A25,J$7+IF(AND(Assumptions!$B$67=1,J$24=(INT((Assumptions!$B$68-1)/12)+1),(INT((Assumptions!$B$68-1)/12)+1)<=$A25),Refinance!$B$14,0)+IF(J$24=$A25,Exit!$G18,0),0) -> 0 | K25: =IF(K$24<=$A25,K$7+IF(AND(Assumptions!$B$67=1,K$24=(INT((Assumptions!$B$68-1)/12)+1),(INT((Assumptions!$B$68-1)/12)+1)<=$A25),Refinance!$B$14,0)+IF(K$24=$A25,Exit!$G18,0),0) -> 0 | L25: =IF(L$24<=$A25,L$7+IF(AND(Assumptions!$B$67=1,L$24=(INT((Assumptions!$B$68-1)/12)+1),(INT((Assumptions!$B$68-1)/12)+1)<=$A25),Refinance!$B$14,0)+IF(L$24=$A25,Exit!$G18,0),0) -> 0 | N25: =IFERROR(IRR(B25:L25),0) -> 0.56074197 | O25: =IFERROR(SUMIF(C25:L25,">0")/Acquisition!$B$23,0) -> 1.560742 | P25: =SUM(C25:L25)-Acquisition!$B$23 -> 336501.25
A26: 2 | B26: =-Acquisition!$B$23 -> -600100 | C26: =IF(C$24<=$A26,C$7+IF(AND(Assumptions!$B$67=1,C$24=(INT((Assumptions!$B$68-1)/12)+1),(INT((Assumptions!$B$68-1)/12)+1)<=$A26),Refinance!$B$14,0)+IF(C$24=$A26,Exit!$G19,0),0) -> 22074.913 | D26: =IF(D$24<=$A26,D$7+IF(AND(Assumptions!$B$67=1,D$24=(INT((Assumptions!$B$68-1)/12)+1),(INT((Assumptions!$B$68-1)/12)+1)<=$A26),Refinance!$B$14,0)+IF(D$24=$A26,Exit!$G19,0),0) -> 1109953.6 | E26: =IF(E$24<=$A26,E$7+IF(AND(Assumptions!$B$67=1,E$24=(INT((Assumptions!$B$68-1)/12)+1),(INT((Assumptions!$B$68-1)/12)+1)<=$A26),Refinance!$B$14,0)+IF(E$24=$A26,Exit!$G19,0),0) -> 0 | F26: =IF(F$24<=$A26,F$7+IF(AND(Assumptions!$B$67=1,F$24=(INT((Assumptions!$B$68-1)/12)+1),(INT((Assumptions!$B$68-1)/12)+1)<=$A26),Refinance!$B$14,0)+IF(F$24=$A26,Exit!$G19,0),0) -> 0 | G26: =IF(G$24<=$A26,G$7+IF(AND(Assumptions!$B$67=1,G$24=(INT((Assumptions!$B$68-1)/12)+1),(INT((Assumptions!$B$68-1)/12)+1)<=$A26),Refinance!$B$14,0)+IF(G$24=$A26,Exit!$G19,0),0) -> 0 | H26: =IF(H$24<=$A26,H$7+IF(AND(Assumptions!$B$67=1,H$24=(INT((Assumptions!$B$68-1)/12)+1),(INT((Assumptions!$B$68-1)/12)+1)<=$A26),Refinance!$B$14,0)+IF(H$24=$A26,Exit!$G19,0),0) -> 0 | I26: =IF(I$24<=$A26,I$7+IF(AND(Assumptions!$B$67=1,I$24=(INT((Assumptions!$B$68-1)/12)+1),(INT((Assumptions!$B$68-1)/12)+1)<=$A26),Refinance!$B$14,0)+IF(I$24=$A26,Exit!$G19,0),0) -> 0 | J26: =IF(J$24<=$A26,J$7+IF(AND(Assumptions!$B$67=1,J$24=(INT((Assumptions!$B$68-1)/12)+1),(INT((Assumptions!$B$68-1)/12)+1)<=$A26),Refinance!$B$14,0)+IF(J$24=$A26,Exit!$G19,0),0) -> 0 | ... L26: =IF(L$24<=$A26,L$7+IF(AND(Assumptions!$B$67=1,L$24=(INT((Assumptions!$B$68-1)/12)+1),(INT((Assumptions!$B$68-1)/12)+1)<=$A26),Refinance!$B$14,0)+IF(L$24=$A26,Exit!$G19,0),0) -> 0 | N26: =IFERROR(IRR(B26:L26),0) -> 0.37852234 | O26: =IFERROR(SUMIF(C26:L26,">0")/Acquisition!$B$23,0) -> 1.8863998 | P26: =SUM(C26:L26)-Acquisition!$B$23 -> 531928.49
A27: 3 | B27: =-Acquisition!$B$23 -> -600100 | C27: =IF(C$24<=$A27,C$7+IF(AND(Assumptions!$B$67=1,C$24=(INT((Assumptions!$B$68-1)/12)+1),(INT((Assumptions!$B$68-1)/12)+1)<=$A27),Refinance!$B$14,0)+IF(C$24=$A27,Exit!$G20,0),0) -> 22074.913 | D27: =IF(D$24<=$A27,D$7+IF(AND(Assumptions!$B$67=1,D$24=(INT((Assumptions!$B$68-1)/12)+1),(INT((Assumptions!$B$68-1)/12)+1)<=$A27),Refinance!$B$14,0)+IF(D$24=$A27,Exit!$G20,0),0) -> 60285.638 | E27: =IF(E$24<=$A27,E$7+IF(AND(Assumptions!$B$67=1,E$24=(INT((Assumptions!$B$68-1)/12)+1),(INT((Assumptions!$B$68-1)/12)+1)<=$A27),Refinance!$B$14,0)+IF(E$24=$A27,Exit!$G20,0),0) -> 1176453.8 | F27: =IF(F$24<=$A27,F$7+IF(AND(Assumptions!$B$67=1,F$24=(INT((Assumptions!$B$68-1)/12)+1),(INT((Assumptions!$B$68-1)/12)+1)<=$A27),Refinance!$B$14,0)+IF(F$24=$A27,Exit!$G20,0),0) -> 0 | G27: =IF(G$24<=$A27,G$7+IF(AND(Assumptions!$B$67=1,G$24=(INT((Assumptions!$B$68-1)/12)+1),(INT((Assumptions!$B$68-1)/12)+1)<=$A27),Refinance!$B$14,0)+IF(G$24=$A27,Exit!$G20,0),0) -> 0 | H27: =IF(H$24<=$A27,H$7+IF(AND(Assumptions!$B$67=1,H$24=(INT((Assumptions!$B$68-1)/12)+1),(INT((Assumptions!$B$68-1)/12)+1)<=$A27),Refinance!$B$14,0)+IF(H$24=$A27,Exit!$G20,0),0) -> 0 | I27: =IF(I$24<=$A27,I$7+IF(AND(Assumptions!$B$67=1,I$24=(INT((Assumptions!$B$68-1)/12)+1),(INT((Assumptions!$B$68-1)/12)+1)<=$A27),Refinance!$B$14,0)+IF(I$24=$A27,Exit!$G20,0),0) -> 0 | J27: =IF(J$24<=$A27,J$7+IF(AND(Assumptions!$B$67=1,J$24=(INT((Assumptions!$B$68-1)/12)+1),(INT((Assumptions!$B$68-1)/12)+1)<=$A27),Refinance!$B$14,0)+IF(J$24=$A27,Exit!$G20,0),0) -> 0 | ... L27: =IF(L$24<=$A27,L$7+IF(AND(Assumptions!$B$67=1,L$24=(INT((Assumptions!$B$68-1)/12)+1),(INT((Assumptions!$B$68-1)/12)+1)<=$A27),Refinance!$B$14,0)+IF(L$24=$A27,Exit!$G20,0),0) -> 0 | N27: =IFERROR(IRR(B27:L27),0) -> 0.29094732 | O27: =IFERROR(SUMIF(C27:L27,">0")/Acquisition!$B$23,0) -> 2.0976743 | P27: =SUM(C27:L27)-Acquisition!$B$23 -> 658714.35
A28: 4 | B28: =-Acquisition!$B$23 -> -600100 | C28: =IF(C$24<=$A28,C$7+IF(AND(Assumptions!$B$67=1,C$24=(INT((Assumptions!$B$68-1)/12)+1),(INT((Assumptions!$B$68-1)/12)+1)<=$A28),Refinance!$B$14,0)+IF(C$24=$A28,Exit!$G21,0),0) -> 22074.913 | D28: =IF(D$24<=$A28,D$7+IF(AND(Assumptions!$B$67=1,D$24=(INT((Assumptions!$B$68-1)/12)+1),(INT((Assumptions!$B$68-1)/12)+1)<=$A28),Refinance!$B$14,0)+IF(D$24=$A28,Exit!$G21,0),0) -> 60285.638 | E28: =IF(E$24<=$A28,E$7+IF(AND(Assumptions!$B$67=1,E$24=(INT((Assumptions!$B$68-1)/12)+1),(INT((Assumptions!$B$68-1)/12)+1)<=$A28),Refinance!$B$14,0)+IF(E$24=$A28,Exit!$G21,0),0) -> 672056.07 | F28: =IF(F$24<=$A28,F$7+IF(AND(Assumptions!$B$67=1,F$24=(INT((Assumptions!$B$68-1)/12)+1),(INT((Assumptions!$B$68-1)/12)+1)<=$A28),Refinance!$B$14,0)+IF(F$24=$A28,Exit!$G21,0),0) -> 624478.5 | G28: =IF(G$24<=$A28,G$7+IF(AND(Assumptions!$B$67=1,G$24=(INT((Assumptions!$B$68-1)/12)+1),(INT((Assumptions!$B$68-1)/12)+1)<=$A28),Refinance!$B$14,0)+IF(G$24=$A28,Exit!$G21,0),0) -> 0 | H28: =IF(H$24<=$A28,H$7+IF(AND(Assumptions!$B$67=1,H$24=(INT((Assumptions!$B$68-1)/12)+1),(INT((Assumptions!$B$68-1)/12)+1)<=$A28),Refinance!$B$14,0)+IF(H$24=$A28,Exit!$G21,0),0) -> 0 | I28: =IF(I$24<=$A28,I$7+IF(AND(Assumptions!$B$67=1,I$24=(INT((Assumptions!$B$68-1)/12)+1),(INT((Assumptions!$B$68-1)/12)+1)<=$A28),Refinance!$B$14,0)+IF(I$24=$A28,Exit!$G21,0),0) -> 0 | J28: =IF(J$24<=$A28,J$7+IF(AND(Assumptions!$B$67=1,J$24=(INT((Assumptions!$B$68-1)/12)+1),(INT((Assumptions!$B$68-1)/12)+1)<=$A28),Refinance!$B$14,0)+IF(J$24=$A28,Exit!$G21,0),0) -> 0 | ... L28: =IF(L$24<=$A28,L$7+IF(AND(Assumptions!$B$67=1,L$24=(INT((Assumptions!$B$68-1)/12)+1),(INT((Assumptions!$B$68-1)/12)+1)<=$A28),Refinance!$B$14,0)+IF(L$24=$A28,Exit!$G21,0),0) -> 0 | N28: =IFERROR(IRR(B28:L28),0) -> 0.28458014 | O28: =IFERROR(SUMIF(C28:L28,">0")/Acquisition!$B$23,0) -> 2.2977756 | P28: =SUM(C28:L28)-Acquisition!$B$23 -> 778795.11
A29: 5 | B29: =-Acquisition!$B$23 -> -600100 | C29: =IF(C$24<=$A29,C$7+IF(AND(Assumptions!$B$67=1,C$24=(INT((Assumptions!$B$68-1)/12)+1),(INT((Assumptions!$B$68-1)/12)+1)<=$A29),Refinance!$B$14,0)+IF(C$24=$A29,Exit!$G22,0),0) -> 22074.913 | D29: =IF(D$24<=$A29,D$7+IF(AND(Assumptions!$B$67=1,D$24=(INT((Assumptions!$B$68-1)/12)+1),(INT((Assumptions!$B$68-1)/12)+1)<=$A29),Refinance!$B$14,0)+IF(D$24=$A29,Exit!$G22,0),0) -> 60285.638 | E29: =IF(E$24<=$A29,E$7+IF(AND(Assumptions!$B$67=1,E$24=(INT((Assumptions!$B$68-1)/12)+1),(INT((Assumptions!$B$68-1)/12)+1)<=$A29),Refinance!$B$14,0)+IF(E$24=$A29,Exit!$G22,0),0) -> 672056.07 | F29: =IF(F$24<=$A29,F$7+IF(AND(Assumptions!$B$67=1,F$24=(INT((Assumptions!$B$68-1)/12)+1),(INT((Assumptions!$B$68-1)/12)+1)<=$A29),Refinance!$B$14,0)+IF(F$24=$A29,Exit!$G22,0),0) -> 23248.685 | G29: =IF(G$24<=$A29,G$7+IF(AND(Assumptions!$B$67=1,G$24=(INT((Assumptions!$B$68-1)/12)+1),(INT((Assumptions!$B$68-1)/12)+1)<=$A29),Refinance!$B$14,0)+IF(G$24=$A29,Exit!$G22,0),0) -> 730404.85 | H29: =IF(H$24<=$A29,H$7+IF(AND(Assumptions!$B$67=1,H$24=(INT((Assumptions!$B$68-1)/12)+1),(INT((Assumptions!$B$68-1)/12)+1)<=$A29),Refinance!$B$14,0)+IF(H$24=$A29,Exit!$G22,0),0) -> 0 | I29: =IF(I$24<=$A29,I$7+IF(AND(Assumptions!$B$67=1,I$24=(INT((Assumptions!$B$68-1)/12)+1),(INT((Assumptions!$B$68-1)/12)+1)<=$A29),Refinance!$B$14,0)+IF(I$24=$A29,Exit!$G22,0),0) -> 0 | J29: =IF(J$24<=$A29,J$7+IF(AND(Assumptions!$B$67=1,J$24=(INT((Assumptions!$B$68-1)/12)+1),(INT((Assumptions!$B$68-1)/12)+1)<=$A29),Refinance!$B$14,0)+IF(J$24=$A29,Exit!$G22,0),0) -> 0 | ... L29: =IF(L$24<=$A29,L$7+IF(AND(Assumptions!$B$67=1,L$24=(INT((Assumptions!$B$68-1)/12)+1),(INT((Assumptions!$B$68-1)/12)+1)<=$A29),Refinance!$B$14,0)+IF(L$24=$A29,Exit!$G22,0),0) -> 0 | N29: =IFERROR(IRR(B29:L29),0) -> 0.27741656 | O29: =IFERROR(SUMIF(C29:L29,">0")/Acquisition!$B$23,0) -> 2.5130314 | P29: =SUM(C29:L29)-Acquisition!$B$23 -> 907970.15
A30: 6 | B30: =-Acquisition!$B$23 -> -600100 | C30: =IF(C$24<=$A30,C$7+IF(AND(Assumptions!$B$67=1,C$24=(INT((Assumptions!$B$68-1)/12)+1),(INT((Assumptions!$B$68-1)/12)+1)<=$A30),Refinance!$B$14,0)+IF(C$24=$A30,Exit!$G23,0),0) -> 22074.913 | D30: =IF(D$24<=$A30,D$7+IF(AND(Assumptions!$B$67=1,D$24=(INT((Assumptions!$B$68-1)/12)+1),(INT((Assumptions!$B$68-1)/12)+1)<=$A30),Refinance!$B$14,0)+IF(D$24=$A30,Exit!$G23,0),0) -> 60285.638 | E30: =IF(E$24<=$A30,E$7+IF(AND(Assumptions!$B$67=1,E$24=(INT((Assumptions!$B$68-1)/12)+1),(INT((Assumptions!$B$68-1)/12)+1)<=$A30),Refinance!$B$14,0)+IF(E$24=$A30,Exit!$G23,0),0) -> 672056.07 | F30: =IF(F$24<=$A30,F$7+IF(AND(Assumptions!$B$67=1,F$24=(INT((Assumptions!$B$68-1)/12)+1),(INT((Assumptions!$B$68-1)/12)+1)<=$A30),Refinance!$B$14,0)+IF(F$24=$A30,Exit!$G23,0),0) -> 23248.685 | G30: =IF(G$24<=$A30,G$7+IF(AND(Assumptions!$B$67=1,G$24=(INT((Assumptions!$B$68-1)/12)+1),(INT((Assumptions!$B$68-1)/12)+1)<=$A30),Refinance!$B$14,0)+IF(G$24=$A30,Exit!$G23,0),0) -> 28417.118 | H30: =IF(H$24<=$A30,H$7+IF(AND(Assumptions!$B$67=1,H$24=(INT((Assumptions!$B$68-1)/12)+1),(INT((Assumptions!$B$68-1)/12)+1)<=$A30),Refinance!$B$14,0)+IF(H$24=$A30,Exit!$G23,0),0) -> 840606.46 | I30: =IF(I$24<=$A30,I$7+IF(AND(Assumptions!$B$67=1,I$24=(INT((Assumptions!$B$68-1)/12)+1),(INT((Assumptions!$B$68-1)/12)+1)<=$A30),Refinance!$B$14,0)+IF(I$24=$A30,Exit!$G23,0),0) -> 0 | J30: =IF(J$24<=$A30,J$7+IF(AND(Assumptions!$B$67=1,J$24=(INT((Assumptions!$B$68-1)/12)+1),(INT((Assumptions!$B$68-1)/12)+1)<=$A30),Refinance!$B$14,0)+IF(J$24=$A30,Exit!$G23,0),0) -> 0 | ... L30: =IF(L$24<=$A30,L$7+IF(AND(Assumptions!$B$67=1,L$24=(INT((Assumptions!$B$68-1)/12)+1),(INT((Assumptions!$B$68-1)/12)+1)<=$A30),Refinance!$B$14,0)+IF(L$24=$A30,Exit!$G23,0),0) -> 0 | N30: =IFERROR(IRR(B30:L30),0) -> 0.27033933 | O30: =IFERROR(SUMIF(C30:L30,">0")/Acquisition!$B$23,0) -> 2.7440241 | P30: =SUM(C30:L30)-Acquisition!$B$23 -> 1046588.9
A31: 7 | B31: =-Acquisition!$B$23 -> -600100 | C31: =IF(C$24<=$A31,C$7+IF(AND(Assumptions!$B$67=1,C$24=(INT((Assumptions!$B$68-1)/12)+1),(INT((Assumptions!$B$68-1)/12)+1)<=$A31),Refinance!$B$14,0)+IF(C$24=$A31,Exit!$G24,0),0) -> 22074.913 | D31: =IF(D$24<=$A31,D$7+IF(AND(Assumptions!$B$67=1,D$24=(INT((Assumptions!$B$68-1)/12)+1),(INT((Assumptions!$B$68-1)/12)+1)<=$A31),Refinance!$B$14,0)+IF(D$24=$A31,Exit!$G24,0),0) -> 60285.638 | E31: =IF(E$24<=$A31,E$7+IF(AND(Assumptions!$B$67=1,E$24=(INT((Assumptions!$B$68-1)/12)+1),(INT((Assumptions!$B$68-1)/12)+1)<=$A31),Refinance!$B$14,0)+IF(E$24=$A31,Exit!$G24,0),0) -> 672056.07 | F31: =IF(F$24<=$A31,F$7+IF(AND(Assumptions!$B$67=1,F$24=(INT((Assumptions!$B$68-1)/12)+1),(INT((Assumptions!$B$68-1)/12)+1)<=$A31),Refinance!$B$14,0)+IF(F$24=$A31,Exit!$G24,0),0) -> 23248.685 | G31: =IF(G$24<=$A31,G$7+IF(AND(Assumptions!$B$67=1,G$24=(INT((Assumptions!$B$68-1)/12)+1),(INT((Assumptions!$B$68-1)/12)+1)<=$A31),Refinance!$B$14,0)+IF(G$24=$A31,Exit!$G24,0),0) -> 28417.118 | H31: =IF(H$24<=$A31,H$7+IF(AND(Assumptions!$B$67=1,H$24=(INT((Assumptions!$B$68-1)/12)+1),(INT((Assumptions!$B$68-1)/12)+1)<=$A31),Refinance!$B$14,0)+IF(H$24=$A31,Exit!$G24,0),0) -> 33769.709 | I31: =IF(I$24<=$A31,I$7+IF(AND(Assumptions!$B$67=1,I$24=(INT((Assumptions!$B$68-1)/12)+1),(INT((Assumptions!$B$68-1)/12)+1)<=$A31),Refinance!$B$14,0)+IF(I$24=$A31,Exit!$G24,0),0) -> 955262.35 | J31: =IF(J$24<=$A31,J$7+IF(AND(Assumptions!$B$67=1,J$24=(INT((Assumptions!$B$68-1)/12)+1),(INT((Assumptions!$B$68-1)/12)+1)<=$A31),Refinance!$B$14,0)+IF(J$24=$A31,Exit!$G24,0),0) -> 0 | ... L31: =IF(L$24<=$A31,L$7+IF(AND(Assumptions!$B$67=1,L$24=(INT((Assumptions!$B$68-1)/12)+1),(INT((Assumptions!$B$68-1)/12)+1)<=$A31),Refinance!$B$14,0)+IF(L$24=$A31,Exit!$G24,0),0) -> 0 | N31: =IFERROR(IRR(B31:L31),0) -> 0.26369184 | O31: =IFERROR(SUMIF(C31:L31,">0")/Acquisition!$B$23,0) -> 2.9913589 | P31: =SUM(C31:L31)-Acquisition!$B$23 -> 1195014.5
A32: 8 | B32: =-Acquisition!$B$23 -> -600100 | C32: =IF(C$24<=$A32,C$7+IF(AND(Assumptions!$B$67=1,C$24=(INT((Assumptions!$B$68-1)/12)+1),(INT((Assumptions!$B$68-1)/12)+1)<=$A32),Refinance!$B$14,0)+IF(C$24=$A32,Exit!$G25,0),0) -> 22074.913 | D32: =IF(D$24<=$A32,D$7+IF(AND(Assumptions!$B$67=1,D$24=(INT((Assumptions!$B$68-1)/12)+1),(INT((Assumptions!$B$68-1)/12)+1)<=$A32),Refinance!$B$14,0)+IF(D$24=$A32,Exit!$G25,0),0) -> 60285.638 | E32: =IF(E$24<=$A32,E$7+IF(AND(Assumptions!$B$67=1,E$24=(INT((Assumptions!$B$68-1)/12)+1),(INT((Assumptions!$B$68-1)/12)+1)<=$A32),Refinance!$B$14,0)+IF(E$24=$A32,Exit!$G25,0),0) -> 672056.07 | F32: =IF(F$24<=$A32,F$7+IF(AND(Assumptions!$B$67=1,F$24=(INT((Assumptions!$B$68-1)/12)+1),(INT((Assumptions!$B$68-1)/12)+1)<=$A32),Refinance!$B$14,0)+IF(F$24=$A32,Exit!$G25,0),0) -> 23248.685 | G32: =IF(G$24<=$A32,G$7+IF(AND(Assumptions!$B$67=1,G$24=(INT((Assumptions!$B$68-1)/12)+1),(INT((Assumptions!$B$68-1)/12)+1)<=$A32),Refinance!$B$14,0)+IF(G$24=$A32,Exit!$G25,0),0) -> 28417.118 | H32: =IF(H$24<=$A32,H$7+IF(AND(Assumptions!$B$67=1,H$24=(INT((Assumptions!$B$68-1)/12)+1),(INT((Assumptions!$B$68-1)/12)+1)<=$A32),Refinance!$B$14,0)+IF(H$24=$A32,Exit!$G25,0),0) -> 33769.709 | I32: =IF(I$24<=$A32,I$7+IF(AND(Assumptions!$B$67=1,I$24=(INT((Assumptions!$B$68-1)/12)+1),(INT((Assumptions!$B$68-1)/12)+1)<=$A32),Refinance!$B$14,0)+IF(I$24=$A32,Exit!$G25,0),0) -> 39312.711 | J32: =IF(J$24<=$A32,J$7+IF(AND(Assumptions!$B$67=1,J$24=(INT((Assumptions!$B$68-1)/12)+1),(INT((Assumptions!$B$68-1)/12)+1)<=$A32),Refinance!$B$14,0)+IF(J$24=$A32,Exit!$G25,0),0) -> 1074559.6 | ... L32: =IF(L$24<=$A32,L$7+IF(AND(Assumptions!$B$67=1,L$24=(INT((Assumptions!$B$68-1)/12)+1),(INT((Assumptions!$B$68-1)/12)+1)<=$A32),Refinance!$B$14,0)+IF(L$24=$A32,Exit!$G25,0),0) -> 0 | N32: =IFERROR(IRR(B32:L32),0) -> 0.25758924 | O32: =IFERROR(SUMIF(C32:L32,">0")/Acquisition!$B$23,0) -> 3.2556648 | P32: =SUM(C32:L32)-Acquisition!$B$23 -> 1353624.4
A33: 9 | B33: =-Acquisition!$B$23 -> -600100 | C33: =IF(C$24<=$A33,C$7+IF(AND(Assumptions!$B$67=1,C$24=(INT((Assumptions!$B$68-1)/12)+1),(INT((Assumptions!$B$68-1)/12)+1)<=$A33),Refinance!$B$14,0)+IF(C$24=$A33,Exit!$G26,0),0) -> 22074.913 | D33: =IF(D$24<=$A33,D$7+IF(AND(Assumptions!$B$67=1,D$24=(INT((Assumptions!$B$68-1)/12)+1),(INT((Assumptions!$B$68-1)/12)+1)<=$A33),Refinance!$B$14,0)+IF(D$24=$A33,Exit!$G26,0),0) -> 60285.638 | E33: =IF(E$24<=$A33,E$7+IF(AND(Assumptions!$B$67=1,E$24=(INT((Assumptions!$B$68-1)/12)+1),(INT((Assumptions!$B$68-1)/12)+1)<=$A33),Refinance!$B$14,0)+IF(E$24=$A33,Exit!$G26,0),0) -> 672056.07 | F33: =IF(F$24<=$A33,F$7+IF(AND(Assumptions!$B$67=1,F$24=(INT((Assumptions!$B$68-1)/12)+1),(INT((Assumptions!$B$68-1)/12)+1)<=$A33),Refinance!$B$14,0)+IF(F$24=$A33,Exit!$G26,0),0) -> 23248.685 | G33: =IF(G$24<=$A33,G$7+IF(AND(Assumptions!$B$67=1,G$24=(INT((Assumptions!$B$68-1)/12)+1),(INT((Assumptions!$B$68-1)/12)+1)<=$A33),Refinance!$B$14,0)+IF(G$24=$A33,Exit!$G26,0),0) -> 28417.118 | H33: =IF(H$24<=$A33,H$7+IF(AND(Assumptions!$B$67=1,H$24=(INT((Assumptions!$B$68-1)/12)+1),(INT((Assumptions!$B$68-1)/12)+1)<=$A33),Refinance!$B$14,0)+IF(H$24=$A33,Exit!$G26,0),0) -> 33769.709 | I33: =IF(I$24<=$A33,I$7+IF(AND(Assumptions!$B$67=1,I$24=(INT((Assumptions!$B$68-1)/12)+1),(INT((Assumptions!$B$68-1)/12)+1)<=$A33),Refinance!$B$14,0)+IF(I$24=$A33,Exit!$G26,0),0) -> 39312.711 | J33: =IF(J$24<=$A33,J$7+IF(AND(Assumptions!$B$67=1,J$24=(INT((Assumptions!$B$68-1)/12)+1),(INT((Assumptions!$B$68-1)/12)+1)<=$A33),Refinance!$B$14,0)+IF(J$24=$A33,Exit!$G26,0),0) -> 45052.582 | ... L33: =IF(L$24<=$A33,L$7+IF(AND(Assumptions!$B$67=1,L$24=(INT((Assumptions!$B$68-1)/12)+1),(INT((Assumptions!$B$68-1)/12)+1)<=$A33),Refinance!$B$14,0)+IF(L$24=$A33,Exit!$G26,0),0) -> 0 | N33: =IFERROR(IRR(B33:L33),0) -> 0.2520483 | O33: =IFERROR(SUMIF(C33:L33,">0")/Acquisition!$B$23,0) -> 3.5375958 | P33: =SUM(C33:L33)-Acquisition!$B$23 -> 1522811.2
A34: 10 | B34: =-Acquisition!$B$23 -> -600100 | C34: =IF(C$24<=$A34,C$7+IF(AND(Assumptions!$B$67=1,C$24=(INT((Assumptions!$B$68-1)/12)+1),(INT((Assumptions!$B$68-1)/12)+1)<=$A34),Refinance!$B$14,0)+IF(C$24=$A34,Exit!$G27,0),0) -> 22074.913 | D34: =IF(D$24<=$A34,D$7+IF(AND(Assumptions!$B$67=1,D$24=(INT((Assumptions!$B$68-1)/12)+1),(INT((Assumptions!$B$68-1)/12)+1)<=$A34),Refinance!$B$14,0)+IF(D$24=$A34,Exit!$G27,0),0) -> 60285.638 | E34: =IF(E$24<=$A34,E$7+IF(AND(Assumptions!$B$67=1,E$24=(INT((Assumptions!$B$68-1)/12)+1),(INT((Assumptions!$B$68-1)/12)+1)<=$A34),Refinance!$B$14,0)+IF(E$24=$A34,Exit!$G27,0),0) -> 672056.07 | F34: =IF(F$24<=$A34,F$7+IF(AND(Assumptions!$B$67=1,F$24=(INT((Assumptions!$B$68-1)/12)+1),(INT((Assumptions!$B$68-1)/12)+1)<=$A34),Refinance!$B$14,0)+IF(F$24=$A34,Exit!$G27,0),0) -> 23248.685 | G34: =IF(G$24<=$A34,G$7+IF(AND(Assumptions!$B$67=1,G$24=(INT((Assumptions!$B$68-1)/12)+1),(INT((Assumptions!$B$68-1)/12)+1)<=$A34),Refinance!$B$14,0)+IF(G$24=$A34,Exit!$G27,0),0) -> 28417.118 | H34: =IF(H$24<=$A34,H$7+IF(AND(Assumptions!$B$67=1,H$24=(INT((Assumptions!$B$68-1)/12)+1),(INT((Assumptions!$B$68-1)/12)+1)<=$A34),Refinance!$B$14,0)+IF(H$24=$A34,Exit!$G27,0),0) -> 33769.709 | I34: =IF(I$24<=$A34,I$7+IF(AND(Assumptions!$B$67=1,I$24=(INT((Assumptions!$B$68-1)/12)+1),(INT((Assumptions!$B$68-1)/12)+1)<=$A34),Refinance!$B$14,0)+IF(I$24=$A34,Exit!$G27,0),0) -> 39312.711 | J34: =IF(J$24<=$A34,J$7+IF(AND(Assumptions!$B$67=1,J$24=(INT((Assumptions!$B$68-1)/12)+1),(INT((Assumptions!$B$68-1)/12)+1)<=$A34),Refinance!$B$14,0)+IF(J$24=$A34,Exit!$G27,0),0) -> 45052.582 | ... L34: =IF(L$24<=$A34,L$7+IF(AND(Assumptions!$B$67=1,L$24=(INT((Assumptions!$B$68-1)/12)+1),(INT((Assumptions!$B$68-1)/12)+1)<=$A34),Refinance!$B$14,0)+IF(L$24=$A34,Exit!$G27,0),0) -> 1231924.5 | N34: =IFERROR(IRR(B34:L34),0) -> 0.24243309 | O34: =IFERROR(SUMIF(C34:L34,">0")/Acquisition!$B$23,0) -> 3.6779502 | P34: =SUM(C34:L34)-Acquisition!$B$23 -> 1607037.9

Sheet Equity Returns (3)
A1: EQUITY RETURNS
A2: Annual levered cash flow to equity. IRR / equity multiple / cash-on-cash. Operations stop at the exit year.
A4: ($) | B4: Year 0 | C4: Year 1 | D4: Year 2 | E4: Year 3 | F4: Year 4 | G4: Year 5 | H4: Year 6 | I4: Year 7 | J4: Year 8 | K4: Year 9 | L4: Year 10
A5: NOI after CapEx | B5: - | C5: =SUM('Monthly Operations'!D42:O42) -> 81224.913 | D5: =SUM('Monthly Operations'!P42:AA42) -> 119435.64 | E5: =SUM('Monthly Operations'!AB42:AM42) -> 128483.35 | F5: =SUM('Monthly Operations'!AN42:AY42) -> 133473.68 | G5: =SUM('Monthly Operations'!AZ42:BK42) -> 138642.11 | H5: =SUM('Monthly Operations'!BL42:BW42) -> 143994.7 | I5: =SUM('Monthly Operations'!BX42:CI42) -> 149537.7 | J5: =SUM('Monthly Operations'!CJ42:CU42) -> 155277.57 | K5: =SUM('Monthly Operations'!CV42:DG42) -> 161220.98 | L5: =SUM('Monthly Operations'!DH42:DS42) -> 167374.82
A6: Debt Service | B6: - | C6: =-SUM('Debt Schedule'!D18:O18) -> -59150 | D6: =-SUM('Debt Schedule'!P18:AA18) -> -59150 | E6: =-SUM('Debt Schedule'!AB18:AM18) -> -72455.425 | F6: =-SUM('Debt Schedule'!AN18:AY18) -> -110224.99 | G6: =-SUM('Debt Schedule'!AZ18:BK18) -> -110224.99 | H6: =-SUM('Debt Schedule'!BL18:BW18) -> -110224.99 | I6: =-SUM('Debt Schedule'!BX18:CI18) -> -110224.99 | J6: =-SUM('Debt Schedule'!CJ18:CU18) -> -110224.99 | K6: =-SUM('Debt Schedule'!CV18:DG18) -> -110224.99 | L6: =-SUM('Debt Schedule'!DH18:DS18) -> -110224.99
A7: Operating CF (levered) | B7: - | C7: =C5+C6 -> 22074.913 | D7: =D5+D6 -> 60285.638 | E7: =E5+E6 -> 56027.925 | F7: =F5+F6 -> 23248.685 | G7: =G5+G6 -> 28417.118 | H7: =H5+H6 -> 33769.709 | I7: =I5+I6 -> 39312.711 | J7: =J5+J6 -> 45052.582 | ... L7: =L5+L6 -> 57149.832
A8: Refinance Proceeds | B8: - | C8: =IF(AND(Assumptions!$B$67=1,(INT((Assumptions!$B$68-1)/12)+1)=COLUMN(A1),(INT((Assumptions!$B$68-1)/12)+1)<=Exit!$B$6),Refinance!$B$14,0) -> 0 | D8: =IF(AND(Assumptions!$B$67=1,(INT((Assumptions!$B$68-1)/12)+1)=COLUMN(B1),(INT((Assumptions!$B$68-1)/12)+1)<=Exit!$B$6),Refinance!$B$14,0) -> 0 | E8: =IF(AND(Assumptions!$B$67=1,(INT((Assumptions!$B$68-1)/12)+1)=COLUMN(C1),(INT((Assumptions!$B$68-1)/12)+1)<=Exit!$B$6),Refinance!$B$14,0) -> 616028.14 | F8: =IF(AND(Assumptions!$B$67=1,(INT((Assumptions!$B$68-1)/12)+1)=COLUMN(D1),(INT((Assumptions!$B$68-1)/12)+1)<=Exit!$B$6),Refinance!$B$14,0) -> 0 | G8: =IF(AND(Assumptions!$B$67=1,(INT((Assumptions!$B$68-1)/12)+1)=COLUMN(E1),(INT((Assumptions!$B$68-1)/12)+1)<=Exit!$B$6),Refinance!$B$14,0) -> 0 | H8: =IF(AND(Assumptions!$B$67=1,(INT((Assumptions!$B$68-1)/12)+1)=COLUMN(F1),(INT((Assumptions!$B$68-1)/12)+1)<=Exit!$B$6),Refinance!$B$14,0) -> 0 | I8: =IF(AND(Assumptions!$B$67=1,(INT((Assumptions!$B$68-1)/12)+1)=COLUMN(G1),(INT((Assumptions!$B$68-1)/12)+1)<=Exit!$B$6),Refinance!$B$14,0) -> 0 | J8: =IF(AND(Assumptions!$B$67=1,(INT((Assumptions!$B$68-1)/12)+1)=COLUMN(H1),(INT((Assumptions!$B$68-1)/12)+1)<=Exit!$B$6),Refinance!$B$14,0) -> 0 | ... L8: =IF(AND(Assumptions!$B$67=1,(INT((Assumptions!$B$68-1)/12)+1)=COLUMN(J1),(INT((Assumptions!$B$68-1)/12)+1)<=Exit!$B$6),Refinance!$B$14,0) -> 0
A9: Net Sale Proceeds | B9: - | C9: =IF(1=Exit!$B$6,Exit!$B$13,0) -> 0 | D9: =IF(2=Exit!$B$6,Exit!$B$13,0) -> 0 | E9: =IF(3=Exit!$B$6,Exit!$B$13,0) -> 0 | F9: =IF(4=Exit!$B$6,Exit!$B$13,0) -> 0 | G9: =IF(5=Exit!$B$6,Exit!$B$13,0) -> 701987.73 | H9: =IF(6=Exit!$B$6,Exit!$B$13,0) -> 0 | I9: =IF(7=Exit!$B$6,Exit!$B$13,0) -> 0 | J9: =IF(8=Exit!$B$6,Exit!$B$13,0) -> 0 | K9: =IF(9=Exit!$B$6,Exit!$B$13,0) -> 0 | L9: =IF(10=Exit!$B$6,Exit!$B$13,0) -> 0
A10: Equity Contributed | B10: =-Acquisition!$B$23 -> -600100 | C10: - | D10: - | E10: - | F10: - | G10: - | H10: - | I10: - | J10: - | K10: - | L10: -
A11: NET CASH FLOW TO EQUITY | B11: =B10 -> -600100 | C11: =IF(1>Exit!$B$6,0,C7+C8)+C9 -> 22074.913 | D11: =IF(2>Exit!$B$6,0,D7+D8)+D9 -> 60285.638 | E11: =IF(3>Exit!$B$6,0,E7+E8)+E9 -> 672056.07 | F11: =IF(4>Exit!$B$6,0,F7+F8)+F9 -> 23248.685 | G11: =IF(5>Exit!$B$6,0,G7+G8)+G9 -> 730404.85 | H11: =IF(6>Exit!$B$6,0,H7+H8)+H9 -> 0 | I11: =IF(7>Exit!$B$6,0,I7+I8)+I9 -> 0 | J11: =IF(8>Exit!$B$6,0,J7+J8)+J9 -> 0 | K11: =IF(9>Exit!$B$6,0,K7+K8)+K9 -> 0 | L11: =IF(10>Exit!$B$6,0,L7+L8)+L9 -> 0
A12: Cumulative CF | B12: =B11 -> -600100 | C12: =B12+C11 -> -578025.09 | D12: =C12+D11 -> -517739.45 | E12: =D12+E11 -> 154316.62 | F12: =E12+F11 -> 177565.3 | G12: =F12+G11 -> 907970.15 | H12: =G12+H11 -> 907970.15 | I12: =H12+I11 -> 907970.15 | J12: =I12+J11 -> 907970.15 | ... L12: =K12+L11 -> 907970.15
A14: RETURN METRICS
A15: Equity Invested | B15: =Acquisition!$B$23 -> 600100
A16: Levered IRR | B16: =IFERROR(IRR(B11:L11),0) -> 0.27741656
A17: Equity Multiple (MOIC) | B17: =IFERROR(SUMIF(C11:L11,">0")/Acquisition!$B$23,0) -> 2.5130314 | E17: IF(C$23>$A24,0,C7+IF(ROUNDUP(Assumptions!$B$68/12,0)=C$23,Refinance!$B$14,0)+IF(C$23=$A24,Exit!G$18,0))
A18: Total Profit | B18: =SUM(C11:L11)-Acquisition!$B$23 -> 907970.15 | C18: =IF(AND(Assumptions!$B$67=1,(INT((Assumptions!$B$68-1)/12)+1)=COLUMN(A11),(INT((Assumptions!$B$68-1)/12)+1)<=Exit!$B$6),Refinance!$B$14,0) -> 0 | E18: IF(1<=1,C7+IF(AND(Assumptions!$B$67=1,1=(INT((Assumptions!$B$68-1)/12)+1),(INT((Assumptions!$B$68-1)/12)+1)<=1),Refinance!$B$14,0)+IF(1=1,Exit!G18,0),0)
A19: Avg Cash-on-Cash (operating) | B19: =IFERROR(AVERAGE(C7:L7)/Acquisition!$B$23,0) -> 0.069377621
A20: Hold Period (years) | B20: =Exit!$B$6 -> 5
A22: EXIT-YEAR CASH-FLOW MATRIX (row = sale year N; col = Year 0..10)
C23: Year | D23: Year | E23: Year | F23: Year | G23: Year | H23: Year | I23: Year | J23: Year | K23: Year | L23: Year
A24: Sale year ↓ | B24: Y0 | C24: 1 | D24: 2 | E24: 3 | F24: 4 | G24: 5 | H24: 6 | I24: 7 | J24: 8 | K24: 9 | L24: 10 | N24: IRR | O24: EM | P24: Profit
A25: 1 | B25: =-Acquisition!$B$23 -> -600100 | C25: =IF(C$24<=$A25,C$7+IF(AND(Assumptions!$B$67=1,C$24=ROUNDUP(Assumptions!$B$68/12,0),$A25>=ROUNDUP(Assumptions!$B$68/12,0)),Refinance!$B$14,0)+IF(C$24=$A25,Exit!$G18,0),0) -> 936601.25 | D25: =IF(D$24<=$A25,D$7+IF(AND(Assumptions!$B$67=1,D$24=ROUNDUP(Assumptions!$B$68/12,0),$A25>=ROUNDUP(Assumptions!$B$68/12,0)),Refinance!$B$14,0)+IF(D$24=$A25,Exit!$G18,0),0) -> 0 | E25: =IF(E$24<=$A25,E$7+IF(AND(Assumptions!$B$67=1,E$24=ROUNDUP(Assumptions!$B$68/12,0),$A25>=ROUNDUP(Assumptions!$B$68/12,0)),Refinance!$B$14,0)+IF(E$24=$A25,Exit!$G18,0),0) -> 0 | F25: =IF(F$24<=$A25,F$7+IF(AND(Assumptions!$B$67=1,F$24=ROUNDUP(Assumptions!$B$68/12,0),$A25>=ROUNDUP(Assumptions!$B$68/12,0)),Refinance!$B$14,0)+IF(F$24=$A25,Exit!$G18,0),0) -> 0 | G25: =IF(G$24<=$A25,G$7+IF(AND(Assumptions!$B$67=1,G$24=ROUNDUP(Assumptions!$B$68/12,0),$A25>=ROUNDUP(Assumptions!$B$68/12,0)),Refinance!$B$14,0)+IF(G$24=$A25,Exit!$G18,0),0) -> 0 | H25: =IF(H$24<=$A25,H$7+IF(AND(Assumptions!$B$67=1,H$24=ROUNDUP(Assumptions!$B$68/12,0),$A25>=ROUNDUP(Assumptions!$B$68/12,0)),Refinance!$B$14,0)+IF(H$24=$A25,Exit!$G18,0),0) -> 0 | I25: =IF(I$24<=$A25,I$7+IF(AND(Assumptions!$B$67=1,I$24=ROUNDUP(Assumptions!$B$68/12,0),$A25>=ROUNDUP(Assumptions!$B$68/12,0)),Refinance!$B$14,0)+IF(I$24=$A25,Exit!$G18,0),0) -> 0 | J25: =IF(J$24<=$A25,J$7+IF(AND(Assumptions!$B$67=1,J$24=ROUNDUP(Assumptions!$B$68/12,0),$A25>=ROUNDUP(Assumptions!$B$68/12,0)),Refinance!$B$14,0)+IF(J$24=$A25,Exit!$G18,0),0) -> 0 | ... L25: =IF(L$24<=$A25,L$7+IF(AND(Assumptions!$B$67=1,L$24=ROUNDUP(Assumptions!$B$68/12,0),$A25>=ROUNDUP(Assumptions!$B$68/12,0)),Refinance!$B$14,0)+IF(L$24=$A25,Exit!$G18,0),0) -> 0 | N25: =IFERROR(IRR(B25:L25),0) -> 0.56074197 | O25: =IFERROR(SUMIF(C25:L25,">0")/Acquisition!$B$23,0) -> 1.560742 | P25: =SUM(C25:L25)-Acquisition!$B$23 -> 336501.25
A26: 2 | B26: =-Acquisition!$B$23 -> -600100 | C26: =IF(C$24<=$A26,C$7+IF(AND(Assumptions!$B$67=1,C$24=ROUNDUP(Assumptions!$B$68/12,0),$A26>=ROUNDUP(Assumptions!$B$68/12,0)),Refinance!$B$14,0)+IF(C$24=$A26,Exit!$G19,0),0) -> 22074.913 | D26: =IF(D$24<=$A26,D$7+IF(AND(Assumptions!$B$67=1,D$24=ROUNDUP(Assumptions!$B$68/12,0),$A26>=ROUNDUP(Assumptions!$B$68/12,0)),Refinance!$B$14,0)+IF(D$24=$A26,Exit!$G19,0),0) -> 1109953.6 | E26: =IF(E$24<=$A26,E$7+IF(AND(Assumptions!$B$67=1,E$24=ROUNDUP(Assumptions!$B$68/12,0),$A26>=ROUNDUP(Assumptions!$B$68/12,0)),Refinance!$B$14,0)+IF(E$24=$A26,Exit!$G19,0),0) -> 0 | F26: =IF(F$24<=$A26,F$7+IF(AND(Assumptions!$B$67=1,F$24=ROUNDUP(Assumptions!$B$68/12,0),$A26>=ROUNDUP(Assumptions!$B$68/12,0)),Refinance!$B$14,0)+IF(F$24=$A26,Exit!$G19,0),0) -> 0 | G26: =IF(G$24<=$A26,G$7+IF(AND(Assumptions!$B$67=1,G$24=ROUNDUP(Assumptions!$B$68/12,0),$A26>=ROUNDUP(Assumptions!$B$68/12,0)),Refinance!$B$14,0)+IF(G$24=$A26,Exit!$G19,0),0) -> 0 | H26: =IF(H$24<=$A26,H$7+IF(AND(Assumptions!$B$67=1,H$24=ROUNDUP(Assumptions!$B$68/12,0),$A26>=ROUNDUP(Assumptions!$B$68/12,0)),Refinance!$B$14,0)+IF(H$24=$A26,Exit!$G19,0),0) -> 0 | I26: =IF(I$24<=$A26,I$7+IF(AND(Assumptions!$B$67=1,I$24=ROUNDUP(Assumptions!$B$68/12,0),$A26>=ROUNDUP(Assumptions!$B$68/12,0)),Refinance!$B$14,0)+IF(I$24=$A26,Exit!$G19,0),0) -> 0 | J26: =IF(J$24<=$A26,J$7+IF(AND(Assumptions!$B$67=1,J$24=ROUNDUP(Assumptions!$B$68/12,0),$A26>=ROUNDUP(Assumptions!$B$68/12,0)),Refinance!$B$14,0)+IF(J$24=$A26,Exit!$G19,0),0) -> 0 | ... L26: =IF(L$24<=$A26,L$7+IF(AND(Assumptions!$B$67=1,L$24=ROUNDUP(Assumptions!$B$68/12,0),$A26>=ROUNDUP(Assumptions!$B$68/12,0)),Refinance!$B$14,0)+IF(L$24=$A26,Exit!$G19,0),0) -> 0 | N26: =IFERROR(IRR(B26:L26),0) -> 0.37852234 | O26: =IFERROR(SUMIF(C26:L26,">0")/Acquisition!$B$23,0) -> 1.8863998 | P26: =SUM(C26:L26)-Acquisition!$B$23 -> 531928.49
A27: 3 | B27: =-Acquisition!$B$23 -> -600100 | C27: =IF(C$24<=$A27,C$7+IF(AND(Assumptions!$B$67=1,C$24=ROUNDUP(Assumptions!$B$68/12,0),$A27>=ROUNDUP(Assumptions!$B$68/12,0)),Refinance!$B$14,0)+IF(C$24=$A27,Exit!$G20,0),0) -> 22074.913 | D27: =IF(D$24<=$A27,D$7+IF(AND(Assumptions!$B$67=1,D$24=ROUNDUP(Assumptions!$B$68/12,0),$A27>=ROUNDUP(Assumptions!$B$68/12,0)),Refinance!$B$14,0)+IF(D$24=$A27,Exit!$G20,0),0) -> 60285.638 | E27: =IF(E$24<=$A27,E$7+IF(AND(Assumptions!$B$67=1,E$24=ROUNDUP(Assumptions!$B$68/12,0),$A27>=ROUNDUP(Assumptions!$B$68/12,0)),Refinance!$B$14,0)+IF(E$24=$A27,Exit!$G20,0),0) -> 1176453.8 | F27: =IF(F$24<=$A27,F$7+IF(AND(Assumptions!$B$67=1,F$24=ROUNDUP(Assumptions!$B$68/12,0),$A27>=ROUNDUP(Assumptions!$B$68/12,0)),Refinance!$B$14,0)+IF(F$24=$A27,Exit!$G20,0),0) -> 0 | G27: =IF(G$24<=$A27,G$7+IF(AND(Assumptions!$B$67=1,G$24=ROUNDUP(Assumptions!$B$68/12,0),$A27>=ROUNDUP(Assumptions!$B$68/12,0)),Refinance!$B$14,0)+IF(G$24=$A27,Exit!$G20,0),0) -> 0 | H27: =IF(H$24<=$A27,H$7+IF(AND(Assumptions!$B$67=1,H$24=ROUNDUP(Assumptions!$B$68/12,0),$A27>=ROUNDUP(Assumptions!$B$68/12,0)),Refinance!$B$14,0)+IF(H$24=$A27,Exit!$G20,0),0) -> 0 | I27: =IF(I$24<=$A27,I$7+IF(AND(Assumptions!$B$67=1,I$24=ROUNDUP(Assumptions!$B$68/12,0),$A27>=ROUNDUP(Assumptions!$B$68/12,0)),Refinance!$B$14,0)+IF(I$24=$A27,Exit!$G20,0),0) -> 0 | J27: =IF(J$24<=$A27,J$7+IF(AND(Assumptions!$B$67=1,J$24=ROUNDUP(Assumptions!$B$68/12,0),$A27>=ROUNDUP(Assumptions!$B$68/12,0)),Refinance!$B$14,0)+IF(J$24=$A27,Exit!$G20,0),0) -> 0 | ... L27: =IF(L$24<=$A27,L$7+IF(AND(Assumptions!$B$67=1,L$24=ROUNDUP(Assumptions!$B$68/12,0),$A27>=ROUNDUP(Assumptions!$B$68/12,0)),Refinance!$B$14,0)+IF(L$24=$A27,Exit!$G20,0),0) -> 0 | N27: =IFERROR(IRR(B27:L27),0) -> 0.29094732 | O27: =IFERROR(SUMIF(C27:L27,">0")/Acquisition!$B$23,0) -> 2.0976743 | P27: =SUM(C27:L27)-Acquisition!$B$23 -> 658714.35
A28: 4 | B28: =-Acquisition!$B$23 -> -600100 | C28: =IF(C$24<=$A28,C$7+IF(AND(Assumptions!$B$67=1,C$24=ROUNDUP(Assumptions!$B$68/12,0),$A28>=ROUNDUP(Assumptions!$B$68/12,0)),Refinance!$B$14,0)+IF(C$24=$A28,Exit!$G21,0),0) -> 22074.913 | D28: =IF(D$24<=$A28,D$7+IF(AND(Assumptions!$B$67=1,D$24=ROUNDUP(Assumptions!$B$68/12,0),$A28>=ROUNDUP(Assumptions!$B$68/12,0)),Refinance!$B$14,0)+IF(D$24=$A28,Exit!$G21,0),0) -> 60285.638 | E28: =IF(E$24<=$A28,E$7+IF(AND(Assumptions!$B$67=1,E$24=ROUNDUP(Assumptions!$B$68/12,0),$A28>=ROUNDUP(Assumptions!$B$68/12,0)),Refinance!$B$14,0)+IF(E$24=$A28,Exit!$G21,0),0) -> 672056.07 | F28: =IF(F$24<=$A28,F$7+IF(AND(Assumptions!$B$67=1,F$24=ROUNDUP(Assumptions!$B$68/12,0),$A28>=ROUNDUP(Assumptions!$B$68/12,0)),Refinance!$B$14,0)+IF(F$24=$A28,Exit!$G21,0),0) -> 624478.5 | G28: =IF(G$24<=$A28,G$7+IF(AND(Assumptions!$B$67=1,G$24=ROUNDUP(Assumptions!$B$68/12,0),$A28>=ROUNDUP(Assumptions!$B$68/12,0)),Refinance!$B$14,0)+IF(G$24=$A28,Exit!$G21,0),0) -> 0 | H28: =IF(H$24<=$A28,H$7+IF(AND(Assumptions!$B$67=1,H$24=ROUNDUP(Assumptions!$B$68/12,0),$A28>=ROUNDUP(Assumptions!$B$68/12,0)),Refinance!$B$14,0)+IF(H$24=$A28,Exit!$G21,0),0) -> 0 | I28: =IF(I$24<=$A28,I$7+IF(AND(Assumptions!$B$67=1,I$24=ROUNDUP(Assumptions!$B$68/12,0),$A28>=ROUNDUP(Assumptions!$B$68/12,0)),Refinance!$B$14,0)+IF(I$24=$A28,Exit!$G21,0),0) -> 0 | J28: =IF(J$24<=$A28,J$7+IF(AND(Assumptions!$B$67=1,J$24=ROUNDUP(Assumptions!$B$68/12,0),$A28>=ROUNDUP(Assumptions!$B$68/12,0)),Refinance!$B$14,0)+IF(J$24=$A28,Exit!$G21,0),0) -> 0 | ... L28: =IF(L$24<=$A28,L$7+IF(AND(Assumptions!$B$67=1,L$24=ROUNDUP(Assumptions!$B$68/12,0),$A28>=ROUNDUP(Assumptions!$B$68/12,0)),Refinance!$B$14,0)+IF(L$24=$A28,Exit!$G21,0),0) -> 0 | N28: =IFERROR(IRR(B28:L28),0) -> 0.28458014 | O28: =IFERROR(SUMIF(C28:L28,">0")/Acquisition!$B$23,0) -> 2.2977756 | P28: =SUM(C28:L28)-Acquisition!$B$23 -> 778795.11
A29: 5 | B29: =-Acquisition!$B$23 -> -600100 | C29: =IF(C$24<=$A29,C$7+IF(AND(Assumptions!$B$67=1,C$24=ROUNDUP(Assumptions!$B$68/12,0),$A29>=ROUNDUP(Assumptions!$B$68/12,0)),Refinance!$B$14,0)+IF(C$24=$A29,Exit!$G22,0),0) -> 22074.913 | D29: =IF(D$24<=$A29,D$7+IF(AND(Assumptions!$B$67=1,D$24=ROUNDUP(Assumptions!$B$68/12,0),$A29>=ROUNDUP(Assumptions!$B$68/12,0)),Refinance!$B$14,0)+IF(D$24=$A29,Exit!$G22,0),0) -> 60285.638 | E29: =IF(E$24<=$A29,E$7+IF(AND(Assumptions!$B$67=1,E$24=ROUNDUP(Assumptions!$B$68/12,0),$A29>=ROUNDUP(Assumptions!$B$68/12,0)),Refinance!$B$14,0)+IF(E$24=$A29,Exit!$G22,0),0) -> 672056.07 | F29: =IF(F$24<=$A29,F$7+IF(AND(Assumptions!$B$67=1,F$24=ROUNDUP(Assumptions!$B$68/12,0),$A29>=ROUNDUP(Assumptions!$B$68/12,0)),Refinance!$B$14,0)+IF(F$24=$A29,Exit!$G22,0),0) -> 23248.685 | G29: =IF(G$24<=$A29,G$7+IF(AND(Assumptions!$B$67=1,G$24=ROUNDUP(Assumptions!$B$68/12,0),$A29>=ROUNDUP(Assumptions!$B$68/12,0)),Refinance!$B$14,0)+IF(G$24=$A29,Exit!$G22,0),0) -> 730404.85 | H29: =IF(H$24<=$A29,H$7+IF(AND(Assumptions!$B$67=1,H$24=ROUNDUP(Assumptions!$B$68/12,0),$A29>=ROUNDUP(Assumptions!$B$68/12,0)),Refinance!$B$14,0)+IF(H$24=$A29,Exit!$G22,0),0) -> 0 | I29: =IF(I$24<=$A29,I$7+IF(AND(Assumptions!$B$67=1,I$24=ROUNDUP(Assumptions!$B$68/12,0),$A29>=ROUNDUP(Assumptions!$B$68/12,0)),Refinance!$B$14,0)+IF(I$24=$A29,Exit!$G22,0),0) -> 0 | J29: =IF(J$24<=$A29,J$7+IF(AND(Assumptions!$B$67=1,J$24=ROUNDUP(Assumptions!$B$68/12,0),$A29>=ROUNDUP(Assumptions!$B$68/12,0)),Refinance!$B$14,0)+IF(J$24=$A29,Exit!$G22,0),0) -> 0 | ... L29: =IF(L$24<=$A29,L$7+IF(AND(Assumptions!$B$67=1,L$24=ROUNDUP(Assumptions!$B$68/12,0),$A29>=ROUNDUP(Assumptions!$B$68/12,0)),Refinance!$B$14,0)+IF(L$24=$A29,Exit!$G22,0),0) -> 0 | N29: =IFERROR(IRR(B29:L29),0) -> 0.27741656 | O29: =IFERROR(SUMIF(C29:L29,">0")/Acquisition!$B$23,0) -> 2.5130314 | P29: =SUM(C29:L29)-Acquisition!$B$23 -> 907970.15
A30: 6 | B30: =-Acquisition!$B$23 -> -600100 | C30: =IF(C$24<=$A30,C$7+IF(AND(Assumptions!$B$67=1,C$24=ROUNDUP(Assumptions!$B$68/12,0),$A30>=ROUNDUP(Assumptions!$B$68/12,0)),Refinance!$B$14,0)+IF(C$24=$A30,Exit!$G23,0),0) -> 22074.913 | D30: =IF(D$24<=$A30,D$7+IF(AND(Assumptions!$B$67=1,D$24=ROUNDUP(Assumptions!$B$68/12,0),$A30>=ROUNDUP(Assumptions!$B$68/12,0)),Refinance!$B$14,0)+IF(D$24=$A30,Exit!$G23,0),0) -> 60285.638 | E30: =IF(E$24<=$A30,E$7+IF(AND(Assumptions!$B$67=1,E$24=ROUNDUP(Assumptions!$B$68/12,0),$A30>=ROUNDUP(Assumptions!$B$68/12,0)),Refinance!$B$14,0)+IF(E$24=$A30,Exit!$G23,0),0) -> 672056.07 | F30: =IF(F$24<=$A30,F$7+IF(AND(Assumptions!$B$67=1,F$24=ROUNDUP(Assumptions!$B$68/12,0),$A30>=ROUNDUP(Assumptions!$B$68/12,0)),Refinance!$B$14,0)+IF(F$24=$A30,Exit!$G23,0),0) -> 23248.685 | G30: =IF(G$24<=$A30,G$7+IF(AND(Assumptions!$B$67=1,G$24=ROUNDUP(Assumptions!$B$68/12,0),$A30>=ROUNDUP(Assumptions!$B$68/12,0)),Refinance!$B$14,0)+IF(G$24=$A30,Exit!$G23,0),0) -> 28417.118 | H30: =IF(H$24<=$A30,H$7+IF(AND(Assumptions!$B$67=1,H$24=ROUNDUP(Assumptions!$B$68/12,0),$A30>=ROUNDUP(Assumptions!$B$68/12,0)),Refinance!$B$14,0)+IF(H$24=$A30,Exit!$G23,0),0) -> 840606.46 | I30: =IF(I$24<=$A30,I$7+IF(AND(Assumptions!$B$67=1,I$24=ROUNDUP(Assumptions!$B$68/12,0),$A30>=ROUNDUP(Assumptions!$B$68/12,0)),Refinance!$B$14,0)+IF(I$24=$A30,Exit!$G23,0),0) -> 0 | J30: =IF(J$24<=$A30,J$7+IF(AND(Assumptions!$B$67=1,J$24=ROUNDUP(Assumptions!$B$68/12,0),$A30>=ROUNDUP(Assumptions!$B$68/12,0)),Refinance!$B$14,0)+IF(J$24=$A30,Exit!$G23,0),0) -> 0 | ... L30: =IF(L$24<=$A30,L$7+IF(AND(Assumptions!$B$67=1,L$24=ROUNDUP(Assumptions!$B$68/12,0),$A30>=ROUNDUP(Assumptions!$B$68/12,0)),Refinance!$B$14,0)+IF(L$24=$A30,Exit!$G23,0),0) -> 0 | N30: =IFERROR(IRR(B30:L30),0) -> 0.27033933 | O30: =IFERROR(SUMIF(C30:L30,">0")/Acquisition!$B$23,0) -> 2.7440241 | P30: =SUM(C30:L30)-Acquisition!$B$23 -> 1046588.9
A31: 7 | B31: =-Acquisition!$B$23 -> -600100 | C31: =IF(C$24<=$A31,C$7+IF(AND(Assumptions!$B$67=1,C$24=ROUNDUP(Assumptions!$B$68/12,0),$A31>=ROUNDUP(Assumptions!$B$68/12,0)),Refinance!$B$14,0)+IF(C$24=$A31,Exit!$G24,0),0) -> 22074.913 | D31: =IF(D$24<=$A31,D$7+IF(AND(Assumptions!$B$67=1,D$24=ROUNDUP(Assumptions!$B$68/12,0),$A31>=ROUNDUP(Assumptions!$B$68/12,0)),Refinance!$B$14,0)+IF(D$24=$A31,Exit!$G24,0),0) -> 60285.638 | E31: =IF(E$24<=$A31,E$7+IF(AND(Assumptions!$B$67=1,E$24=ROUNDUP(Assumptions!$B$68/12,0),$A31>=ROUNDUP(Assumptions!$B$68/12,0)),Refinance!$B$14,0)+IF(E$24=$A31,Exit!$G24,0),0) -> 672056.07 | F31: =IF(F$24<=$A31,F$7+IF(AND(Assumptions!$B$67=1,F$24=ROUNDUP(Assumptions!$B$68/12,0),$A31>=ROUNDUP(Assumptions!$B$68/12,0)),Refinance!$B$14,0)+IF(F$24=$A31,Exit!$G24,0),0) -> 23248.685 | G31: =IF(G$24<=$A31,G$7+IF(AND(Assumptions!$B$67=1,G$24=ROUNDUP(Assumptions!$B$68/12,0),$A31>=ROUNDUP(Assumptions!$B$68/12,0)),Refinance!$B$14,0)+IF(G$24=$A31,Exit!$G24,0),0) -> 28417.118 | H31: =IF(H$24<=$A31,H$7+IF(AND(Assumptions!$B$67=1,H$24=ROUNDUP(Assumptions!$B$68/12,0),$A31>=ROUNDUP(Assumptions!$B$68/12,0)),Refinance!$B$14,0)+IF(H$24=$A31,Exit!$G24,0),0) -> 33769.709 | I31: =IF(I$24<=$A31,I$7+IF(AND(Assumptions!$B$67=1,I$24=ROUNDUP(Assumptions!$B$68/12,0),$A31>=ROUNDUP(Assumptions!$B$68/12,0)),Refinance!$B$14,0)+IF(I$24=$A31,Exit!$G24,0),0) -> 955262.35 | J31: =IF(J$24<=$A31,J$7+IF(AND(Assumptions!$B$67=1,J$24=ROUNDUP(Assumptions!$B$68/12,0),$A31>=ROUNDUP(Assumptions!$B$68/12,0)),Refinance!$B$14,0)+IF(J$24=$A31,Exit!$G24,0),0) -> 0 | ... L31: =IF(L$24<=$A31,L$7+IF(AND(Assumptions!$B$67=1,L$24=ROUNDUP(Assumptions!$B$68/12,0),$A31>=ROUNDUP(Assumptions!$B$68/12,0)),Refinance!$B$14,0)+IF(L$24=$A31,Exit!$G24,0),0) -> 0 | N31: =IFERROR(IRR(B31:L31),0) -> 0.26369184 | O31: =IFERROR(SUMIF(C31:L31,">0")/Acquisition!$B$23,0) -> 2.9913589 | P31: =SUM(C31:L31)-Acquisition!$B$23 -> 1195014.5
A32: 8 | B32: =-Acquisition!$B$23 -> -600100 | C32: =IF(C$24<=$A32,C$7+IF(AND(Assumptions!$B$67=1,C$24=ROUNDUP(Assumptions!$B$68/12,0),$A32>=ROUNDUP(Assumptions!$B$68/12,0)),Refinance!$B$14,0)+IF(C$24=$A32,Exit!$G25,0),0) -> 22074.913 | D32: =IF(D$24<=$A32,D$7+IF(AND(Assumptions!$B$67=1,D$24=ROUNDUP(Assumptions!$B$68/12,0),$A32>=ROUNDUP(Assumptions!$B$68/12,0)),Refinance!$B$14,0)+IF(D$24=$A32,Exit!$G25,0),0) -> 60285.638 | E32: =IF(E$24<=$A32,E$7+IF(AND(Assumptions!$B$67=1,E$24=ROUNDUP(Assumptions!$B$68/12,0),$A32>=ROUNDUP(Assumptions!$B$68/12,0)),Refinance!$B$14,0)+IF(E$24=$A32,Exit!$G25,0),0) -> 672056.07 | F32: =IF(F$24<=$A32,F$7+IF(AND(Assumptions!$B$67=1,F$24=ROUNDUP(Assumptions!$B$68/12,0),$A32>=ROUNDUP(Assumptions!$B$68/12,0)),Refinance!$B$14,0)+IF(F$24=$A32,Exit!$G25,0),0) -> 23248.685 | G32: =IF(G$24<=$A32,G$7+IF(AND(Assumptions!$B$67=1,G$24=ROUNDUP(Assumptions!$B$68/12,0),$A32>=ROUNDUP(Assumptions!$B$68/12,0)),Refinance!$B$14,0)+IF(G$24=$A32,Exit!$G25,0),0) -> 28417.118 | H32: =IF(H$24<=$A32,H$7+IF(AND(Assumptions!$B$67=1,H$24=ROUNDUP(Assumptions!$B$68/12,0),$A32>=ROUNDUP(Assumptions!$B$68/12,0)),Refinance!$B$14,0)+IF(H$24=$A32,Exit!$G25,0),0) -> 33769.709 | I32: =IF(I$24<=$A32,I$7+IF(AND(Assumptions!$B$67=1,I$24=ROUNDUP(Assumptions!$B$68/12,0),$A32>=ROUNDUP(Assumptions!$B$68/12,0)),Refinance!$B$14,0)+IF(I$24=$A32,Exit!$G25,0),0) -> 39312.711 | J32: =IF(J$24<=$A32,J$7+IF(AND(Assumptions!$B$67=1,J$24=ROUNDUP(Assumptions!$B$68/12,0),$A32>=ROUNDUP(Assumptions!$B$68/12,0)),Refinance!$B$14,0)+IF(J$24=$A32,Exit!$G25,0),0) -> 1074559.6 | ... L32: =IF(L$24<=$A32,L$7+IF(AND(Assumptions!$B$67=1,L$24=ROUNDUP(Assumptions!$B$68/12,0),$A32>=ROUNDUP(Assumptions!$B$68/12,0)),Refinance!$B$14,0)+IF(L$24=$A32,Exit!$G25,0),0) -> 0 | N32: =IFERROR(IRR(B32:L32),0) -> 0.25758924 | O32: =IFERROR(SUMIF(C32:L32,">0")/Acquisition!$B$23,0) -> 3.2556648 | P32: =SUM(C32:L32)-Acquisition!$B$23 -> 1353624.4
A33: 9 | B33: =-Acquisition!$B$23 -> -600100 | C33: =IF(C$24<=$A33,C$7+IF(AND(Assumptions!$B$67=1,C$24=ROUNDUP(Assumptions!$B$68/12,0),$A33>=ROUNDUP(Assumptions!$B$68/12,0)),Refinance!$B$14,0)+IF(C$24=$A33,Exit!$G26,0),0) -> 22074.913 | D33: =IF(D$24<=$A33,D$7+IF(AND(Assumptions!$B$67=1,D$24=ROUNDUP(Assumptions!$B$68/12,0),$A33>=ROUNDUP(Assumptions!$B$68/12,0)),Refinance!$B$14,0)+IF(D$24=$A33,Exit!$G26,0),0) -> 60285.638 | E33: =IF(E$24<=$A33,E$7+IF(AND(Assumptions!$B$67=1,E$24=ROUNDUP(Assumptions!$B$68/12,0),$A33>=ROUNDUP(Assumptions!$B$68/12,0)),Refinance!$B$14,0)+IF(E$24=$A33,Exit!$G26,0),0) -> 672056.07 | F33: =IF(F$24<=$A33,F$7+IF(AND(Assumptions!$B$67=1,F$24=ROUNDUP(Assumptions!$B$68/12,0),$A33>=ROUNDUP(Assumptions!$B$68/12,0)),Refinance!$B$14,0)+IF(F$24=$A33,Exit!$G26,0),0) -> 23248.685 | G33: =IF(G$24<=$A33,G$7+IF(AND(Assumptions!$B$67=1,G$24=ROUNDUP(Assumptions!$B$68/12,0),$A33>=ROUNDUP(Assumptions!$B$68/12,0)),Refinance!$B$14,0)+IF(G$24=$A33,Exit!$G26,0),0) -> 28417.118 | H33: =IF(H$24<=$A33,H$7+IF(AND(Assumptions!$B$67=1,H$24=ROUNDUP(Assumptions!$B$68/12,0),$A33>=ROUNDUP(Assumptions!$B$68/12,0)),Refinance!$B$14,0)+IF(H$24=$A33,Exit!$G26,0),0) -> 33769.709 | I33: =IF(I$24<=$A33,I$7+IF(AND(Assumptions!$B$67=1,I$24=ROUNDUP(Assumptions!$B$68/12,0),$A33>=ROUNDUP(Assumptions!$B$68/12,0)),Refinance!$B$14,0)+IF(I$24=$A33,Exit!$G26,0),0) -> 39312.711 | J33: =IF(J$24<=$A33,J$7+IF(AND(Assumptions!$B$67=1,J$24=ROUNDUP(Assumptions!$B$68/12,0),$A33>=ROUNDUP(Assumptions!$B$68/12,0)),Refinance!$B$14,0)+IF(J$24=$A33,Exit!$G26,0),0) -> 45052.582 | ... L33: =IF(L$24<=$A33,L$7+IF(AND(Assumptions!$B$67=1,L$24=ROUNDUP(Assumptions!$B$68/12,0),$A33>=ROUNDUP(Assumptions!$B$68/12,0)),Refinance!$B$14,0)+IF(L$24=$A33,Exit!$G26,0),0) -> 0 | N33: =IFERROR(IRR(B33:L33),0) -> 0.2520483 | O33: =IFERROR(SUMIF(C33:L33,">0")/Acquisition!$B$23,0) -> 3.5375958 | P33: =SUM(C33:L33)-Acquisition!$B$23 -> 1522811.2
A34: 10 | B34: =-Acquisition!$B$23 -> -600100 | C34: =IF(C$24<=$A34,C$7+IF(AND(Assumptions!$B$67=1,C$24=ROUNDUP(Assumptions!$B$68/12,0),$A34>=ROUNDUP(Assumptions!$B$68/12,0)),Refinance!$B$14,0)+IF(C$24=$A34,Exit!$G27,0),0) -> 22074.913 | D34: =IF(D$24<=$A34,D$7+IF(AND(Assumptions!$B$67=1,D$24=ROUNDUP(Assumptions!$B$68/12,0),$A34>=ROUNDUP(Assumptions!$B$68/12,0)),Refinance!$B$14,0)+IF(D$24=$A34,Exit!$G27,0),0) -> 60285.638 | E34: =IF(E$24<=$A34,E$7+IF(AND(Assumptions!$B$67=1,E$24=ROUNDUP(Assumptions!$B$68/12,0),$A34>=ROUNDUP(Assumptions!$B$68/12,0)),Refinance!$B$14,0)+IF(E$24=$A34,Exit!$G27,0),0) -> 672056.07 | F34: =IF(F$24<=$A34,F$7+IF(AND(Assumptions!$B$67=1,F$24=ROUNDUP(Assumptions!$B$68/12,0),$A34>=ROUNDUP(Assumptions!$B$68/12,0)),Refinance!$B$14,0)+IF(F$24=$A34,Exit!$G27,0),0) -> 23248.685 | G34: =IF(G$24<=$A34,G$7+IF(AND(Assumptions!$B$67=1,G$24=ROUNDUP(Assumptions!$B$68/12,0),$A34>=ROUNDUP(Assumptions!$B$68/12,0)),Refinance!$B$14,0)+IF(G$24=$A34,Exit!$G27,0),0) -> 28417.118 | H34: =IF(H$24<=$A34,H$7+IF(AND(Assumptions!$B$67=1,H$24=ROUNDUP(Assumptions!$B$68/12,0),$A34>=ROUNDUP(Assumptions!$B$68/12,0)),Refinance!$B$14,0)+IF(H$24=$A34,Exit!$G27,0),0) -> 33769.709 | I34: =IF(I$24<=$A34,I$7+IF(AND(Assumptions!$B$67=1,I$24=ROUNDUP(Assumptions!$B$68/12,0),$A34>=ROUNDUP(Assumptions!$B$68/12,0)),Refinance!$B$14,0)+IF(I$24=$A34,Exit!$G27,0),0) -> 39312.711 | J34: =IF(J$24<=$A34,J$7+IF(AND(Assumptions!$B$67=1,J$24=ROUNDUP(Assumptions!$B$68/12,0),$A34>=ROUNDUP(Assumptions!$B$68/12,0)),Refinance!$B$14,0)+IF(J$24=$A34,Exit!$G27,0),0) -> 45052.582 | ... L34: =IF(L$24<=$A34,L$7+IF(AND(Assumptions!$B$67=1,L$24=ROUNDUP(Assumptions!$B$68/12,0),$A34>=ROUNDUP(Assumptions!$B$68/12,0)),Refinance!$B$14,0)+IF(L$24=$A34,Exit!$G27,0),0) -> 1231924.5 | N34: =IFERROR(IRR(B34:L34),0) -> 0.24243309 | O34: =IFERROR(SUMIF(C34:L34,">0")/Acquisition!$B$23,0) -> 3.6779502 | P34: =SUM(C34:L34)-Acquisition!$B$23 -> 1607037.9

Sheet LP GP Waterfall
A1: LP / GP DISTRIBUTION WATERFALL
A2: European waterfall: preferred return (compounded), return of capital, GP catch-up, then promote split.
A4: ($) | B4: Year 0 | C4: Year 1 | D4: Year 2 | E4: Year 3 | F4: Year 4 | G4: Year 5 | H4: Year 6 | I4: Year 7 | J4: Year 8 | K4: Year 9 | L4: Year 10
A5: Distributable CF | B5: =-'Equity Returns'!B11 -> 600100 | C5: =MAX(0,'Equity Returns'!C11) -> 22074.913 | D5: =MAX(0,'Equity Returns'!D11) -> 60285.638 | E5: =MAX(0,'Equity Returns'!E11) -> 672056.07 | F5: =MAX(0,'Equity Returns'!F11) -> 23248.685 | G5: =MAX(0,'Equity Returns'!G11) -> 730404.85 | H5: =MAX(0,'Equity Returns'!H11) -> 0 | I5: =MAX(0,'Equity Returns'!I11) -> 0 | J5: =MAX(0,'Equity Returns'!J11) -> 0 | ... L5: =MAX(0,'Equity Returns'!L11) -> 0
A6: Pref Accrued | B6: 0 | C6: =Assumptions!$B$82*B10 -> 48008 | D6: =Assumptions!$B$82*C10 -> 48008 | E6: =Assumptions!$B$82*D10 -> 48008 | F6: =Assumptions!$B$82*E10 -> 0 | G6: =Assumptions!$B$82*F10 -> 0 | H6: =Assumptions!$B$82*G10 -> 0 | I6: =Assumptions!$B$82*H10 -> 0 | J6: =Assumptions!$B$82*I10 -> 0 | ... L6: =Assumptions!$B$82*K10 -> 0
A7: Pref Balance (unpaid) | B7: 0 | C7: =(B7+C6)-C8 -> 25933.087 | D7: =(C7+D6)-D8 -> 13655.449 | E7: =(D7+E6)-E8 -> 0 | F7: =(E7+F6)-F8 -> 0 | G7: =(F7+G6)-G8 -> 0 | H7: =(G7+H6)-H8 -> 0 | I7: =(H7+I6)-I8 -> 0 | J7: =(I7+J6)-J8 -> 0 | ... L7: =(K7+L6)-L8 -> 0
A8: Tier 1: Preferred Paid | B8: 0 | C8: =MIN(C5,(B7+C6)) -> 22074.913 | D8: =MIN(D5,(C7+D6)) -> 60285.638 | E8: =MIN(E5,(D7+E6)) -> 61663.449 | F8: =MIN(F5,(E7+F6)) -> 0 | G8: =MIN(G5,(F7+G6)) -> 0 | H8: =MIN(H5,(G7+H6)) -> 0 | I8: =MIN(I5,(H7+I6)) -> 0 | J8: =MIN(J5,(I7+J6)) -> 0 | ... L8: =MIN(L5,(K7+L6)) -> 0
A9: Tier 2: Return of Capital | B9: 0 | C9: =MIN((C5-C8),B10) -> 0 | D9: =MIN((D5-D8),C10) -> 0 | E9: =MIN((E5-E8),D10) -> 600100 | F9: =MIN((F5-F8),E10) -> 0 | G9: =MIN((G5-G8),F10) -> 0 | H9: =MIN((H5-H8),G10) -> 0 | I9: =MIN((I5-I8),H10) -> 0 | J9: =MIN((J5-J8),I10) -> 0 | ... L9: =MIN((L5-L8),K10) -> 0
A10: Unreturned Capital | B10: =B5 -> 600100 | C10: =B10-C9 -> 600100 | D10: =C10-D9 -> 600100 | E10: =D10-E9 -> 0 | F10: =E10-F9 -> 0 | G10: =F10-G9 -> 0 | H10: =G10-H9 -> 0 | I10: =H10-I9 -> 0 | J10: =I10-J9 -> 0 | ... L10: =K10-L9 -> 0
A11: Cum. Preferred Paid | B11: 0 | C11: =B11+C8 -> 22074.913 | D11: =C11+D8 -> 82360.551 | E11: =D11+E8 -> 144024 | F11: =E11+F8 -> 144024 | G11: =F11+G8 -> 144024 | H11: =G11+H8 -> 144024 | I11: =H11+I8 -> 144024 | J11: =I11+J8 -> 144024 | ... L11: =K11+L8 -> 144024
A12: Tier 3: GP Catch-up | B12: 0 | C12: =MIN(((C5-C8)-C9),Assumptions!$B$83*MAX(0,(Assumptions!$B$84/(1-Assumptions!$B$84))*C11-B13)) -> 0 | D12: =MIN(((D5-D8)-D9),Assumptions!$B$83*MAX(0,(Assumptions!$B$84/(1-Assumptions!$B$84))*D11-C13)) -> 0 | E12: =MIN(((E5-E8)-E9),Assumptions!$B$83*MAX(0,(Assumptions!$B$84/(1-Assumptions!$B$84))*E11-D13)) -> 10292.617 | F12: =MIN(((F5-F8)-F9),Assumptions!$B$83*MAX(0,(Assumptions!$B$84/(1-Assumptions!$B$84))*F11-E13)) -> 23248.685 | G12: =MIN(((G5-G8)-G9),Assumptions!$B$83*MAX(0,(Assumptions!$B$84/(1-Assumptions!$B$84))*G11-F13)) -> 2464.6975 | H12: =MIN(((H5-H8)-H9),Assumptions!$B$83*MAX(0,(Assumptions!$B$84/(1-Assumptions!$B$84))*H11-G13)) -> 0 | I12: =MIN(((I5-I8)-I9),Assumptions!$B$83*MAX(0,(Assumptions!$B$84/(1-Assumptions!$B$84))*I11-H13)) -> 0 | J12: =MIN(((J5-J8)-J9),Assumptions!$B$83*MAX(0,(Assumptions!$B$84/(1-Assumptions!$B$84))*J11-I13)) -> 0 | ... L12: =MIN(((L5-L8)-L9),Assumptions!$B$83*MAX(0,(Assumptions!$B$84/(1-Assumptions!$B$84))*L11-K13)) -> 0
A13: Cum. Catch-up | B13: 0 | C13: =B13+C12 -> 0 | D13: =C13+D12 -> 0 | E13: =D13+E12 -> 10292.617 | F13: =E13+F12 -> 33541.302 | G13: =F13+G12 -> 36006 | H13: =G13+H12 -> 36006 | I13: =H13+I12 -> 36006 | J13: =I13+J12 -> 36006 | ... L13: =K13+L12 -> 36006 | N13: =144024+36006 -> 180030
A14: Tier 4: Residual | B14: 0 | C14: =(((C5-C8)-C9)-C12) -> 0 | D14: =(((D5-D8)-D9)-D12) -> 0 | E14: =(((E5-E8)-E9)-E12) -> 0 | F14: =(((F5-F8)-F9)-F12) -> 0 | G14: =(((G5-G8)-G9)-G12) -> 727940.15 | H14: =(((H5-H8)-H9)-H12) -> 0 | I14: =(((I5-I8)-I9)-I12) -> 0 | J14: =(((J5-J8)-J9)-J12) -> 0 | ... L14: =(((L5-L8)-L9)-L12) -> 0 | M14: 36006 | N14: =J13/N13 -> 0.2
A15: SPLIT | M15: 144024 | N15: =L11/N13 -> 0.8
A16: LP Distribution | B16: 0 | C16: =Assumptions!$B$80*(C8+C9)+(1-Assumptions!$B$84)*C14 -> 19867.422 | D16: =Assumptions!$B$80*(D8+D9)+(1-Assumptions!$B$84)*D14 -> 54257.074 | E16: =Assumptions!$B$80*(E8+E9)+(1-Assumptions!$B$84)*E14 -> 595587.1 | F16: =Assumptions!$B$80*(F8+F9)+(1-Assumptions!$B$84)*F14 -> 0 | G16: =Assumptions!$B$80*(G8+G9)+(1-Assumptions!$B$84)*G14 -> 582352.12 | H16: =Assumptions!$B$80*(H8+H9)+(1-Assumptions!$B$84)*H14 -> 0 | I16: =Assumptions!$B$80*(I8+I9)+(1-Assumptions!$B$84)*I14 -> 0 | J16: =Assumptions!$B$80*(J8+J9)+(1-Assumptions!$B$84)*J14 -> 0 | ... L16: =Assumptions!$B$80*(L8+L9)+(1-Assumptions!$B$84)*L14 -> 0 | M16: =SUM(M14:M15) -> 180030
A17: GP Distribution | B17: 0 | C17: =Assumptions!$B$81*(C8+C9)+C12+Assumptions!$B$84*C14 -> 2207.4913 | D17: =Assumptions!$B$81*(D8+D9)+D12+Assumptions!$B$84*D14 -> 6028.5638 | E17: =Assumptions!$B$81*(E8+E9)+E12+Assumptions!$B$84*E14 -> 76468.962 | F17: =Assumptions!$B$81*(F8+F9)+F12+Assumptions!$B$84*F14 -> 23248.685 | G17: =Assumptions!$B$81*(G8+G9)+G12+Assumptions!$B$84*G14 -> 148052.73 | H17: =Assumptions!$B$81*(H8+H9)+H12+Assumptions!$B$84*H14 -> 0 | I17: =Assumptions!$B$81*(I8+I9)+I12+Assumptions!$B$84*I14 -> 0 | J17: =Assumptions!$B$81*(J8+J9)+J12+Assumptions!$B$84*J14 -> 0 | ... L17: =Assumptions!$B$81*(L8+L9)+L12+Assumptions!$B$84*L14 -> 0
A18: CASH FLOWS
A19: LP Net Cash Flow | B19: =-Assumptions!$B$80*B10 -> -540090 | C19: =C16 -> 19867.422 | D19: =D16 -> 54257.074 | E19: =E16 -> 595587.1 | F19: =F16 -> 0 | G19: =G16 -> 582352.12 | H19: =H16 -> 0 | I19: =I16 -> 0 | J19: =J16 -> 0 | ... L19: =L16 -> 0
A20: GP Net Cash Flow | B20: =-Assumptions!$B$81*B10 -> -60010 | C20: =C17 -> 2207.4913 | D20: =D17 -> 6028.5638 | E20: =E17 -> 76468.962 | F20: =F17 -> 23248.685 | G20: =G17 -> 148052.73 | H20: =H17 -> 0 | I20: =I17 -> 0 | J20: =J17 -> 0 | ... L20: =L17 -> 0
A22: RETURNS BY PARTNER | B22: LP | C22: GP
A23: IRR | B23: =IFERROR(IRR(B19:L19),0) -> 0.25405811 | C23: =IFERROR(IRR(B20:L20),0) -> 0.43592626
A24: Equity Multiple | B24: =IFERROR(SUM(C16:L16)/(Assumptions!$B$80*Acquisition!$B$23),0) -> 2.3182501 | C24: =IFERROR(SUM(C17:L17)/(Assumptions!$B$81*Acquisition!$B$23),0) -> 4.2660628
A25: Total Distributions | B25: =SUM(C16:L16) -> 1252063.7 | C25: =SUM(C17:L17) -> 256006.43
A26: Capital Invested | B26: =Assumptions!$B$80*Acquisition!$B$23 -> 540090 | C26: =Assumptions!$B$81*Acquisition!$B$23 -> 60010

Sheet Sensitivities
A1: SENSITIVITY ANALYSIS
A2: One-variable levered-return sensitivities. Annual cash-flow approximation of the monthly model (holds base exit year).
A4: 1. Purchase Price → IRR / Equity Multiple
A5: Price | B5: Y0 | C5: Y1 | D5: Y2 | E5: Y3 | F5: Y4 | G5: Y5 | H5: Y6 | I5: Y7 | J5: Y8 | K5: Y9 | L5: Y10 | M5: IRR | N5: EM
A6: =0.85*Assumptions!$B$8 -> 1105000 | B6: =-((A6*(1+Assumptions!$B$65)+Assumptions!$B$62*(Assumptions!$B$58*A6)+Assumptions!$B$56)-(Assumptions!$B$58*A6)) -> -536335 | C6: =IF(1<=Exit!$B$6,1*'Equity Returns'!C5+((Assumptions!$B$58*A6)/Acquisition!$B$10)*'Equity Returns'!C6+IF(AND(Assumptions!$B$67=1,1=(INT((Assumptions!$B$68-1)/12)+1)),(Refinance!$B$11+Refinance!$B$13+Refinance!$B$12*((Assumptions!$B$58*A6)/Acquisition!$B$10)),0)+IF(1=Exit!$B$6,(Exit!$B$9*(1-(Assumptions!$B$77+Assumptions!$B$78))+Exit!$B$12*((Assumptions!$B$58*A6)/Acquisition!$B$10)),0),0) -> 30947.413 | D6: =IF(2<=Exit!$B$6,1*'Equity Returns'!D5+((Assumptions!$B$58*A6)/Acquisition!$B$10)*'Equity Returns'!D6+IF(AND(Assumptions!$B$67=1,2=(INT((Assumptions!$B$68-1)/12)+1)),(Refinance!$B$11+Refinance!$B$13+Refinance!$B$12*((Assumptions!$B$58*A6)/Acquisition!$B$10)),0)+IF(2=Exit!$B$6,(Exit!$B$9*(1-(Assumptions!$B$77+Assumptions!$B$78))+Exit!$B$12*((Assumptions!$B$58*A6)/Acquisition!$B$10)),0),0) -> 69158.138 | E6: =IF(3<=Exit!$B$6,1*'Equity Returns'!E5+((Assumptions!$B$58*A6)/Acquisition!$B$10)*'Equity Returns'!E6+IF(AND(Assumptions!$B$67=1,3=(INT((Assumptions!$B$68-1)/12)+1)),(Refinance!$B$11+Refinance!$B$13+Refinance!$B$12*((Assumptions!$B$58*A6)/Acquisition!$B$10)),0)+IF(3=Exit!$B$6,(Exit!$B$9*(1-(Assumptions!$B$77+Assumptions!$B$78))+Exit!$B$12*((Assumptions!$B$58*A6)/Acquisition!$B$10)),0),0) -> 818029.64 | F6: =IF(4<=Exit!$B$6,1*'Equity Returns'!F5+((Assumptions!$B$58*A6)/Acquisition!$B$10)*'Equity Returns'!F6+IF(AND(Assumptions!$B$67=1,4=(INT((Assumptions!$B$68-1)/12)+1)),(Refinance!$B$11+Refinance!$B$13+Refinance!$B$12*((Assumptions!$B$58*A6)/Acquisition!$B$10)),0)+IF(4=Exit!$B$6,(Exit!$B$9*(1-(Assumptions!$B$77+Assumptions!$B$78))+Exit!$B$12*((Assumptions!$B$58*A6)/Acquisition!$B$10)),0),0) -> 39782.434 | G6: =IF(5<=Exit!$B$6,1*'Equity Returns'!G5+((Assumptions!$B$58*A6)/Acquisition!$B$10)*'Equity Returns'!G6+IF(AND(Assumptions!$B$67=1,5=(INT((Assumptions!$B$68-1)/12)+1)),(Refinance!$B$11+Refinance!$B$13+Refinance!$B$12*((Assumptions!$B$58*A6)/Acquisition!$B$10)),0)+IF(5=Exit!$B$6,(Exit!$B$9*(1-(Assumptions!$B$77+Assumptions!$B$78))+Exit!$B$12*((Assumptions!$B$58*A6)/Acquisition!$B$10)),0),0) -> 970670.1 | H6: =IF(6<=Exit!$B$6,1*'Equity Returns'!H5+((Assumptions!$B$58*A6)/Acquisition!$B$10)*'Equity Returns'!H6+IF(AND(Assumptions!$B$67=1,6=(INT((Assumptions!$B$68-1)/12)+1)),(Refinance!$B$11+Refinance!$B$13+Refinance!$B$12*((Assumptions!$B$58*A6)/Acquisition!$B$10)),0)+IF(6=Exit!$B$6,(Exit!$B$9*(1-(Assumptions!$B$77+Assumptions!$B$78))+Exit!$B$12*((Assumptions!$B$58*A6)/Acquisition!$B$10)),0),0) -> 0 | I6: =IF(7<=Exit!$B$6,1*'Equity Returns'!I5+((Assumptions!$B$58*A6)/Acquisition!$B$10)*'Equity Returns'!I6+IF(AND(Assumptions!$B$67=1,7=(INT((Assumptions!$B$68-1)/12)+1)),(Refinance!$B$11+Refinance!$B$13+Refinance!$B$12*((Assumptions!$B$58*A6)/Acquisition!$B$10)),0)+IF(7=Exit!$B$6,(Exit!$B$9*(1-(Assumptions!$B$77+Assumptions!$B$78))+Exit!$B$12*((Assumptions!$B$58*A6)/Acquisition!$B$10)),0),0) -> 0 | J6: =IF(8<=Exit!$B$6,1*'Equity Returns'!J5+((Assumptions!$B$58*A6)/Acquisition!$B$10)*'Equity Returns'!J6+IF(AND(Assumptions!$B$67=1,8=(INT((Assumptions!$B$68-1)/12)+1)),(Refinance!$B$11+Refinance!$B$13+Refinance!$B$12*((Assumptions!$B$58*A6)/Acquisition!$B$10)),0)+IF(8=Exit!$B$6,(Exit!$B$9*(1-(Assumptions!$B$77+Assumptions!$B$78))+Exit!$B$12*((Assumptions!$B$58*A6)/Acquisition!$B$10)),0),0) -> 0 | K6: =IF(9<=Exit!$B$6,1*'Equity Returns'!K5+((Assumptions!$B$58*A6)/Acquisition!$B$10)*'Equity Returns'!K6+IF(AND(Assumptions!$B$67=1,9=(INT((Assumptions!$B$68-1)/12)+1)),(Refinance!$B$11+Refinance!$B$13+Refinance!$B$12*((Assumptions!$B$58*A6)/Acquisition!$B$10)),0)+IF(9=Exit!$B$6,(Exit!$B$9*(1-(Assumptions!$B$77+Assumptions!$B$78))+Exit!$B$12*((Assumptions!$B$58*A6)/Acquisition!$B$10)),0),0) -> 0 | L6: =IF(10<=Exit!$B$6,1*'Equity Returns'!L5+((Assumptions!$B$58*A6)/Acquisition!$B$10)*'Equity Returns'!L6+IF(AND(Assumptions!$B$67=1,10=(INT((Assumptions!$B$68-1)/12)+1)),(Refinance!$B$11+Refinance!$B$13+Refinance!$B$12*((Assumptions!$B$58*A6)/Acquisition!$B$10)),0)+IF(10=Exit!$B$6,(Exit!$B$9*(1-(Assumptions!$B$77+Assumptions!$B$78))+Exit!$B$12*((Assumptions!$B$58*A6)/Acquisition!$B$10)),0),0) -> 0 | M6: =IFERROR(IRR(B6:L6),0) -> 0.4073496 | N6: =IFERROR(SUMIF(C6:L6,">0")/(-B6),0) -> 3.595864
A7: =0.9*Assumptions!$B$8 -> 1170000 | B7: =-((A7*(1+Assumptions!$B$65)+Assumptions!$B$62*(Assumptions!$B$58*A7)+Assumptions!$B$56)-(Assumptions!$B$58*A7)) -> -557590 | C7: =IF(1<=Exit!$B$6,1*'Equity Returns'!C5+((Assumptions!$B$58*A7)/Acquisition!$B$10)*'Equity Returns'!C6+IF(AND(Assumptions!$B$67=1,1=(INT((Assumptions!$B$68-1)/12)+1)),(Refinance!$B$11+Refinance!$B$13+Refinance!$B$12*((Assumptions!$B$58*A7)/Acquisition!$B$10)),0)+IF(1=Exit!$B$6,(Exit!$B$9*(1-(Assumptions!$B$77+Assumptions!$B$78))+Exit!$B$12*((Assumptions!$B$58*A7)/Acquisition!$B$10)),0),0) -> 27989.913 | D7: =IF(2<=Exit!$B$6,1*'Equity Returns'!D5+((Assumptions!$B$58*A7)/Acquisition!$B$10)*'Equity Returns'!D6+IF(AND(Assumptions!$B$67=1,2=(INT((Assumptions!$B$68-1)/12)+1)),(Refinance!$B$11+Refinance!$B$13+Refinance!$B$12*((Assumptions!$B$58*A7)/Acquisition!$B$10)),0)+IF(2=Exit!$B$6,(Exit!$B$9*(1-(Assumptions!$B$77+Assumptions!$B$78))+Exit!$B$12*((Assumptions!$B$58*A7)/Acquisition!$B$10)),0),0) -> 66200.638 | E7: =IF(3<=Exit!$B$6,1*'Equity Returns'!E5+((Assumptions!$B$58*A7)/Acquisition!$B$10)*'Equity Returns'!E6+IF(AND(Assumptions!$B$67=1,3=(INT((Assumptions!$B$68-1)/12)+1)),(Refinance!$B$11+Refinance!$B$13+Refinance!$B$12*((Assumptions!$B$58*A7)/Acquisition!$B$10)),0)+IF(3=Exit!$B$6,(Exit!$B$9*(1-(Assumptions!$B$77+Assumptions!$B$78))+Exit!$B$12*((Assumptions!$B$58*A7)/Acquisition!$B$10)),0),0) -> 769371.78 | F7: =IF(4<=Exit!$B$6,1*'Equity Returns'!F5+((Assumptions!$B$58*A7)/Acquisition!$B$10)*'Equity Returns'!F6+IF(AND(Assumptions!$B$67=1,4=(INT((Assumptions!$B$68-1)/12)+1)),(Refinance!$B$11+Refinance!$B$13+Refinance!$B$12*((Assumptions!$B$58*A7)/Acquisition!$B$10)),0)+IF(4=Exit!$B$6,(Exit!$B$9*(1-(Assumptions!$B$77+Assumptions!$B$78))+Exit!$B$12*((Assumptions!$B$58*A7)/Acquisition!$B$10)),0),0) -> 34271.185 | G7: =IF(5<=Exit!$B$6,1*'Equity Returns'!G5+((Assumptions!$B$58*A7)/Acquisition!$B$10)*'Equity Returns'!G6+IF(AND(Assumptions!$B$67=1,5=(INT((Assumptions!$B$68-1)/12)+1)),(Refinance!$B$11+Refinance!$B$13+Refinance!$B$12*((Assumptions!$B$58*A7)/Acquisition!$B$10)),0)+IF(5=Exit!$B$6,(Exit!$B$9*(1-(Assumptions!$B$77+Assumptions!$B$78))+Exit!$B$12*((Assumptions!$B$58*A7)/Acquisition!$B$10)),0),0) -> 890581.68 | H7: =IF(6<=Exit!$B$6,1*'Equity Returns'!H5+((Assumptions!$B$58*A7)/Acquisition!$B$10)*'Equity Returns'!H6+IF(AND(Assumptions!$B$67=1,6=(INT((Assumptions!$B$68-1)/12)+1)),(Refinance!$B$11+Refinance!$B$13+Refinance!$B$12*((Assumptions!$B$58*A7)/Acquisition!$B$10)),0)+IF(6=Exit!$B$6,(Exit!$B$9*(1-(Assumptions!$B$77+Assumptions!$B$78))+Exit!$B$12*((Assumptions!$B$58*A7)/Acquisition!$B$10)),0),0) -> 0 | I7: =IF(7<=Exit!$B$6,1*'Equity Returns'!I5+((Assumptions!$B$58*A7)/Acquisition!$B$10)*'Equity Returns'!I6+IF(AND(Assumptions!$B$67=1,7=(INT((Assumptions!$B$68-1)/12)+1)),(Refinance!$B$11+Refinance!$B$13+Refinance!$B$12*((Assumptions!$B$58*A7)/Acquisition!$B$10)),0)+IF(7=Exit!$B$6,(Exit!$B$9*(1-(Assumptions!$B$77+Assumptions!$B$78))+Exit!$B$12*((Assumptions!$B$58*A7)/Acquisition!$B$10)),0),0) -> 0 | J7: =IF(8<=Exit!$B$6,1*'Equity Returns'!J5+((Assumptions!$B$58*A7)/Acquisition!$B$10)*'Equity Returns'!J6+IF(AND(Assumptions!$B$67=1,8=(INT((Assumptions!$B$68-1)/12)+1)),(Refinance!$B$11+Refinance!$B$13+Refinance!$B$12*((Assumptions!$B$58*A7)/Acquisition!$B$10)),0)+IF(8=Exit!$B$6,(Exit!$B$9*(1-(Assumptions!$B$77+Assumptions!$B$78))+Exit!$B$12*((Assumptions!$B$58*A7)/Acquisition!$B$10)),0),0) -> 0 | K7: =IF(9<=Exit!$B$6,1*'Equity Returns'!K5+((Assumptions!$B$58*A7)/Acquisition!$B$10)*'Equity Returns'!K6+IF(AND(Assumptions!$B$67=1,9=(INT((Assumptions!$B$68-1)/12)+1)),(Refinance!$B$11+Refinance!$B$13+Refinance!$B$12*((Assumptions!$B$58*A7)/Acquisition!$B$10)),0)+IF(9=Exit!$B$6,(Exit!$B$9*(1-(Assumptions!$B$77+Assumptions!$B$78))+Exit!$B$12*((Assumptions!$B$58*A7)/Acquisition!$B$10)),0),0) -> 0 | L7: =IF(10<=Exit!$B$6,1*'Equity Returns'!L5+((Assumptions!$B$58*A7)/Acquisition!$B$10)*'Equity Returns'!L6+IF(AND(Assumptions!$B$67=1,10=(INT((Assumptions!$B$68-1)/12)+1)),(Refinance!$B$11+Refinance!$B$13+Refinance!$B$12*((Assumptions!$B$58*A7)/Acquisition!$B$10)),0)+IF(10=Exit!$B$6,(Exit!$B$9*(1-(Assumptions!$B$77+Assumptions!$B$78))+Exit!$B$12*((Assumptions!$B$58*A7)/Acquisition!$B$10)),0),0) -> 0 | M7: =IFERROR(IRR(B7:L7),0) -> 0.36414753 | N7: =IFERROR(SUMIF(C7:L7,">0")/(-B7),0) -> 3.2074019
A8: =0.95*Assumptions!$B$8 -> 1235000 | B8: =-((A8*(1+Assumptions!$B$65)+Assumptions!$B$62*(Assumptions!$B$58*A8)+Assumptions!$B$56)-(Assumptions!$B$58*A8)) -> -578845 | C8: =IF(1<=Exit!$B$6,1*'Equity Returns'!C5+((Assumptions!$B$58*A8)/Acquisition!$B$10)*'Equity Returns'!C6+IF(AND(Assumptions!$B$67=1,1=(INT((Assumptions!$B$68-1)/12)+1)),(Refinance!$B$11+Refinance!$B$13+Refinance!$B$12*((Assumptions!$B$58*A8)/Acquisition!$B$10)),0)+IF(1=Exit!$B$6,(Exit!$B$9*(1-(Assumptions!$B$77+Assumptions!$B$78))+Exit!$B$12*((Assumptions!$B$58*A8)/Acquisition!$B$10)),0),0) -> 25032.413 | D8: =IF(2<=Exit!$B$6,1*'Equity Returns'!D5+((Assumptions!$B$58*A8)/Acquisition!$B$10)*'Equity Returns'!D6+IF(AND(Assumptions!$B$67=1,2=(INT((Assumptions!$B$68-1)/12)+1)),(Refinance!$B$11+Refinance!$B$13+Refinance!$B$12*((Assumptions!$B$58*A8)/Acquisition!$B$10)),0)+IF(2=Exit!$B$6,(Exit!$B$9*(1-(Assumptions!$B$77+Assumptions!$B$78))+Exit!$B$12*((Assumptions!$B$58*A8)/Acquisition!$B$10)),0),0) -> 63243.138 | E8: =IF(3<=Exit!$B$6,1*'Equity Returns'!E5+((Assumptions!$B$58*A8)/Acquisition!$B$10)*'Equity Returns'!E6+IF(AND(Assumptions!$B$67=1,3=(INT((Assumptions!$B$68-1)/12)+1)),(Refinance!$B$11+Refinance!$B$13+Refinance!$B$12*((Assumptions!$B$58*A8)/Acquisition!$B$10)),0)+IF(3=Exit!$B$6,(Exit!$B$9*(1-(Assumptions!$B$77+Assumptions!$B$78))+Exit!$B$12*((Assumptions!$B$58*A8)/Acquisition!$B$10)),0),0) -> 720713.92 | F8: =IF(4<=Exit!$B$6,1*'Equity Returns'!F5+((Assumptions!$B$58*A8)/Acquisition!$B$10)*'Equity Returns'!F6+IF(AND(Assumptions!$B$67=1,4=(INT((Assumptions!$B$68-1)/12)+1)),(Refinance!$B$11+Refinance!$B$13+Refinance!$B$12*((Assumptions!$B$58*A8)/Acquisition!$B$10)),0)+IF(4=Exit!$B$6,(Exit!$B$9*(1-(Assumptions!$B$77+Assumptions!$B$78))+Exit!$B$12*((Assumptions!$B$58*A8)/Acquisition!$B$10)),0),0) -> 28759.935 | G8: =IF(5<=Exit!$B$6,1*'Equity Returns'!G5+((Assumptions!$B$58*A8)/Acquisition!$B$10)*'Equity Returns'!G6+IF(AND(Assumptions!$B$67=1,5=(INT((Assumptions!$B$68-1)/12)+1)),(Refinance!$B$11+Refinance!$B$13+Refinance!$B$12*((Assumptions!$B$58*A8)/Acquisition!$B$10)),0)+IF(5=Exit!$B$6,(Exit!$B$9*(1-(Assumptions!$B$77+Assumptions!$B$78))+Exit!$B$12*((Assumptions!$B$58*A8)/Acquisition!$B$10)),0),0) -> 810493.27 | H8: =IF(6<=Exit!$B$6,1*'Equity Returns'!H5+((Assumptions!$B$58*A8)/Acquisition!$B$10)*'Equity Returns'!H6+IF(AND(Assumptions!$B$67=1,6=(INT((Assumptions!$B$68-1)/12)+1)),(Refinance!$B$11+Refinance!$B$13+Refinance!$B$12*((Assumptions!$B$58*A8)/Acquisition!$B$10)),0)+IF(6=Exit!$B$6,(Exit!$B$9*(1-(Assumptions!$B$77+Assumptions!$B$78))+Exit!$B$12*((Assumptions!$B$58*A8)/Acquisition!$B$10)),0),0) -> 0 | I8: =IF(7<=Exit!$B$6,1*'Equity Returns'!I5+((Assumptions!$B$58*A8)/Acquisition!$B$10)*'Equity Returns'!I6+IF(AND(Assumptions!$B$67=1,7=(INT((Assumptions!$B$68-1)/12)+1)),(Refinance!$B$11+Refinance!$B$13+Refinance!$B$12*((Assumptions!$B$58*A8)/Acquisition!$B$10)),0)+IF(7=Exit!$B$6,(Exit!$B$9*(1-(Assumptions!$B$77+Assumptions!$B$78))+Exit!$B$12*((Assumptions!$B$58*A8)/Acquisition!$B$10)),0),0) -> 0 | J8: =IF(8<=Exit!$B$6,1*'Equity Returns'!J5+((Assumptions!$B$58*A8)/Acquisition!$B$10)*'Equity Returns'!J6+IF(AND(Assumptions!$B$67=1,8=(INT((Assumptions!$B$68-1)/12)+1)),(Refinance!$B$11+Refinance!$B$13+Refinance!$B$12*((Assumptions!$B$58*A8)/Acquisition!$B$10)),0)+IF(8=Exit!$B$6,(Exit!$B$9*(1-(Assumptions!$B$77+Assumptions!$B$78))+Exit!$B$12*((Assumptions!$B$58*A8)/Acquisition!$B$10)),0),0) -> 0 | K8: =IF(9<=Exit!$B$6,1*'Equity Returns'!K5+((Assumptions!$B$58*A8)/Acquisition!$B$10)*'Equity Returns'!K6+IF(AND(Assumptions!$B$67=1,9=(INT((Assumptions!$B$68-1)/12)+1)),(Refinance!$B$11+Refinance!$B$13+Refinance!$B$12*((Assumptions!$B$58*A8)/Acquisition!$B$10)),0)+IF(9=Exit!$B$6,(Exit!$B$9*(1-(Assumptions!$B$77+Assumptions!$B$78))+Exit!$B$12*((Assumptions!$B$58*A8)/Acquisition!$B$10)),0),0) -> 0 | L8: =IF(10<=Exit!$B$6,1*'Equity Returns'!L5+((Assumptions!$B$58*A8)/Acquisition!$B$10)*'Equity Returns'!L6+IF(AND(Assumptions!$B$67=1,10=(INT((Assumptions!$B$68-1)/12)+1)),(Refinance!$B$11+Refinance!$B$13+Refinance!$B$12*((Assumptions!$B$58*A8)/Acquisition!$B$10)),0)+IF(10=Exit!$B$6,(Exit!$B$9*(1-(Assumptions!$B$77+Assumptions!$B$78))+Exit!$B$12*((Assumptions!$B$58*A8)/Acquisition!$B$10)),0),0) -> 0 | M8: =IFERROR(IRR(B8:L8),0) -> 0.32094867 | N8: =IFERROR(SUMIF(C8:L8,">0")/(-B8),0) -> 2.8474681
A9: =1*Assumptions!$B$8 -> 1300000 | B9: =-((A9*(1+Assumptions!$B$65)+Assumptions!$B$62*(Assumptions!$B$58*A9)+Assumptions!$B$56)-(Assumptions!$B$58*A9)) -> -600100 | C9: =IF(1<=Exit!$B$6,1*'Equity Returns'!C5+((Assumptions!$B$58*A9)/Acquisition!$B$10)*'Equity Returns'!C6+IF(AND(Assumptions!$B$67=1,1=(INT((Assumptions!$B$68-1)/12)+1)),(Refinance!$B$11+Refinance!$B$13+Refinance!$B$12*((Assumptions!$B$58*A9)/Acquisition!$B$10)),0)+IF(1=Exit!$B$6,(Exit!$B$9*(1-(Assumptions!$B$77+Assumptions!$B$78))+Exit!$B$12*((Assumptions!$B$58*A9)/Acquisition!$B$10)),0),0) -> 22074.913 | D9: =IF(2<=Exit!$B$6,1*'Equity Returns'!D5+((Assumptions!$B$58*A9)/Acquisition!$B$10)*'Equity Returns'!D6+IF(AND(Assumptions!$B$67=1,2=(INT((Assumptions!$B$68-1)/12)+1)),(Refinance!$B$11+Refinance!$B$13+Refinance!$B$12*((Assumptions!$B$58*A9)/Acquisition!$B$10)),0)+IF(2=Exit!$B$6,(Exit!$B$9*(1-(Assumptions!$B$77+Assumptions!$B$78))+Exit!$B$12*((Assumptions!$B$58*A9)/Acquisition!$B$10)),0),0) -> 60285.638 | E9: =IF(3<=Exit!$B$6,1*'Equity Returns'!E5+((Assumptions!$B$58*A9)/Acquisition!$B$10)*'Equity Returns'!E6+IF(AND(Assumptions!$B$67=1,3=(INT((Assumptions!$B$68-1)/12)+1)),(Refinance!$B$11+Refinance!$B$13+Refinance!$B$12*((Assumptions!$B$58*A9)/Acquisition!$B$10)),0)+IF(3=Exit!$B$6,(Exit!$B$9*(1-(Assumptions!$B$77+Assumptions!$B$78))+Exit!$B$12*((Assumptions!$B$58*A9)/Acquisition!$B$10)),0),0) -> 672056.07 | F9: =IF(4<=Exit!$B$6,1*'Equity Returns'!F5+((Assumptions!$B$58*A9)/Acquisition!$B$10)*'Equity Returns'!F6+IF(AND(Assumptions!$B$67=1,4=(INT((Assumptions!$B$68-1)/12)+1)),(Refinance!$B$11+Refinance!$B$13+Refinance!$B$12*((Assumptions!$B$58*A9)/Acquisition!$B$10)),0)+IF(4=Exit!$B$6,(Exit!$B$9*(1-(Assumptions!$B$77+Assumptions!$B$78))+Exit!$B$12*((Assumptions!$B$58*A9)/Acquisition!$B$10)),0),0) -> 23248.685 | G9: =IF(5<=Exit!$B$6,1*'Equity Returns'!G5+((Assumptions!$B$58*A9)/Acquisition!$B$10)*'Equity Returns'!G6+IF(AND(Assumptions!$B$67=1,5=(INT((Assumptions!$B$68-1)/12)+1)),(Refinance!$B$11+Refinance!$B$13+Refinance!$B$12*((Assumptions!$B$58*A9)/Acquisition!$B$10)),0)+IF(5=Exit!$B$6,(Exit!$B$9*(1-(Assumptions!$B$77+Assumptions!$B$78))+Exit!$B$12*((Assumptions!$B$58*A9)/Acquisition!$B$10)),0),0) -> 730404.85 | H9: =IF(6<=Exit!$B$6,1*'Equity Returns'!H5+((Assumptions!$B$58*A9)/Acquisition!$B$10)*'Equity Returns'!H6+IF(AND(Assumptions!$B$67=1,6=(INT((Assumptions!$B$68-1)/12)+1)),(Refinance!$B$11+Refinance!$B$13+Refinance!$B$12*((Assumptions!$B$58*A9)/Acquisition!$B$10)),0)+IF(6=Exit!$B$6,(Exit!$B$9*(1-(Assumptions!$B$77+Assumptions!$B$78))+Exit!$B$12*((Assumptions!$B$58*A9)/Acquisition!$B$10)),0),0) -> 0 | I9: =IF(7<=Exit!$B$6,1*'Equity Returns'!I5+((Assumptions!$B$58*A9)/Acquisition!$B$10)*'Equity Returns'!I6+IF(AND(Assumptions!$B$67=1,7=(INT((Assumptions!$B$68-1)/12)+1)),(Refinance!$B$11+Refinance!$B$13+Refinance!$B$12*((Assumptions!$B$58*A9)/Acquisition!$B$10)),0)+IF(7=Exit!$B$6,(Exit!$B$9*(1-(Assumptions!$B$77+Assumptions!$B$78))+Exit!$B$12*((Assumptions!$B$58*A9)/Acquisition!$B$10)),0),0) -> 0 | J9: =IF(8<=Exit!$B$6,1*'Equity Returns'!J5+((Assumptions!$B$58*A9)/Acquisition!$B$10)*'Equity Returns'!J6+IF(AND(Assumptions!$B$67=1,8=(INT((Assumptions!$B$68-1)/12)+1)),(Refinance!$B$11+Refinance!$B$13+Refinance!$B$12*((Assumptions!$B$58*A9)/Acquisition!$B$10)),0)+IF(8=Exit!$B$6,(Exit!$B$9*(1-(Assumptions!$B$77+Assumptions!$B$78))+Exit!$B$12*((Assumptions!$B$58*A9)/Acquisition!$B$10)),0),0) -> 0 | K9: =IF(9<=Exit!$B$6,1*'Equity Returns'!K5+((Assumptions!$B$58*A9)/Acquisition!$B$10)*'Equity Returns'!K6+IF(AND(Assumptions!$B$67=1,9=(INT((Assumptions!$B$68-1)/12)+1)),(Refinance!$B$11+Refinance!$B$13+Refinance!$B$12*((Assumptions!$B$58*A9)/Acquisition!$B$10)),0)+IF(9=Exit!$B$6,(Exit!$B$9*(1-(Assumptions!$B$77+Assumptions!$B$78))+Exit!$B$12*((Assumptions!$B$58*A9)/Acquisition!$B$10)),0),0) -> 0 | L9: =IF(10<=Exit!$B$6,1*'Equity Returns'!L5+((Assumptions!$B$58*A9)/Acquisition!$B$10)*'Equity Returns'!L6+IF(AND(Assumptions!$B$67=1,10=(INT((Assumptions!$B$68-1)/12)+1)),(Refinance!$B$11+Refinance!$B$13+Refinance!$B$12*((Assumptions!$B$58*A9)/Acquisition!$B$10)),0)+IF(10=Exit!$B$6,(Exit!$B$9*(1-(Assumptions!$B$77+Assumptions!$B$78))+Exit!$B$12*((Assumptions!$B$58*A9)/Acquisition!$B$10)),0),0) -> 0 | M9: =IFERROR(IRR(B9:L9),0) -> 0.27741656 | N9: =IFERROR(SUMIF(C9:L9,">0")/(-B9),0) -> 2.5130314
A10: =1.05*Assumptions!$B$8 -> 1365000 | B10: =-((A10*(1+Assumptions!$B$65)+Assumptions!$B$62*(Assumptions!$B$58*A10)+Assumptions!$B$56)-(Assumptions!$B$58*A10)) -> -621355 | C10: =IF(1<=Exit!$B$6,1*'Equity Returns'!C5+((Assumptions!$B$58*A10)/Acquisition!$B$10)*'Equity Returns'!C6+IF(AND(Assumptions!$B$67=1,1=(INT((Assumptions!$B$68-1)/12)+1)),(Refinance!$B$11+Refinance!$B$13+Refinance!$B$12*((Assumptions!$B$58*A10)/Acquisition!$B$10)),0)+IF(1=Exit!$B$6,(Exit!$B$9*(1-(Assumptions!$B$77+Assumptions!$B$78))+Exit!$B$12*((Assumptions!$B$58*A10)/Acquisition!$B$10)),0),0) -> 19117.413 | D10: =IF(2<=Exit!$B$6,1*'Equity Returns'!D5+((Assumptions!$B$58*A10)/Acquisition!$B$10)*'Equity Returns'!D6+IF(AND(Assumptions!$B$67=1,2=(INT((Assumptions!$B$68-1)/12)+1)),(Refinance!$B$11+Refinance!$B$13+Refinance!$B$12*((Assumptions!$B$58*A10)/Acquisition!$B$10)),0)+IF(2=Exit!$B$6,(Exit!$B$9*(1-(Assumptions!$B$77+Assumptions!$B$78))+Exit!$B$12*((Assumptions!$B$58*A10)/Acquisition!$B$10)),0),0) -> 57328.138 | E10: =IF(3<=Exit!$B$6,1*'Equity Returns'!E5+((Assumptions!$B$58*A10)/Acquisition!$B$10)*'Equity Returns'!E6+IF(AND(Assumptions!$B$67=1,3=(INT((Assumptions!$B$68-1)/12)+1)),(Refinance!$B$11+Refinance!$B$13+Refinance!$B$12*((Assumptions!$B$58*A10)/Acquisition!$B$10)),0)+IF(3=Exit!$B$6,(Exit!$B$9*(1-(Assumptions!$B$77+Assumptions!$B$78))+Exit!$B$12*((Assumptions!$B$58*A10)/Acquisition!$B$10)),0),0) -> 623398.21 | F10: =IF(4<=Exit!$B$6,1*'Equity Returns'!F5+((Assumptions!$B$58*A10)/Acquisition!$B$10)*'Equity Returns'!F6+IF(AND(Assumptions!$B$67=1,4=(INT((Assumptions!$B$68-1)/12)+1)),(Refinance!$B$11+Refinance!$B$13+Refinance!$B$12*((Assumptions!$B$58*A10)/Acquisition!$B$10)),0)+IF(4=Exit!$B$6,(Exit!$B$9*(1-(Assumptions!$B$77+Assumptions!$B$78))+Exit!$B$12*((Assumptions!$B$58*A10)/Acquisition!$B$10)),0),0) -> 17737.436 | G10: =IF(5<=Exit!$B$6,1*'Equity Returns'!G5+((Assumptions!$B$58*A10)/Acquisition!$B$10)*'Equity Returns'!G6+IF(AND(Assumptions!$B$67=1,5=(INT((Assumptions!$B$68-1)/12)+1)),(Refinance!$B$11+Refinance!$B$13+Refinance!$B$12*((Assumptions!$B$58*A10)/Acquisition!$B$10)),0)+IF(5=Exit!$B$6,(Exit!$B$9*(1-(Assumptions!$B$77+Assumptions!$B$78))+Exit!$B$12*((Assumptions!$B$58*A10)/Acquisition!$B$10)),0),0) -> 650316.43 | H10: =IF(6<=Exit!$B$6,1*'Equity Returns'!H5+((Assumptions!$B$58*A10)/Acquisition!$B$10)*'Equity Returns'!H6+IF(AND(Assumptions!$B$67=1,6=(INT((Assumptions!$B$68-1)/12)+1)),(Refinance!$B$11+Refinance!$B$13+Refinance!$B$12*((Assumptions!$B$58*A10)/Acquisition!$B$10)),0)+IF(6=Exit!$B$6,(Exit!$B$9*(1-(Assumptions!$B$77+Assumptions!$B$78))+Exit!$B$12*((Assumptions!$B$58*A10)/Acquisition!$B$10)),0),0) -> 0 | I10: =IF(7<=Exit!$B$6,1*'Equity Returns'!I5+((Assumptions!$B$58*A10)/Acquisition!$B$10)*'Equity Returns'!I6+IF(AND(Assumptions!$B$67=1,7=(INT((Assumptions!$B$68-1)/12)+1)),(Refinance!$B$11+Refinance!$B$13+Refinance!$B$12*((Assumptions!$B$58*A10)/Acquisition!$B$10)),0)+IF(7=Exit!$B$6,(Exit!$B$9*(1-(Assumptions!$B$77+Assumptions!$B$78))+Exit!$B$12*((Assumptions!$B$58*A10)/Acquisition!$B$10)),0),0) -> 0 | J10: =IF(8<=Exit!$B$6,1*'Equity Returns'!J5+((Assumptions!$B$58*A10)/Acquisition!$B$10)*'Equity Returns'!J6+IF(AND(Assumptions!$B$67=1,8=(INT((Assumptions!$B$68-1)/12)+1)),(Refinance!$B$11+Refinance!$B$13+Refinance!$B$12*((Assumptions!$B$58*A10)/Acquisition!$B$10)),0)+IF(8=Exit!$B$6,(Exit!$B$9*(1-(Assumptions!$B$77+Assumptions!$B$78))+Exit!$B$12*((Assumptions!$B$58*A10)/Acquisition!$B$10)),0),0) -> 0 | K10: =IF(9<=Exit!$B$6,1*'Equity Returns'!K5+((Assumptions!$B$58*A10)/Acquisition!$B$10)*'Equity Returns'!K6+IF(AND(Assumptions!$B$67=1,9=(INT((Assumptions!$B$68-1)/12)+1)),(Refinance!$B$11+Refinance!$B$13+Refinance!$B$12*((Assumptions!$B$58*A10)/Acquisition!$B$10)),0)+IF(9=Exit!$B$6,(Exit!$B$9*(1-(Assumptions!$B$77+Assumptions!$B$78))+Exit!$B$12*((Assumptions!$B$58*A10)/Acquisition!$B$10)),0),0) -> 0 | L10: =IF(10<=Exit!$B$6,1*'Equity Returns'!L5+((Assumptions!$B$58*A10)/Acquisition!$B$10)*'Equity Returns'!L6+IF(AND(Assumptions!$B$67=1,10=(INT((Assumptions!$B$68-1)/12)+1)),(Refinance!$B$11+Refinance!$B$13+Refinance!$B$12*((Assumptions!$B$58*A10)/Acquisition!$B$10)),0)+IF(10=Exit!$B$6,(Exit!$B$9*(1-(Assumptions!$B$77+Assumptions!$B$78))+Exit!$B$12*((Assumptions!$B$58*A10)/Acquisition!$B$10)),0),0) -> 0 | M10: =IFERROR(IRR(B10:L10),0) -> 0.23316061 | N10: =IFERROR(SUMIF(C10:L10,">0")/(-B10),0) -> 2.2014752
A11: =1.1*Assumptions!$B$8 -> 1430000 | B11: =-((A11*(1+Assumptions!$B$65)+Assumptions!$B$62*(Assumptions!$B$58*A11)+Assumptions!$B$56)-(Assumptions!$B$58*A11)) -> -642610 | C11: =IF(1<=Exit!$B$6,1*'Equity Returns'!C5+((Assumptions!$B$58*A11)/Acquisition!$B$10)*'Equity Returns'!C6+IF(AND(Assumptions!$B$67=1,1=(INT((Assumptions!$B$68-1)/12)+1)),(Refinance!$B$11+Refinance!$B$13+Refinance!$B$12*((Assumptions!$B$58*A11)/Acquisition!$B$10)),0)+IF(1=Exit!$B$6,(Exit!$B$9*(1-(Assumptions!$B$77+Assumptions!$B$78))+Exit!$B$12*((Assumptions!$B$58*A11)/Acquisition!$B$10)),0),0) -> 16159.913 | D11: =IF(2<=Exit!$B$6,1*'Equity Returns'!D5+((Assumptions!$B$58*A11)/Acquisition!$B$10)*'Equity Returns'!D6+IF(AND(Assumptions!$B$67=1,2=(INT((Assumptions!$B$68-1)/12)+1)),(Refinance!$B$11+Refinance!$B$13+Refinance!$B$12*((Assumptions!$B$58*A11)/Acquisition!$B$10)),0)+IF(2=Exit!$B$6,(Exit!$B$9*(1-(Assumptions!$B$77+Assumptions!$B$78))+Exit!$B$12*((Assumptions!$B$58*A11)/Acquisition!$B$10)),0),0) -> 54370.638 | E11: =IF(3<=Exit!$B$6,1*'Equity Returns'!E5+((Assumptions!$B$58*A11)/Acquisition!$B$10)*'Equity Returns'!E6+IF(AND(Assumptions!$B$67=1,3=(INT((Assumptions!$B$68-1)/12)+1)),(Refinance!$B$11+Refinance!$B$13+Refinance!$B$12*((Assumptions!$B$58*A11)/Acquisition!$B$10)),0)+IF(3=Exit!$B$6,(Exit!$B$9*(1-(Assumptions!$B$77+Assumptions!$B$78))+Exit!$B$12*((Assumptions!$B$58*A11)/Acquisition!$B$10)),0),0) -> 574740.35 | F11: =IF(4<=Exit!$B$6,1*'Equity Returns'!F5+((Assumptions!$B$58*A11)/Acquisition!$B$10)*'Equity Returns'!F6+IF(AND(Assumptions!$B$67=1,4=(INT((Assumptions!$B$68-1)/12)+1)),(Refinance!$B$11+Refinance!$B$13+Refinance!$B$12*((Assumptions!$B$58*A11)/Acquisition!$B$10)),0)+IF(4=Exit!$B$6,(Exit!$B$9*(1-(Assumptions!$B$77+Assumptions!$B$78))+Exit!$B$12*((Assumptions!$B$58*A11)/Acquisition!$B$10)),0),0) -> 12226.186 | G11: =IF(5<=Exit!$B$6,1*'Equity Returns'!G5+((Assumptions!$B$58*A11)/Acquisition!$B$10)*'Equity Returns'!G6+IF(AND(Assumptions!$B$67=1,5=(INT((Assumptions!$B$68-1)/12)+1)),(Refinance!$B$11+Refinance!$B$13+Refinance!$B$12*((Assumptions!$B$58*A11)/Acquisition!$B$10)),0)+IF(5=Exit!$B$6,(Exit!$B$9*(1-(Assumptions!$B$77+Assumptions!$B$78))+Exit!$B$12*((Assumptions!$B$58*A11)/Acquisition!$B$10)),0),0) -> 570228.01 | H11: =IF(6<=Exit!$B$6,1*'Equity Returns'!H5+((Assumptions!$B$58*A11)/Acquisition!$B$10)*'Equity Returns'!H6+IF(AND(Assumptions!$B$67=1,6=(INT((Assumptions!$B$68-1)/12)+1)),(Refinance!$B$11+Refinance!$B$13+Refinance!$B$12*((Assumptions!$B$58*A11)/Acquisition!$B$10)),0)+IF(6=Exit!$B$6,(Exit!$B$9*(1-(Assumptions!$B$77+Assumptions!$B$78))+Exit!$B$12*((Assumptions!$B$58*A11)/Acquisition!$B$10)),0),0) -> 0 | I11: =IF(7<=Exit!$B$6,1*'Equity Returns'!I5+((Assumptions!$B$58*A11)/Acquisition!$B$10)*'Equity Returns'!I6+IF(AND(Assumptions!$B$67=1,7=(INT((Assumptions!$B$68-1)/12)+1)),(Refinance!$B$11+Refinance!$B$13+Refinance!$B$12*((Assumptions!$B$58*A11)/Acquisition!$B$10)),0)+IF(7=Exit!$B$6,(Exit!$B$9*(1-(Assumptions!$B$77+Assumptions!$B$78))+Exit!$B$12*((Assumptions!$B$58*A11)/Acquisition!$B$10)),0),0) -> 0 | J11: =IF(8<=Exit!$B$6,1*'Equity Returns'!J5+((Assumptions!$B$58*A11)/Acquisition!$B$10)*'Equity Returns'!J6+IF(AND(Assumptions!$B$67=1,8=(INT((Assumptions!$B$68-1)/12)+1)),(Refinance!$B$11+Refinance!$B$13+Refinance!$B$12*((Assumptions!$B$58*A11)/Acquisition!$B$10)),0)+IF(8=Exit!$B$6,(Exit!$B$9*(1-(Assumptions!$B$77+Assumptions!$B$78))+Exit!$B$12*((Assumptions!$B$58*A11)/Acquisition!$B$10)),0),0) -> 0 | K11: =IF(9<=Exit!$B$6,1*'Equity Returns'!K5+((Assumptions!$B$58*A11)/Acquisition!$B$10)*'Equity Returns'!K6+IF(AND(Assumptions!$B$67=1,9=(INT((Assumptions!$B$68-1)/12)+1)),(Refinance!$B$11+Refinance!$B$13+Refinance!$B$12*((Assumptions!$B$58*A11)/Acquisition!$B$10)),0)+IF(9=Exit!$B$6,(Exit!$B$9*(1-(Assumptions!$B$77+Assumptions!$B$78))+Exit!$B$12*((Assumptions!$B$58*A11)/Acquisition!$B$10)),0),0) -> 0 | L11: =IF(10<=Exit!$B$6,1*'Equity Returns'!L5+((Assumptions!$B$58*A11)/Acquisition!$B$10)*'Equity Returns'!L6+IF(AND(Assumptions!$B$67=1,10=(INT((Assumptions!$B$68-1)/12)+1)),(Refinance!$B$11+Refinance!$B$13+Refinance!$B$12*((Assumptions!$B$58*A11)/Acquisition!$B$10)),0)+IF(10=Exit!$B$6,(Exit!$B$9*(1-(Assumptions!$B$77+Assumptions!$B$78))+Exit!$B$12*((Assumptions!$B$58*A11)/Acquisition!$B$10)),0),0) -> 0 | M11: =IFERROR(IRR(B11:L11),0) -> 0.18770269 | N11: =IFERROR(SUMIF(C11:L11,">0")/(-B11),0) -> 1.9105291
A12: =1.15*Assumptions!$B$8 -> 1495000 | B12: =-((A12*(1+Assumptions!$B$65)+Assumptions!$B$62*(Assumptions!$B$58*A12)+Assumptions!$B$56)-(Assumptions!$B$58*A12)) -> -663865 | C12: =IF(1<=Exit!$B$6,1*'Equity Returns'!C5+((Assumptions!$B$58*A12)/Acquisition!$B$10)*'Equity Returns'!C6+IF(AND(Assumptions!$B$67=1,1=(INT((Assumptions!$B$68-1)/12)+1)),(Refinance!$B$11+Refinance!$B$13+Refinance!$B$12*((Assumptions!$B$58*A12)/Acquisition!$B$10)),0)+IF(1=Exit!$B$6,(Exit!$B$9*(1-(Assumptions!$B$77+Assumptions!$B$78))+Exit!$B$12*((Assumptions!$B$58*A12)/Acquisition!$B$10)),0),0) -> 13202.413 | D12: =IF(2<=Exit!$B$6,1*'Equity Returns'!D5+((Assumptions!$B$58*A12)/Acquisition!$B$10)*'Equity Returns'!D6+IF(AND(Assumptions!$B$67=1,2=(INT((Assumptions!$B$68-1)/12)+1)),(Refinance!$B$11+Refinance!$B$13+Refinance!$B$12*((Assumptions!$B$58*A12)/Acquisition!$B$10)),0)+IF(2=Exit!$B$6,(Exit!$B$9*(1-(Assumptions!$B$77+Assumptions!$B$78))+Exit!$B$12*((Assumptions!$B$58*A12)/Acquisition!$B$10)),0),0) -> 51413.138 | E12: =IF(3<=Exit!$B$6,1*'Equity Returns'!E5+((Assumptions!$B$58*A12)/Acquisition!$B$10)*'Equity Returns'!E6+IF(AND(Assumptions!$B$67=1,3=(INT((Assumptions!$B$68-1)/12)+1)),(Refinance!$B$11+Refinance!$B$13+Refinance!$B$12*((Assumptions!$B$58*A12)/Acquisition!$B$10)),0)+IF(3=Exit!$B$6,(Exit!$B$9*(1-(Assumptions!$B$77+Assumptions!$B$78))+Exit!$B$12*((Assumptions!$B$58*A12)/Acquisition!$B$10)),0),0) -> 526082.49 | F12: =IF(4<=Exit!$B$6,1*'Equity Returns'!F5+((Assumptions!$B$58*A12)/Acquisition!$B$10)*'Equity Returns'!F6+IF(AND(Assumptions!$B$67=1,4=(INT((Assumptions!$B$68-1)/12)+1)),(Refinance!$B$11+Refinance!$B$13+Refinance!$B$12*((Assumptions!$B$58*A12)/Acquisition!$B$10)),0)+IF(4=Exit!$B$6,(Exit!$B$9*(1-(Assumptions!$B$77+Assumptions!$B$78))+Exit!$B$12*((Assumptions!$B$58*A12)/Acquisition!$B$10)),0),0) -> 6714.9367 | G12: =IF(5<=Exit!$B$6,1*'Equity Returns'!G5+((Assumptions!$B$58*A12)/Acquisition!$B$10)*'Equity Returns'!G6+IF(AND(Assumptions!$B$67=1,5=(INT((Assumptions!$B$68-1)/12)+1)),(Refinance!$B$11+Refinance!$B$13+Refinance!$B$12*((Assumptions!$B$58*A12)/Acquisition!$B$10)),0)+IF(5=Exit!$B$6,(Exit!$B$9*(1-(Assumptions!$B$77+Assumptions!$B$78))+Exit!$B$12*((Assumptions!$B$58*A12)/Acquisition!$B$10)),0),0) -> 490139.6 | H12: =IF(6<=Exit!$B$6,1*'Equity Returns'!H5+((Assumptions!$B$58*A12)/Acquisition!$B$10)*'Equity Returns'!H6+IF(AND(Assumptions!$B$67=1,6=(INT((Assumptions!$B$68-1)/12)+1)),(Refinance!$B$11+Refinance!$B$13+Refinance!$B$12*((Assumptions!$B$58*A12)/Acquisition!$B$10)),0)+IF(6=Exit!$B$6,(Exit!$B$9*(1-(Assumptions!$B$77+Assumptions!$B$78))+Exit!$B$12*((Assumptions!$B$58*A12)/Acquisition!$B$10)),0),0) -> 0 | I12: =IF(7<=Exit!$B$6,1*'Equity Returns'!I5+((Assumptions!$B$58*A12)/Acquisition!$B$10)*'Equity Returns'!I6+IF(AND(Assumptions!$B$67=1,7=(INT((Assumptions!$B$68-1)/12)+1)),(Refinance!$B$11+Refinance!$B$13+Refinance!$B$12*((Assumptions!$B$58*A12)/Acquisition!$B$10)),0)+IF(7=Exit!$B$6,(Exit!$B$9*(1-(Assumptions!$B$77+Assumptions!$B$78))+Exit!$B$12*((Assumptions!$B$58*A12)/Acquisition!$B$10)),0),0) -> 0 | J12: =IF(8<=Exit!$B$6,1*'Equity Returns'!J5+((Assumptions!$B$58*A12)/Acquisition!$B$10)*'Equity Returns'!J6+IF(AND(Assumptions!$B$67=1,8=(INT((Assumptions!$B$68-1)/12)+1)),(Refinance!$B$11+Refinance!$B$13+Refinance!$B$12*((Assumptions!$B$58*A12)/Acquisition!$B$10)),0)+IF(8=Exit!$B$6,(Exit!$B$9*(1-(Assumptions!$B$77+Assumptions!$B$78))+Exit!$B$12*((Assumptions!$B$58*A12)/Acquisition!$B$10)),0),0) -> 0 | K12: =IF(9<=Exit!$B$6,1*'Equity Returns'!K5+((Assumptions!$B$58*A12)/Acquisition!$B$10)*'Equity Returns'!K6+IF(AND(Assumptions!$B$67=1,9=(INT((Assumptions!$B$68-1)/12)+1)),(Refinance!$B$11+Refinance!$B$13+Refinance!$B$12*((Assumptions!$B$58*A12)/Acquisition!$B$10)),0)+IF(9=Exit!$B$6,(Exit!$B$9*(1-(Assumptions!$B$77+Assumptions!$B$78))+Exit!$B$12*((Assumptions!$B$58*A12)/Acquisition!$B$10)),0),0) -> 0 | L12: =IF(10<=Exit!$B$6,1*'Equity Returns'!L5+((Assumptions!$B$58*A12)/Acquisition!$B$10)*'Equity Returns'!L6+IF(AND(Assumptions!$B$67=1,10=(INT((Assumptions!$B$68-1)/12)+1)),(Refinance!$B$11+Refinance!$B$13+Refinance!$B$12*((Assumptions!$B$58*A12)/Acquisition!$B$10)),0)+IF(10=Exit!$B$6,(Exit!$B$9*(1-(Assumptions!$B$77+Assumptions!$B$78))+Exit!$B$12*((Assumptions!$B$58*A12)/Acquisition!$B$10)),0),0) -> 0 | M12: =IFERROR(IRR(B12:L12),0) -> 0.14042308 | N12: =IFERROR(SUMIF(C12:L12,">0")/(-B12),0) -> 1.6382135
A15: 2. Exit Cap Rate → IRR / Equity Multiple
A16: Exit Cap | B16: Y0 | C16: Y1 | D16: Y2 | E16: Y3 | F16: Y4 | G16: Y5 | H16: Y6 | I16: Y7 | J16: Y8 | K16: Y9 | L16: Y10 | M16: IRR | N16: EM
A17: =Assumptions!$B$12+-0.015 -> 0.05 | B17: =-Acquisition!$B$23 -> -600100 | C17: =IF(1<=Exit!$B$6,1*'Equity Returns'!C5+1*'Equity Returns'!C6+IF(AND(Assumptions!$B$67=1,1=(INT((Assumptions!$B$68-1)/12)+1)),Refinance!$B$14,0)+IF(1=Exit!$B$6,(Exit!$B$7/A17*(1-(Assumptions!$B$77+Assumptions!$B$78))+Exit!$B$12),0),0) -> 22074.913 | D17: =IF(2<=Exit!$B$6,1*'Equity Returns'!D5+1*'Equity Returns'!D6+IF(AND(Assumptions!$B$67=1,2=(INT((Assumptions!$B$68-1)/12)+1)),Refinance!$B$14,0)+IF(2=Exit!$B$6,(Exit!$B$7/A17*(1-(Assumptions!$B$77+Assumptions!$B$78))+Exit!$B$12),0),0) -> 60285.638 | E17: =IF(3<=Exit!$B$6,1*'Equity Returns'!E5+1*'Equity Returns'!E6+IF(AND(Assumptions!$B$67=1,3=(INT((Assumptions!$B$68-1)/12)+1)),Refinance!$B$14,0)+IF(3=Exit!$B$6,(Exit!$B$7/A17*(1-(Assumptions!$B$77+Assumptions!$B$78))+Exit!$B$12),0),0) -> 672056.07 | F17: =IF(4<=Exit!$B$6,1*'Equity Returns'!F5+1*'Equity Returns'!F6+IF(AND(Assumptions!$B$67=1,4=(INT((Assumptions!$B$68-1)/12)+1)),Refinance!$B$14,0)+IF(4=Exit!$B$6,(Exit!$B$7/A17*(1-(Assumptions!$B$77+Assumptions!$B$78))+Exit!$B$12),0),0) -> 23248.685 | G17: =IF(5<=Exit!$B$6,1*'Equity Returns'!G5+1*'Equity Returns'!G6+IF(AND(Assumptions!$B$67=1,5=(INT((Assumptions!$B$68-1)/12)+1)),Refinance!$B$14,0)+IF(5=Exit!$B$6,(Exit!$B$7/A17*(1-(Assumptions!$B$77+Assumptions!$B$78))+Exit!$B$12),0),0) -> 1388464.2 | H17: =IF(6<=Exit!$B$6,1*'Equity Returns'!H5+1*'Equity Returns'!H6+IF(AND(Assumptions!$B$67=1,6=(INT((Assumptions!$B$68-1)/12)+1)),Refinance!$B$14,0)+IF(6=Exit!$B$6,(Exit!$B$7/A17*(1-(Assumptions!$B$77+Assumptions!$B$78))+Exit!$B$12),0),0) -> 0 | I17: =IF(7<=Exit!$B$6,1*'Equity Returns'!I5+1*'Equity Returns'!I6+IF(AND(Assumptions!$B$67=1,7=(INT((Assumptions!$B$68-1)/12)+1)),Refinance!$B$14,0)+IF(7=Exit!$B$6,(Exit!$B$7/A17*(1-(Assumptions!$B$77+Assumptions!$B$78))+Exit!$B$12),0),0) -> 0 | J17: =IF(8<=Exit!$B$6,1*'Equity Returns'!J5+1*'Equity Returns'!J6+IF(AND(Assumptions!$B$67=1,8=(INT((Assumptions!$B$68-1)/12)+1)),Refinance!$B$14,0)+IF(8=Exit!$B$6,(Exit!$B$7/A17*(1-(Assumptions!$B$77+Assumptions!$B$78))+Exit!$B$12),0),0) -> 0 | K17: =IF(9<=Exit!$B$6,1*'Equity Returns'!K5+1*'Equity Returns'!K6+IF(AND(Assumptions!$B$67=1,9=(INT((Assumptions!$B$68-1)/12)+1)),Refinance!$B$14,0)+IF(9=Exit!$B$6,(Exit!$B$7/A17*(1-(Assumptions!$B$77+Assumptions!$B$78))+Exit!$B$12),0),0) -> 0 | L17: =IF(10<=Exit!$B$6,1*'Equity Returns'!L5+1*'Equity Returns'!L6+IF(AND(Assumptions!$B$67=1,10=(INT((Assumptions!$B$68-1)/12)+1)),Refinance!$B$14,0)+IF(10=Exit!$B$6,(Exit!$B$7/A17*(1-(Assumptions!$B$77+Assumptions!$B$78))+Exit!$B$12),0),0) -> 0 | M17: =IFERROR(IRR(B17:L17),0) -> 0.37223857 | N17: =IFERROR(SUMIF(C17:L17,">0")/(-B17),0) -> 3.6096142
